Workbook
Name print_area_mi2: #REF!
Name print_area_mi2: #REF!
Name サイズ: [1]凡例!$C$2:$C$4
Name 工事件名１: [1]凡例!$D$2:$D$25
Name 工事件名２: [1]凡例!$E$2:$E$25
Name 他支所名: [1]凡例!$B$3:$B$28
Name 多摩７５０管理図: #REF!
Name 多摩７５０管理図: #REF!
Name 多摩７５０管理図２: #REF!
Name 多摩７５０管理図２: #REF!
Name 年号: [1]凡例!$A$3:$A$4

Sheet ISO台帳(多)
A1: 整理番号 | B1: 受注日 | C1: 受注月 | D1: 受注番号 | E1: 工事番号 | F1: ＮＣ区分 | G1: 担当者 | H1: 工 事 場 所 | I1: 住所（行政区） | J1: 件名 | K1: 件名区分 | L1: 現場日 | M1: 顧客引渡 実施日 | N1: 納品月 | O1: 繁閑調整 | P1: 委託業者名(外注) | Q1: 外注納品 実施日 | R1: 外注支払月 | S1: 外注費 | T1: 委託業者名(外注)2 | U1: 外注発注日2 | V1: 外注納品 予定日2 | W1: 外注納品 実施日2 | X1: 部門長2 | Y1: 外注支払月2 | Z1: 外注費2 | AA1: 入金月 | AB1: 請求書発行番号 | AC1: 入金月（月のみ） | AD1: 事務所/分室 | AE1: 精算 グループ | AF1: 金額 | AG1: 精算延長 | AH1: 繁閑調整金 | AI1: 列1 | AN1: =SUM(AG:AG) -> 26922
A2: 1 | B2: 44943 | C2: 1 | D2: 230733 | E2: 313- | F2: 多摩 | G2: 森田 雄次 | H2: 立川市栄町3-24 | I2: 立川市 | J2: 入取替 | K2: 1 | L2: 済み | M2: 45789 | N2: 5 | AB2: 20038437
A3: 2 | B3: 44426 | C3: 8 | D3: 231196 | E3: 311-242018X | F3: 西部 | G3: 今村 公人 | H3: 調布市布田2-43 | I3: 調布市 | J3: 入取替 | K3: 2 | L3: 済み | M3: 45561 | N3: 9 | AA3: 25.6 | AB3: 10013732 | AC3: 6 | AE3: 35 | AF3: 405178 | AG3: 205
A4: 3 | B4: 44426 | C4: 8 | D4: 231197 | E4: 311-242017X | F4: 西部 | G4: 今村 公人 | H4: 調布市布田2-21 | I4: 調布市 | J4: 入取替 | K4: 3 | L4: 済み | M4: 45714 | N4: 2 | AA4: 25.6 | AB4: 10013731 | AC4: 6 | AE4: 35 | AF4: 285695 | AG4: 219
A5: 4 | B5: 45210 | C5: 10 | D5: 330379 | E5: 313-386726A | F5: 多摩 | G5: 下川原 聡 | H5: 国分寺市西恋ヶ窪1-27 | I5: 国分寺 | J5: 他受（道路） | K5: 4 | L5: 済み | M5: 45806 | N5: 5 | AA5: 25.8 | AB5: 30027118 | AC5: 8 | AE5: 35 | AF5: 235960 | AG5: 60
A6: 5 | B6: 45210 | C6: 10 | D6: 330390 | E6: 311-142008X | F6: 西部 | G6: 早川 浩太郎 | H6: 調布市小島町1-8 | I6: 調布市 | J6: 占用位置変更 | K6: 5 | L6: 済み | M6: 45597 | N6: 11 | AB6: 30027456
A7: 6 | B7: 45216 | C7: 10 | D7: 330396 | E7: 313-特殊見積 | F7: 多摩 | G7: 上松 一雄 | H7: 東大和市高木3-270 | I7: 東大和 | J7: 奈良橋川仮設検討 | K7: 6 | L7: 済み | M7: 保留 | T7: 上松 | U7: 45800 | V7: 45868 | W7: 45965 | X7: 5/23蓮見 | Y7: 25.11 | AA7: 25.12 | AB7: 30041042 | AC7: 12 | AE7: 35 | AF7: 1881952 | AG7: 718
A8: 7 | B8: 45264 | C8: 12 | D8: 330525 | E8: 313-486716A | F8: 多摩 | G8: 今村 公人 | H8: 東大和市上北台1-1066 | I8: 東大和 | J8: 他受（道路） | K8: 7 | L8: 済み | M8: 45790 | N8: 5 | AA8: 25.9 | AB8: 30034488 | AC8: 9 | AE8: 35 | AF8: 294195 | AG8: 22
A9: 8 | B9: 45285 | C9: 12 | D9: 330604 | E9: 313-486721C | F9: 多摩 | G9: 早川 浩太郎 | H9: 東村山市本町1-16 | I9: 東村山 | J9: 他受（道路・線路上マンション立ち退き後） | K9: 8 | L9: 済み | M9: 45595 | N9: 10 | AB9: 30037695
A10: 9 | B10: 45315 | C10: 1 | D10: 330667 | E10: 313-443032X | F10: 多摩 | G10: 吉田 真人 | H10: 小平市花小金井1-17 | I10: 小平市 | J10: 入取替 | K10: 9 | L10: 済み | M10: 45875 | N10: 8 | O10: 神奈川 | AA10: 25.8 | AB10: 30040336 | AC10: 8 | AE10: 40 | AF10: 247191 | AG10: 57 | AH10: 247191
A11: 10 | B11: 45315 | C11: 1 | D11: 330668 | E11: 313-443033X | F11: 多摩 | G11: 上野 謙二 | H11: 小平市小川西町3-12 | I11: 小平市 | J11: 入取替 | K11: 10 | L11: 済み | T11: 上野 | U11: 45450 | V11: 45534 | X11: 6/7蓮見 | AB11: 30040333
A12: 11 | B12: 45315 | C12: 1 | D12: 330669 | E12: 313-443034X | F12: 多摩 | G12: 上野 謙二 | H12: 小平市仲町291 | I12: 小平市 | J12: 入取替 | K12: 11 | L12: 済み | T12: 上野 | U12: 45542 | V12: 45534 | X12: 9/7蓮見 | AB12: 30040331
A13: 12 | B13: 45327 | C13: 2 | D13: 330698 | E13: 313-443015X | F13: 多摩 | G13: 堀田 正法 | H13: 八王子市めじろ台1-41 | I13: 八王子 | J13: 入取替 | K13: 12 | L13: 済み | M13: 45959 | N13: 10 | AA13: 25.10 | AB13: 30042237 | AC13: 10 | AE13: 40 | AF13: 211789 | AG13: 52
A14: 13 | B14: 45327 | C14: 2 | D14: 330702 | E14: 313-443038X | F14: 多摩 | G14: 若林 実 | H14: 国分寺市泉町1-10 | I14: 国分寺 | J14: 入取替 | K14: 13 | L14: 済み | P14: 若林 | AB14: 30042241
A15: 14 | B15: 45327 | C15: 2 | D15: 330703 | E15: 313-443048X | F15: 多摩 | G15: 立川 太貴 | H15: 東大和市南街2-101 | I15: 東大和 | J15: 入取替 | K15: 14 | L15: 済み | M15: 45874 | N15: 8 | AB15: 30042193
A16: 15 | B16: 45327 | C16: 2 | D16: 330705 | E16: 313-443044X | F16: 多摩 | G16: 小林 哲也 | H16: 国立市西2-3 | I16: 国立市 | J16: 入取替 | K16: 15 | L16: 済み | AB16: 30042262
A17: 16 | B17: 45327 | C17: 2 | D17: 330706 | E17: 313-443043X | F17: 多摩 | G17: 若林 実 | H17: 国立市中1-14 | I17: 国立市 | J17: 入取替 | K17: 16 | L17: 済み | P17: 若林 | AB17: 30042265
A18: 17 | B18: 45327 | C18: 2 | D18: 330708 | E18: 313-443049X | F18: 多摩 | G18: 堀田 正法 | H18: 東村山市萩山町2-20 | I18: 東村山 | J18: 入取替 | K18: 17 | L18: 済み | AB18: 30042270
A19: 18 | B19: 45330 | C19: 2 | D19: 330725 | E19: 313-443039X | F19: 多摩 | G19: 森田 雄次 | H19: 国分寺市東元町2-14 | I19: 国分寺 | J19: 入取替 | K19: 18 | L19: 済み | M19: 45735 | N19: 3 | P19: 望月 | Q19: 45380 | R19: 24.3 | AA19: 25.6 | AB19: 50014381 | AC19: 6 | AE19: 35 | AF19: 376749 | AG19: 164
A20: 19 | B20: 45330 | C20: 2 | D20: 330726 | E20: 313-443040X | F20: 多摩 | G20: 森田 雄次 | H20: 国分寺市東元町2-7 | I20: 国分寺 | J20: 入取替 | K20: 19 | L20: 済み | M20: 45742 | N20: 3 | P20: 望月 | Q20: 45380 | R20: 24.3 | AA20: 25.6 | AB20: 50014379 | AC20: 6 | AE20: 35 | AF20: 389123 | AG20: 162
A21: 20 | B21: 45366 | C21: 3 | D21: 330855 | E21: 313-特殊見積 | F21: 多摩 | G21: 森田 雄次 | H21: 日野市程久保895 | I21: 日野市 | J21: 橋梁構造確認 | K21: 20 | L21: 済み | M21: 45387 | N21: 4 | AA21: 24.5 | AB21: 30047922 | AC21: 5
A22: 21 | B22: 45413 | C22: 5 | D22: 330939 | E22: 313-471713X | F22: 多摩 | G22: 森田 雄次 | H22: 多摩市関戸5-16 | I22: 多摩市 | J22: 他受（水道） | K22: 21 | L22: 済み | M22: 45842 | N22: 7 | AA22: 25.8 | AB22: 40016344 | AC22: 8 | AE22: 35 | AF22: 387826 | AG22: 57
A23: 22 | B23: 45446 | C23: 6 | D23: 430005 | E23: 313-419058X | F23: 多摩 | G23: 立川 太貴 | H23: 八王子市大和田町4-25 | I23: 八王子 | J23: 変更 | K23: 22 | L23: 済み | M23: 45447 | N23: 6 | AB23: 40039408
A24: 23 | B24: 45453 | C24: 6 | D24: 430040 | E24: 313-443051X | F24: 多摩 | G24: 今村 公人 | H24: 国分寺市東元町3-21-42 | I24: 国分寺 | J24: 入取替 | K24: 23 | L24: 済み | M24: 保留 | AB24: 40040658
A25: 24 | B25: 45455 | C25: 6 | D25: 430052 | E25: 313-419088X | F25: 多摩 | G25: 小林 哲也 | H25: 八王子市館町522 都 | I25: 八王子 | J25: 需要 | K25: 24 | L25: 済み | M25: 45870 | N25: 8 | AA25: 25.9 | AB25: 40041401 | AC25: 9 | AE25: 35 | AF25: 423726 | AG25: 300
A26: 25 | B26: 45457 | C26: 6 | D26: 430061 | E26: 313-476802A | F26: 多摩 | G26: 今村 公人 | H26: 八王子市館町1879 | I26: 八王子 | J26: 他受・本設戻し | K26: 25 | L26: 済み | P26: 日鉄 | Q26: 45891 | R26: 25.9 | S26: 280000 | AB26: 40041471
A27: 26 | B27: 45470 | C27: 6 | D27: 430097 | E27: 313-541017X | F27: 多摩 | G27: 小林 哲也 | H27: 小平市大沼町4-43 | I27: 小平市 | J27: 入取替（CCB事業中） | K27: 26 | L27: 済み | AB27: 40043649
A28: 27 | B28: 45469 | C28: 6 | D28: 430106 | E28: 313-541004X | F28: 多摩 | G28: 今村 公人 | H28: 八王子市中野上町5-1 | I28: 八王子 | J28: 入取替（DG） | K28: 27 | L28: 済み | M28: 45730 | N28: 3 | AB28: 40043488
A29: 28 | B29: 45469 | C29: 6 | D29: 430107 | E29: 313-541005X | F29: 多摩 | G29: 今村 公人 | H29: 八王子市中野上町5-5 | I29: 八王子 | J29: 入取替（DG） | K29: 28 | L29: 済み | AB29: 40043490
A30: 29 | B30: 45469 | C30: 6 | D30: 430108 | E30: 313-541007X | F30: 多摩 | G30: 若林 実 | H30: 八王子市中野上町4-43 | I30: 八王子 | J30: 入取替（DG） | K30: 29 | L30: 済み | M30: 45716 | N30: 2 | P30: 若林 | Q30: 45716 | R30: 25.2 | AB30: 40043491
A31: 30 | B31: 45469 | C31: 6 | D31: 430109 | E31: 313-541008X | F31: 多摩 | G31: 下川原 聡 | H31: 八王子市中野上町4-40 | I31: 八王子 | J31: 入取替（DG） | K31: 30 | L31: 済み | M31: 45702 | N31: 2 | AA31: 26.1 | AB31: 40043493 | AC31: 1 | AE31: 35 | AF31: 395407 | AG31: 137
A32: 31 | B32: 45469 | C32: 6 | D32: 430111 | E32: 313-541011X | F32: 多摩 | G32: 小林 哲也 | H32: 八王子市中野山王3-1 | I32: 八王子 | J32: 入取替（DG） | K32: 31 | L32: 済み | M32: 45719 | N32: 3 | AB32: 40043498
A33: 32 | B33: 45469 | C33: 6 | D33: 430112 | E33: 313-541012X | F33: 多摩 | G33: 今津 輝 | H33: 八王子市中野山王3-18 | I33: 八王子 | J33: 入取替（DG） | K33: 32 | L33: 済み | M33: 45735 | N33: 3 | T33: 今津 | U33: 45539 | V33: 45626 | W33: 45735 | X33: 9/4蓮見 | AB33: 40043500
A34: 33 | B34: 45469 | C34: 6 | D34: 430113 | E34: 313-541013X | F34: 多摩 | G34: 今津 輝 | H34: 八王子市中野山王3-20 | I34: 八王子 | J34: 入取替（DG） | K34: 33 | L34: 済み | M34: 45735 | N34: 3 | T34: 今津 | U34: 45539 | V34: 45626 | W34: 45735 | X34: 9/4蓮見 | AB34: 40043503
A35: 34 | B35: 45469 | C35: 6 | D35: 430114 | E35: 313-541014X | F35: 多摩 | G35: 三日尻 道男 | H35: 八王子市大和田町6-12 | I35: 八王子 | J35: 入取替（DG） | K35: 34 | L35: 済み | M35: 45723 | N35: 3 | AA35: 26.2 | AB35: 40043506 | AC35: 2 | AE35: 35 | AF35: 603682 | AG35: 240
A36: 35 | B36: 45469 | C36: 6 | D36: 430115 | E36: 313-541015X | F36: 多摩 | G36: 堀田 正法 | H36: 八王子市台町3-19 | I36: 八王子 | J36: 入取替（DG） | K36: 35 | L36: 済み | M36: 45707 | N36: 2 | AA36: 25.12 | AB36: 40043508 | AC36: 12 | AE36: 35 | AF36: 335532 | AG36: 69
A37: 36 | B37: 45477 | C37: 7 | D37: 430127 | E37: 313-443054X | F37: 多摩 | G37: 立川 太貴 | H37: 東村山市青葉町2-5 | I37: 東村山 | J37: 入取替 | K37: 36 | L37: 済み | M37: 45898 | N37: 8 | P37: 望月 | Q37: 45826 | R37: 25.6 | AA37: 26.1 | AB37: 40044701 | AC37: 1 | AE37: 35 | AF37: 1158817 | AG37: 453
A38: 37 | B38: 45484 | C38: 7 | D38: 430191 | E38: 313-541020F | F38: 多摩 | G38: 下川原 聡 | H38: 国分寺市東元町2-20 | I38: 国分寺 | J38: 入取替（DG） | K38: 37 | L38: 済み | M38: 45614 | N38: 11 | AA38: 25.8 | AB38: 40045739 | AC38: 8 | AE38: 301 | AF38: 426843 | AG38: 159
A39: 38 | B39: 45506 | C39: 8 | D39: 430193 | E39: 313-186724X | F39: 多摩 | G39: 今村 公人 | H39: 八王子市館町1097-15 | I39: 八王子 | J39: バルブかさ上げ申請 | K39: 38 | L39: 済み | M39: 保留 | AB39: 40048094
A40: 39 | B40: 45510 | C40: 8 | D40: 430199 | E40: 313-586717X | F40: 多摩 | G40: 今村 公人 | H40: 八王子市大船町182 | I40: 八王子 | J40: 他受（無償） | K40: 39 | AB40: 40048340
A41: 40 | B41: 45544 | C41: 9 | D41: 430269 | E41: 313-343060X | F41: 多摩 | G41: 小林 哲也 | H41: 八王子市子安町2-31 | I41: 八王子 | J41: TTLに変更 | K41: 40 | L41: 済み | M41: 45586 | N41: 10 | AA41: 25.9 | AB41: 40051964 | AC41: 9 | AE41: 35 | AF41: 63379
A42: 41 | B42: 45545 | C42: 9 | D42: 430277 | E42: 313-486721B | F42: 多摩 | G42: 早川 浩太郎 | H42: 東村山市本町2-21 | I42: 東村山 | J42: 断面図変更 | K42: 41 | L42: 済み | M42: 45546 | N42: 9 | AB42: 40052056
A43: 42 | B43: 45546 | C43: 9 | D43: 430280 | E43: 313-309401X | F43: 多摩 | G43: 今村 公人 | H43: 八王子市左入町684 | I43: 八王子 | J43: NADF | K43: 42 | L43: 済み | M43: 45552 | N43: 9 | AB43: 40052132
A44: 43 | B44: 45546 | C44: 9 | D44: 430281 | E44: 313-474719A | F44: 多摩 | G44: 上野 謙二 | H44: 日野市東平山2-14 | I44: 日野市 | J44: 西平山区画整理（他受） | K44: 43 | L44: 済み | M44: 45862 | N44: 7 | T44: 上野 | U44: 45546 | V44: 45596 | W44: 45862 | X44: 9/11蓮見 | Y44: 25.8 | AA44: 25.8 | AB44: 40052157 | AC44: 8 | AE44: 35 | AF44: 316764 | AG44: 11
A45: 44 | B45: 45552 | C45: 9 | D45: 430291 | E45: 313-533001X | F45: 多摩 | G45: 小林 哲也 | H45: 立川市西砂町1-70 | I45: 立川市 | J45: 供A | K45: 44 | L45: 済み | M45: 45926 | N45: 9 | AA45: 25.10 | AB45: 40052570 | AC45: 10 | AE45: 35 | AF45: 308514 | AG45: 201
A46: 45 | B46: 45552 | C46: 9 | D46: 430298 | E46: 313-531003X | F46: 多摩 | G46: 今村 公人 | H46: 立川市富士見町5-19 | I46: 立川市 | J46: 供A | K46: 45 | L46: 済み | M46: 45625 | N46: 11 | AB46: 40052586
A47: 46 | B47: 45582 | C47: 10 | D47: 430368 | E47: 313-535006X | F47: 多摩 | G47: 上野 謙二 | H47: 八王子市石川町2605 | I47: 八王子 | J47: 供A | K47: 47 | L47: 済み | M47: 保留 | T47: 上野 | U47: 45947 | V47: 45990 | X47: 10/17早川 | AB47: 40056144
A48: 47 | B48: 45593 | C48: 10 | D48: 430388 | E48: 313-671706A | F48: 多摩 | G48: 森田 雄次 | H48: 立川市柴崎町1-1 | I48: 立川市 | J48: 他受（有償） | K48: 48 | L48: 済み | M48: 45716 | N48: 2 | AB48: 40057178
A49: 48 | B49: 45593 | C49: 10 | D49: 430389 | E49: 313-671706X | F49: 多摩 | G49: 森田 雄次 | H49: 立川市柴崎町1-1 | I49: 立川市 | J49: 他受（有償） | K49: 49 | L49: 済み | M49: 45716 | N49: 2 | AA49: 26.2 | AB49: 40057179 | AC49: 2 | AE49: 35 | AF49: 40391
A50: 49 | B50: 45593 | C50: 10 | D50: 430391 | E50: 313-544002X | F50: 多摩 | G50: 小林 哲也 | H50: 八王子市中野上町2-14 | I50: 八王子 | J50: 入取替 | K50: 50 | L50: 済み | M50: 45779 | N50: 5 | AA50: 25.7 | AB50: 40058466 | AC50: 7 | AE50: 35 | AF50: 425678 | AG50: 25
A51: 50 | B51: 45604 | C51: 11 | D51: 430425 | E51: 313-541042X | F51: 多摩 | G51: 若林 実 | H51: 八王子市大和田町4-15 | I51: 八王子 | J51: 入取替（DG） | K51: 51 | L51: 済み | P51: セニア | AB51: 40058430
A52: 51 | B52: 45604 | C52: 11 | D52: 430427 | E52: 313-541041X | F52: 多摩 | G52: 今村 公人 | H52: 八王子市散田町2-60 | I52: 八王子 | J52: 入取替（DG） | K52: 52 | AB52: 40058431
A53: 52 | B53: 45604 | C53: 11 | D53: 430428 | E53: 313-541040X | F53: 多摩 | G53: 今村 公人 | H53: 八王子市台町3-27 | I53: 八王子 | J53: 入取替（DG） | K53: 53 | AB53: 40058434
A54: 53 | B54: 45604 | C54: 11 | D54: 430429 | E54: 313-541039X | F54: 多摩 | G54: 森田 雄次 | H54: 八王子市大和田町4-9 | I54: 八王子 | J54: 入取替（DG） | K54: 54 | M54: 46013 | N54: 12 | P54: 共立 | Q54: 45988 | AB54: 40058435
A55: 54 | B55: 45604 | C55: 11 | D55: 430430 | E55: 313-541038X | F55: 多摩 | G55: 立川 太貴 | H55: 八王子市大和田町4-12 | I55: 八王子 | J55: 入取替（DG） | K55: 55 | AB55: 40058436
A56: 55 | B56: 45604 | C56: 11 | D56: 430431 | E56: 313-541029X | F56: 多摩 | G56: 上野 謙二 | H56: 日野市新井3-1 | I56: 日野市 | J56: 入取替（DG） | K56: 56 | L56: 済み | P56: エリア | AB56: 40058437
A57: 56 | B57: 45604 | C57: 11 | D57: 430432 | E57: 313-541033X | F57: 多摩 | G57: 上野 謙二 | H57: 東大和市清水5-1003 | I57: 東大和 | J57: 入取替（DG） | K57: 57 | L57: 済み | P57: エリア | AB57: 40058520
A58: 57 | B58: 45604 | C58: 11 | D58: 430433 | E58: 313-541037X | F58: 多摩 | G58: 西部 | H58: 小平市喜平町3-3 | I58: 小平市 | J58: 入取替（DG） | K58: 58 | L58: 済み | O58: 西部 | AB58: 40058527
A59: 58 | B59: 45604 | C59: 11 | D59: 430434 | E59: 313-541035X | F59: 多摩 | G59: 上松 一雄 | H59: 小平市花小金井3-43 | I59: 小平市 | J59: 入取替（DG） | K59: 59 | L59: 済み | M59: 45959 | N59: 10 | P59: セニア | Q59: 45959 | R59: 25.10 | AB59: 40058530
A60: 59 | B60: 45604 | C60: 11 | D60: 430435 | E60: 313-541034X | F60: 多摩 | H60: 小平市仲町73 ガバナ出管 | I60: 小平市 | J60: 入取替（DG） | K60: 60 | AB60: 40058531
A61: 60 | B61: 45604 | C61: 11 | D61: 430436 | E61: 313-541027X | F61: 多摩 | G61: 森田 雄次 | H61: 小平市上水南町2-15 都道 | I61: 小平市 | J61: 入取替（DG） | K61: 61 | P61: 共立 | Q61: 45988 | AB61: 40058532
A62: 61 | B62: 45604 | C62: 11 | D62: 430437 | E62: 313-541024X | F62: 多摩 | G62: 西部 | H62: 小平市喜平町3-3 | I62: 小平市 | J62: 入取替（DG） | K62: 62 | L62: 済み | O62: 西部 | AB62: 40058533
A63: 62 | B63: 45607 | C63: 11 | D63: 430441 | E63: 313-541023X | F63: 多摩 | G63: 森田 雄次 | H63: 小平市鈴木町2-729 都道 | I63: 小平市 | J63: 入取替（DG） | K63: 63 | P63: 望月 | Q63: 45897 | AB63: 40058534
A64: 63 | B64: 45607 | C64: 11 | D64: 430443 | E64: 313-541022X | F64: 多摩 | G64: 森田 雄次 | H64: 小平市上水南町2-15 都道 | I64: 小平市 | J64: 入取替（DG） | K64: 64 | P64: 共立 | Q64: 45988 | AB64: 40058535
A65: 64 | B65: 45607 | C65: 11 | D65: 430444 | E65: 313-541051X | F65: 多摩 | G65: 西部 | H65: 多摩市和田1261 | I65: 多摩市 | J65: 入取替（DG） | K65: 65 | L65: 済み | O65: 西部 | AB65: 40058616
A66: 65 | B66: 45607 | C66: 11 | D66: 430445 | E66: 313-541048X | F66: 多摩 | G66: 西部 | H66: 国立市東3-16 | I66: 国立市 | J66: 入取替（DG） | K66: 66 | L66: 済み | O66: 西部 | AB66: 40058621
A67: 66 | B67: 45607 | C67: 11 | D67: 430446 | E67: 313-541047X | F67: 多摩 | G67: 西部 | H67: 国立市北2-7 | I67: 国立市 | J67: 入取替（DG） | K67: 67 | L67: 済み | O67: 西部 | AB67: 40058622
A68: 67 | B68: 45607 | C68: 11 | D68: 430447 | E68: 313-541049X | F68: 多摩 | G68: 若林 実 | H68: 立川市若葉町2-45 | I68: 立川市 | J68: 入取替（DG） | K68: 68 | L68: 済み | P68: セニア | AB68: 40058763
A69: 68 | B69: 45607 | C69: 11 | D69: 430448 | E69: 313-541030X | F69: 多摩 | G69: 西部 | H69: 東村山市美住町1-13 | I69: 東村山 | J69: 入取替（DG） | K69: 69 | L69: 済み | O69: 西部 | AB69: 40058766
A70: 69 | B70: 45608 | C70: 11 | D70: 430451 | E70: 313-541031X | F70: 多摩 | G70: 西部 | H70: 東村山市富士見町1-14 | I70: 東村山 | J70: 入取替（DG） | K70: 70 | L70: 済み | O70: 西部 | AB70: 40058767
A71: 70 | B71: 45608 | C71: 11 | D71: 430452 | E71: 313-541032X | F71: 多摩 | G71: 西部 | H71: 東村山市美住町1-4 | I71: 東村山 | J71: 入取替（DG） | K71: 71 | L71: 済み | O71: 西部 | AB71: 40058768
A72: 71 | B72: 45608 | C72: 11 | D72: 430455 | E72: 313-541036X | F72: 多摩 | G72: 西部 | H72: 小平市喜平町3-2 | I72: 小平市 | J72: 入取替（DG） | K72: 72 | L72: 済み | O72: 西部 | AB72: 40058528
A73: 72 | B73: 45609 | C73: 11 | D73: 430456 | E73: 313-541050X | F73: 多摩 | G73: 若林 実 | H73: 立川市羽衣町1-4 | I73: 立川市 | J73: 入取替（DG） | K73: 73 | L73: 済み | P73: セニア | AB73: 40058762
A74: 73 | B74: 45614 | C74: 11 | D74: 430464 | E74: 313-541052X | F74: 多摩 | G74: 森田 雄次 | H74: 国分寺市日吉町3-3 | I74: 国分寺 | J74: 入取替（DG） | K74: 74 | P74: 共立 | Q74: 45999 | AB74: 40059959
A75: 74 | B75: 45614 | C75: 11 | D75: 430465 | E75: 313-541053X | F75: 多摩 | G75: 若林 実 | H75: 国分寺市戸倉4-41 | I75: 国分寺 | J75: 入取替（DG） | K75: 75 | L75: 済み | P75: セニア | AB75: 40059958
A76: 75 | B76: 45614 | C76: 11 | D76: 430466 | E76: 313-541054X | F76: 多摩 | G76: 三日尻 道男 | H76: 国分寺市東戸倉2-3 | I76: 国分寺 | J76: 入取替（DG） | K76: 76 | AB76: 40059957
A77: 76 | B77: 45614 | C77: 11 | D77: 430467 | E77: 313-541055X | F77: 多摩 | G77: 森田 雄次 | H77: 国分寺市富士本3-51 | I77: 国分寺 | J77: 入取替（DG） | K77: 77 | P77: 望月 | Q77: 45897 | AB77: 40059956
A78: 77 | B78: 45614 | C78: 11 | D78: 430468 | E78: 313-541056X | F78: 多摩 | G78: 立川 太貴 | H78: 国分寺市戸倉3-28 | I78: 国分寺 | J78: 入取替（DG） | K78: 78 | AB78: 40059955
A79: 78 | B79: 45622 | C79: 11 | D79: 430471 | E79: 313-541028X | F79: 多摩 | G79: 立川 太貴 | H79: 国分寺市戸倉1-7 | I79: 国分寺 | J79: 入取替（DG） | K79: 79 | AB79: 40060597
A80: 79 | B80: 45623 | C80: 11 | D80: 430476 | E80: 313-541026X | F80: 多摩 | G80: 立川 太貴 | H80: 国分寺市西恋ヶ窪1-46 | I80: 国分寺 | J80: 入取替（DG） | K80: 80 | AB80: 40060713
A81: 80 | B81: 45623 | C81: 11 | D81: 430477 | E81: 313-541025X | F81: 多摩 | G81: 小林 哲也 | H81: 国分寺市戸倉2-5 | I81: 国分寺 | J81: 入取替（DG） | K81: 81 | AB81: 40060723
A82: 81 | B82: 45631 | C82: 12 | D82: 430497 | E82: 313-541064X | F82: 多摩 | G82: 西部 | H82: 多摩市和田1261 | I82: 多摩市 | J82: 入取替（DG） | K82: 82 | L82: 済み | O82: 西部 | AB82: 40061775
A83: 82 | B83: 45631 | C83: 12 | D83: 430498 | E83: 313-541068X | F83: 多摩 | H83: 日野市落川334 ガバナ | I83: 日野市 | J83: 入取替（DG） | K83: 83 | AB83: 40063910
A84: 83 | B84: 45631 | C84: 12 | D84: 430499 | E84: 313-541058X | F84: 多摩 | H84: 八王子市台町3-28 ガバナ | I84: 八王子 | J84: 入取替（DG） | K84: 84 | AB84: 40061768
A85: 84 | B85: 45631 | C85: 12 | D85: 430500 | E85: 313-541061X | F85: 多摩 | G85: 山田 敏雄 | H85: 八王子市明神町2-20 国道 | I85: 八王子 | J85: 入取替（DG） | K85: 85 | AB85: 40063904
A86: 85 | B86: 45631 | C86: 12 | D86: 430501 | E86: 313-541059X | F86: 多摩 | G86: 小林 哲也 | H86: 八王子市大和田町5-2 一部国道 | I86: 八王子 | J86: 入取替（DG） | K86: 86 | AB86: 40063903
A87: 86 | B87: 45637 | C87: 12 | D87: 430507 | E87: 313-541066X | F87: 多摩 | G87: 上野 謙二 | H87: 日野市日野本町5-11 | I87: 日野市 | J87: 入取替（DG） | K87: 87 | L87: 済み | P87: エリア | AB87: 40063906
A88: 87 | B88: 45644 | C88: 12 | D88: 430529 | E88: 313-543001X | F88: 多摩 | G88: 小林 哲也 | H88: 小平市小川町1-759 | I88: 小平市 | J88: 入取替 | K88: 88 | L88: 済み | M88: 45757 | N88: 4 | AB88: 40063258
A89: 88 | B89: 45644 | C89: 12 | D89: 430533 | E89: 313-541065X | F89: 多摩 | G89: 堀田 正法 | H89: 日野市日野台4-4 都道 | I89: 日野市 | J89: 入取替（DG） | K89: 89 | AB89: 40063268
A90: 89 | B90: 45644 | C90: 12 | D90: 430535 | E90: 313-541067X | F90: 多摩 | G90: 今村 公人 | H90: 日野市日野本町4-5 都道 | I90: 日野市 | J90: 入取替（DG） | K90: 90 | AB90: 40063267
A91: 90 | B91: 45644 | C91: 12 | D91: 430536 | E91: 313-541060X | F91: 多摩 | H91: 八王子市富士見町15 ガバナ | I91: 八王子 | J91: 入取替（DG） | K91: 91 | AB91: 40063266
A92: 91 | B92: 45642 | C92: 12 | D92: 430537 | E92: 313-543013X | F92: 多摩 | G92: 三日尻 道男 | H92: 国立市東1-20 | I92: 国立市 | J92: 入取替 | K92: 92 | L92: 済み | M92: 45839 | N92: 7 | AA92: 25.7 | AB92: 40063003 | AC92: 7 | AE92: 40 | AF92: 264540 | AG92: 49
A93: 92 | B93: 45644 | C93: 12 | D93: 430539 | E93: 313-543023X | F93: 多摩 | G93: 河野 友則 | H93: 八王子市明神町4-9 | I93: 八王子 | J93: 入取替 | K93: 93 | AB93: 40062963
A94: 93 | B94: 45644 | C94: 12 | D94: 430540 | E94: 313-543025X | F94: 多摩 | G94: 三日尻 道男 | H94: 八王子市富士見町20 | I94: 八王子 | J94: 入取替 | K94: 94 | L94: 済み | AB94: 40062964
A95: 94 | B95: 45644 | C95: 12 | D95: 430541 | E95: 313-543026X | F95: 多摩 | G95: 上野 謙二 | H95: 八王子市富士見町23 | I95: 八王子 | J95: 入取替 | K95: 95 | L95: 不要 | P95: エリア | AB95: 40062966
A96: 95 | B96: 45644 | C96: 12 | D96: 430545 | E96: 313-543037X | F96: 多摩 | G96: 早川 浩太郎 | H96: 八王子市みつい台1-3 | I96: 八王子 | J96: 入取替 | K96: 96 | AB96: 40062973
A97: 96 | B97: 45644 | C97: 12 | D97: 430546 | E97: 313-543038X | F97: 多摩 | G97: 早川 浩太郎 | H97: 八王子市みつい台1-27 | I97: 八王子 | J97: 入取替 | K97: 97 | AB97: 40062974
A98: 97 | B98: 45644 | C98: 12 | D98: 430547 | E98: 313-543039X | F98: 多摩 | G98: 上野 謙二 | H98: 八王子市丸山町15 | I98: 八王子 | J98: 入取替 | K98: 98 | L98: 不要 | P98: エリア | AB98: 40062975
A99: 98 | B99: 45644 | C99: 12 | D99: 430548 | E99: 313-543042X | F99: 多摩 | G99: 上野 謙二 | H99: 立川市柴崎町3-13 | I99: 立川市 | J99: 入取替 | K99: 99 | L99: 済み | M99: 45832 | N99: 6 | T99: 上野 | U99: 45786 | V99: 45838 | W99: 45832 | X99: 5/9蓮見 | Y99: 25.7 | AA99: 25.7 | AB99: 40062987 | AC99: 7 | AE99: 40 | AF99: 304446 | AG99: 79
A100: 99 | B100: 45645 | C100: 12 | D100: 430549 | E100: 313-543043X | F100: 多摩 | G100: 今村 公人 | H100: 立川市柴崎町3-17 | I100: 立川市 | J100: 入取替 | K100: 100 | AB100: 40062991
...

Sheet ISO台帳(西)
A1: 整理番号 | B1: 受注日 | C1: 受注月 | D1: 受注番号 | E1: 工事番号 | F1: ＮＣ区分 | G1: 担当者 | H1: 工 事 場 所 | I1: 住所（行政区） | J1: 件名 | K1: 件名区分 | L1: 現場日 | M1: 顧客引渡 実施日 | N1: 納品月 | O1: 繁閑調整 | P1: 委託業者名(外注) | Q1: 外注納品 実施日 | R1: 部所長 | S1: 外注支払月 | T1: 外注費 | U1: 委託業者名(外注)2 | V1: 外注発注日2 | W1: 外注納品 予定日2 | X1: 外注納品 実施日2 | Y1: 部所長2 | Z1: 外注支払月2 | AA1: 外注費2 | AB1: 入金月 | AC1: 請求書発行番号 | AD1: 入金月（月のみ） | AE1: 事務所/分室 | AF1: 精算 グループ | AG1: 金額 | AH1: 精算延長 | AI1: 繁閑調整金
A2: 1 | B2: 43920 | C2: 3 | D2: 910835 | E2: 311-077201X | F2: 西部 | G2: 上松 一雄 | H2: 三鷹市牟礼2-5-15 | I2: 三鷹市 | J2: 他受 架管本設 | L2: - | M2: 中止 | V2: 44690 | AB2: - | AC2: 90053007
A3: 2 | B3: 44657 | C3: 4 | D3: 110753 | E3: 311-243011I | F3: 西部 | G3: 茂木 政寛 | H3: 世田谷区下馬1-52 | I3: 世田谷 | J3: 入取替（KF） | L3: - | M3: 45439 | N3: 5 | P3: エステー | Q3: 44736 | R3: 4/28古川 | S3: 22.6 | AC3: 20000545
A4: 3 | B4: 44662 | C4: 4 | D4: 110761 | E4: 311-243061I | F4: 西部 | G4: 鈴木 怜於名 | H4: 世田谷区下馬6-49 | I4: 世田谷 | J4: 入取替（KF） | L4: - | M4: 45433 | N4: 5 | P4: エステー | Q4: 44706 | R4: 4/22古川 | S4: 22.5 | AC4: 20000881
A5: 4 | B5: 44890 | C5: 11 | D5: 210310 | E5: 311-343035X | F5: 西部 | G5: 上松 一雄 | H5: 三鷹市上連雀1-10-4 | I5: 三鷹市 | J5: 入取替（KF） | L5: - | M5: 45531 | N5: 8 | AC5: 20031677
A6: 5 | B6: 44890 | C6: 11 | D6: 210313 | E6: 311-343038X | F6: 西部 | G6: 上松 一雄 | H6: 三鷹市井の頭2-29 | I6: 三鷹市 | J6: 入取替（KF） | L6: - | M6: 45544 | N6: 9 | V6: 45873 | X6: 45897 | Z6: 25.8 0 | AA6: 123888 0 | AC6: 20031681
A7: 6 | B7: 44890 | C7: 11 | D7: 210314 | E7: 311-343039X | F7: 西部 | G7: 上松 一雄 | H7: 三鷹市下連雀4-8 | I7: 三鷹市 | J7: 入取替（KF） | L7: - | M7: 45531 | N7: 8 | AC7: 20031682
A8: 7 | B8: 45082 | C8: 6 | D8: 310008 | E8: 113-442674X | F8: 南部 | G8: 小林 昌志 | H8: 大田区田園調布5-17-22 | I8: 大田区 | J8: 入取替（KF） | M8: 45854 | N8: 7 | P8: 共立 | Q8: 45320 | R8: 12/20古川 | S8: 24.2 | AB8: 25.7 | AC8: 30009457 | AD8: 7 | AF8: 16 | AG8: 262168 | AH8: 170
A9: 8 | B9: 45082 | C9: 6 | D9: 310016 | E9: 113-442689X | F9: 南部 | G9: 小林 昌志 | H9: 大田区山王2-12-2 | I9: 大田区 | J9: 入取替（KF）(区) | M9: 45862 | N9: 7 | P9: 共立 | Q9: 45350 | R9: 1/23古川 | S9: 24.3 | AB9: 25.7 | AC9: 30009336 | AD9: 7 | AF9: 16 | AG9: 175939 | AH9: 52
A10: 9 | B10: 45082 | C10: 6 | D10: 310020 | E10: 113-442694X | F10: 南部 | G10: 小林 昌志 | H10: 大田区大森中2-4-17 | I10: 大田区 | J10: 入取替（KF）(区) | M10: 45869 | N10: 7 | P10: 共立 | Q10: 45350 | R10: 1/23古川 | S10: 24.3 | AB10: 25.8 | AC10: 30009847 | AD10: 8 | AF10: 16 | AG10: 196626 | AH10: 65
A11: 10 | B11: 45121 | C11: 7 | D11: 310170 | E11: 311-142237X | F11: 西部 | G11: 鈴木 怜於名 | H11: 世田谷区南烏山6-25 | I11: 世田谷 | J11: DF 特殊件名20号 | L11: 不要 | M11: 中止 | AC11: 請求なし
A12: 11 | B12: 45323 | C12: 2 | D12: 310791 | E12: 311-443206X | F12: 西部 | G12: 上松 一雄 | H12: 武蔵野市境南町3-4 | I12: 武蔵野 | J12: 入取替（KF） | L12: - | N12: 1 | AC12: 30041918
A13: 12 | B13: 45324 | C13: 2 | D13: 310795 | E13: 311-443202X | F13: 西部 | G13: 上松 一雄 | H13: 三鷹市上連雀2-17 | I13: 三鷹市 | J13: 入取替（KF） | L13: - | M13: 45687 | N13: 1 | AC13: 30042113
A14: 13 | B14: 45324 | C14: 2 | D14: 310796 | E14: 311-443203X | F14: 西部 | G14: 上松 一雄 | H14: 三鷹市井の頭2-34 | I14: 三鷹市 | J14: 入取替（KF） | L14: - | M14: 45735 | N14: 3 | AC14: 30042114
A15: 14 | B15: 45358 | C15: 3 | D15: 310913 | E15: 113-490119X | F15: 南部 | G15: 茂木 政寛 | H15: 大田区上池台2-32-1 | I15: 大田区 | J15: 入取替 | M15: 45504 | N15: 7 | P15: 共立 | Q15: 45398 | R15: 4/2古川 | S15: 24.4 | AB15: - | AC15: 中止・請求なし
A16: 15 | B16: 45370 | C16: 3 | D16: 310943 | E16: 113-541176X | F16: 南部 | G16: 藤田 雄也 | H16: 大田区南雪谷1-19-8 | I16: 大田区 | J16: 入取替（DG） | M16: 45741 | N16: 3 | AB16: 25.12 | AC16: 30048213 | AD16: 12 | AF16: 16 | AG16: 745712 | AH16: 71
A17: 16 | B17: 45422 | C17: 5 | D17: 311086 | E17: 113-Z40063X | F17: 南部 | G17: 藤田 雄也 | H17: 大田区大森西2-20 | I17: 大田区 | J17: 供給改善 概算 | M17: 45866 | N17: 7 | AB17: 25.7 | AC17: 40022462 | AD17: 7 | AF17: 16 | AG17: 108628
A18: 17 | B18: 45426 | C18: 5 | D18: 311096 | E18: 113-Z00154X | F18: 南部 | G18: 古川 智基 | H18: 大田区平和島1-2 | I18: 大田区 | J18: 他受 | M18: 45492 | N18: 7 | P18: 共立 | Q18: 45462 | R18: 5/28古川 | S18: 24.6 | AC18: 40026514
A19: 18 | B19: 45434 | C19: 5 | D19: 311126 | E19: 113-541508X | F19: 南部 | G19: 藤田 雄也 | H19: 大田区西六郷1-5-3 | I19: 大田区 | J19: 入取替（DG）(2025年度施工) (住宅政策本部) | L19: 済 | M19: 46052 | N19: 1 | P19: 共立 | Q19: 45628 | R19: 10/29古川 | S19: 24.12 | AB19: 26.2 | AC19: 40038020 | AD19: 2 | AF19: 16 | AG19: 216867 | AH19: 57
A20: 19 | B20: 45447 | C20: 6 | D20: 410002 | E20: 113-541507X | F20: 南部 | G20: 黒須 雄也 | H20: 大田区西蒲田7-60-9 | I20: 大田区 | J20: 入取替（DG） | M20: 45771 | N20: 4 | P20: 共立 | Q20: 45601 | R20: 9/30古川 | S20: 24.11 | AB20: - | AC20: 中止・請求なし
A21: 20 | B21: 45447 | C21: 6 | D21: 410004 | E21: 113-590023X | F21: 南部 | G21: 古川 智基 | H21: 大田区蒲田3-24-4 | I21: 大田区 | J21: 入取替（DG） | M21: 45869 | N21: 7 | P21: 共立 | Q21: 45628 | R21: 10/29古川 | S21: 24.12 | AB21: 25.8 | AC21: 40039521 | AD21: 8 | AF21: 16 | AG21: 156845 | AH21: 10
A22: 21 | B22: 45447 | C22: 6 | D22: 410005 | E22: 113-590024X | F22: 南部 | G22: 古川 智基 | H22: 大田区羽田4-4-29 | I22: 大田区 | J22: 入取替（DG） | M22: 45866 | N22: 7 | P22: 共立 | Q22: 45643 | R22: 12/2古川 | S22: 24.12 | AB22: 25.7 | AC22: 40039475 | AD22: 7 | AF22: 16 | AG22: 204317 | AH22: 10
A23: 22 | B23: 45461 | C23: 6 | D23: 410040 | E23: 311-541010X | F23: 西部 | G23: 茂木 政寛 | H23: 東久留米市滝山6-2 | I23: 東久留 | J23: 入取替（DG） | L23: - | N23: 1 | P23: 共立 | Q23: 45611 | R23: 9/30古川 | S23: 24.11 | AC23: 40042030
A24: 23 | B24: 45461 | C24: 6 | D24: 410041 | E24: 311-541011X | F24: 西部 | G24: 茂木 政寛 | H24: 東久留米市滝山6-2 | I24: 東久留 | J24: 入取替（DG） | L24: - | N24: 1 | P24: 共立 | Q24: 45611 | R24: 9/30古川 | S24: 24.11 | AC24: 40042029
A25: 24 | B25: 45461 | C25: 6 | D25: 410050 | E25: 311-641019X | F25: 西部 | G25: 鈴木 怜於名 | H25: 東久留米市南沢3-1 | I25: 東久留 | J25: 入取替（DG） | L25: - | M25: 45785 | N25: 5 | P25: 共立 | Q25: 45517 | R25: 7/9古川 | S25: 24.8 | AC25: 40042036
A26: 25 | B26: 45461 | C26: 6 | D26: 410051 | E26: 311-641021X | F26: 西部 | G26: 上松 一雄 | H26: 東久留米市南沢3-10 | I26: 東久留 | J26: 入取替（DG） | L26: - | M26: 45687 | N26: 1 | AC26: 40042038
A27: 26 | B27: 45461 | C27: 6 | D27: 410052 | E27: 311-641028X | F27: 西部 | G27: 小林 昌志 | H27: 東久留米市滝山6-1 | I27: 東久留 | J27: 入取替（DG） | L27: - | M27: 46080 | N27: 2 | P27: 共立 | Q27: 45540 | R27: 7/31古川 | S27: 24.9 | AB27: 26.2 | AC27: 40042039 | AD27: 2 | AF27: 35 | AG27: 263525
A28: 27 | B28: 45461 | C28: 6 | D28: 410053 | E28: 311-641029X | F28: 西部 | G28: 小林 昌志 | H28: 東久留米市滝山6-1 | I28: 東久留 | J28: 入取替（DG） | L28: - | M28: 45721 | N28: 3 | P28: 共立 | Q28: 45540 | R28: 7/31古川 | S28: 24.9 | AC28: 40042041
A29: 28 | B29: 45461 | C29: 6 | D29: 410054 | E29: 311-641030X | F29: 西部 | G29: 小林 昌志 | H29: 東久留米市滝山7-19 | I29: 東久留 | J29: 入取替（DG） | L29: - | M29: 45754 | N29: 4 | P29: 共立 | Q29: 45540 | R29: 7/31古川 | S29: 24.9 | AC29: 40042043
A30: 29 | B30: 45476 | C30: 7 | D30: 410090 | E30: 311-641012F | F30: 西部 | G30: 安藤 嶺 | H30: 東久留米市八幡町3-3 | I30: 東久留 | J30: FLEX | L30: 済 | M30: 45708 | N30: 2 | P30: 共立 | Q30: 45565 | R30: 8/27古川 | S30: 24.10 | AC30: 日鉄P＆E
A31: 30 | B31: 45476 | C31: 7 | D31: 410091 | E31: 311-641014F | F31: 西部 | G31: 安藤 嶺 | H31: 東久留米市滝山4-11 | I31: 東久留 | J31: FLEX | L31: 済 | M31: 45636 | N31: 12 | P31: 共立 | Q31: 45568 | R31: 8/27古川 | S31: 24.10 | AB31: 25.11 | AC31: 日鉄P＆E | AD31: 11 | AF31: 301 | AG31: 405546 | AH31: 153
A32: 31 | B32: 45476 | C32: 7 | D32: 410092 | E32: 311-641016F | F32: 西部 | G32: 茂木 政寛 | H32: 東久留米市前沢5-11 | I32: 東久留 | J32: FLEX | L32: 済 | M32: 45632 | N32: 12 | P32: 共立 | Q32: 45601 | R32: 9/30古川 | S32: 24.11 | AB32: 25.9 | AC32: 日鉄P＆E | AD32: 9 | AF32: 301 | AG32: 434548 | AH32: 231
A33: 32 | B33: 45476 | C33: 7 | D33: 410093 | E33: 311-641018F | F33: 西部 | G33: 鈴木 怜於名 | H33: 東久留米市中央町1-1 | I33: 東久留 | J33: FLEX | L33: 済 | M33: 45625 | N33: 11 | AC33: 日鉄P＆E
A34: 33 | B34: 45476 | C34: 7 | D34: 410094 | E34: 311-641020F | F34: 西部 | G34: 鈴木 怜於名 | H34: 東久留米市南沢3-5 | I34: 東久留 | J34: FLEX | L34: 済 | M34: 45628 | N34: 12 | AC34: 日鉄P＆E
A35: 34 | B35: 45476 | C35: 7 | D35: 410095 | E35: 311-641022F | F35: 西部 | G35: 鈴木 怜於名 | H35: 東久留米市本町4-13 | I35: 東久留 | J35: FLEX | L35: 済 | M35: 45635 | N35: 12 | P35: 共立 | Q35: 45517 | R35: 7/9古川 | S35: 24.8 | AB35: 25.8 | AC35: 日鉄P＆E | AD35: 8 | AF35: 301 | AG35: 516860 | AH35: 227
A36: 35 | B36: 45476 | C36: 7 | D36: 410097 | E36: 311-641032F | F36: 西部 | G36: 茂木 政寛 | H36: 東久留米市本町4-7 | I36: 東久留 | J36: FLEX | L36: 済 | M36: 45642 | N36: 12 | P36: 共立 | Q36: 45505 | R36: 7/9古川 | S36: 24.8 | AC36: 日鉄P＆E
A37: 36 | B37: 45476 | C37: 7 | D37: 410098 | E37: 311-641033F | F37: 西部 | G37: 茂木 政寛 | H37: 東久留米市本町4-9 | I37: 東久留 | J37: FLEX | L37: 済 | M37: 45911 | N37: 9 | P37: 共立 | Q37: 45505 | R37: 7/9古川 | S37: 24.8 | AC37: 日鉄P＆E
A38: 37 | B38: 45482 | C38: 7 | D38: 410124 | E38: 311-641025X | F38: 西部 | G38: 茂木 政寛 | H38: 三鷹市野崎1-3 | I38: 三鷹市 | J38: 入取替（DG） | L38: - | M38: 45687 | N38: 1 | P38: 共立 | Q38: 45567 | R38: 8/27古川 | S38: 24.10 | AC38: 40045342
A39: 38 | B39: 45502 | C39: 7 | D39: 410164 | E39: 311-542032F | F39: 西部 | G39: 茂木 政寛 | H39: 東久留米市小山2-3-4 | I39: 東久留 | J39: FLEX | L39: - | M39: 45639 | N39: 12 | P39: 共立 | Q39: 45596 | R39: 10/15古川 | S39: 24.11 | AB39: 25.10 | AC39: 日鉄P＆E | AD39: 10 | AF39: 301 | AG39: 643253 | AH39: 33
A40: 39 | B40: 45519 | C40: 8 | D40: 410213 | E40: 311-142237X | F40: 西部 | G40: 鈴木 怜於名 | H40: 世田谷区南烏山6-25 | I40: 世田谷 | J40: DF | L40: 不要 | M40: 45800 | N40: 5 | AB40: 25.8 | AC40: 40049285 | AD40: 8 | AF40: 35 | AG40: 84016
A41: 40 | B41: 45527 | C41: 8 | D41: 410232 | E41: 113-533504X | F41: 南部 | G41: 黒須 雄也 | H41: 大田区羽田旭町11-1 | I41: 大田区 | J41: 他受 拡幅 | M41: - | AB41: 25.8 | AC41: 40050052 | AD41: 8 | AF41: 16 | AG41: 61675
A42: 41 | B42: 45565 | C42: 9 | D42: 410310 | E42: 113-542641X | F42: 南部 | G42: 古川 智基 | H42: 大田区大森北6-16-6 | I42: 大田区 | J42: 入取替（KF） | M42: 45733 | N42: 3 | AB42: - | AC42: 中止・請求なし
A43: 42 | B43: 45566 | C43: 10 | D43: 410314 | E43: 311-543257X | F43: 西部 | G43: 茂木 政寛 | H43: 東久留米市小山5-1 | I43: 東久留 | J43: 入取替（KF） 非開削 | L43: - | M43: 中止 | AC43: 40054347
A44: 43 | B44: 45566 | C44: 10 | D44: 410315 | E44: 311-543261X | F44: 西部 | G44: 茂木 政寛 | H44: 東久留米市本町1-6 | I44: 東久留 | J44: 入取替（KF） 非開削 | L44: - | M44: 中止 | AC44: 40054354
A45: 44 | B45: 45567 | C45: 10 | D45: 410316 | E45: 311-543243X | F45: 西部 | G45: 上松 一雄 | H45: 武蔵野市桜堤1-1 | I45: 武蔵野 | J45: 入取替（KF） 非開削 | L45: - | M45: 中止26/3/3 | AC45: 40054435
A46: 45 | B46: 45567 | C46: 10 | D46: 410317 | E46: 311-543244X | F46: 西部 | G46: 上松 一雄 | H46: 武蔵野市関前5-8 | I46: 武蔵野 | J46: 入取替（KF） 非開削 | L46: - | M46: 中止26/3/3 | AC46: 40054463
A47: 46 | B47: 45567 | C47: 10 | D47: 410318 | E47: 311-543245X | F47: 西部 | G47: 上松 一雄 | H47: 武蔵野市関前3-2 | I47: 武蔵野 | J47: 入取替（KF） | L47: - | M47: 45716 | N47: 2 | AC47: 40054471
A48: 47 | B48: 45567 | C48: 10 | D48: 410320 | E48: 311-543247X | F48: 西部 | G48: 上松 一雄 | H48: 武蔵野市境南町1-2 | I48: 武蔵野 | J48: 入取替（KF） 非開削 | L48: - | M48: 中止26/3/3 | AC48: 40054457
A49: 48 | B49: 45567 | C49: 10 | D49: 410321 | E49: 311-543248X | F49: 西部 | G49: 上松 一雄 | H49: 武蔵野市吉祥寺南町3-10 | I49: 武蔵野 | J49: 入取替（KF） 非開削 | L49: - | M49: 中止26/3/3 | AC49: 40054465
A50: 49 | B50: 45567 | C50: 10 | D50: 410322 | E50: 311-543249X | F50: 西部 | G50: 上松 一雄 | H50: 武蔵野市吉祥寺南町3-24 | I50: 武蔵野 | J50: 入取替（KF） | L50: - | M50: 45734 | N50: 3 | AC50: 40054480
A51: 50 | B51: 45567 | C51: 10 | D51: 410323 | E51: 311-543250X | F51: 西部 | G51: 上松 一雄 | H51: 武蔵野市吉祥寺南町3-6 | I51: 武蔵野 | J51: 入取替（KF） | L51: - | M51: 45716 | N51: 2 | U51: セニア | V51: 45931 | X51: 45716 | Z51: 26.2 | AA51: 11164 | AB51: 26.2 | AC51: 40054481 | AD51: 2 | AF51: 35 | AG51: 16539
A52: 51 | B52: 45567 | C52: 10 | D52: 410324 | E52: 311-543251X | F52: 西部 | G52: 上松 一雄 | H52: 武蔵野市吉祥寺本町4-9 | I52: 武蔵野 | J52: 入取替（KF） 非開削× | L52: - | M52: 45744 | N52: 3 | AC52: 40054436
A53: 52 | B53: 45567 | C53: 10 | D53: 410325 | E53: 311-543252X | F53: 西部 | G53: 上松 一雄 | H53: 武蔵野市境1-20 | I53: 武蔵野 | J53: 入取替（KF） 非開削 | L53: - | M53: 中止26/3/3 | AC53: 40054468
A54: 53 | B54: 45567 | C54: 10 | D54: 410326 | E54: 311-543253X | F54: 西部 | G54: 上松 一雄 | H54: 武蔵野市境1-16 | I54: 武蔵野 | J54: 入取替（KF） 非開削 | L54: - | M54: 中止26/3/3 | AC54: 40054447
A55: 54 | B55: 45567 | C55: 10 | D55: 410327 | E55: 311-543254X | F55: 西部 | G55: 上松 一雄 | H55: 武蔵野市関前4-2 | I55: 武蔵野 | J55: 入取替（KF） 非開削 | L55: - | M55: 中止26/3/3 | AC55: 40054445
A56: 55 | B56: 45567 | C56: 10 | D56: 410328 | E56: 311-543255X | F56: 西部 | G56: 上松 一雄 | H56: 武蔵野市西久保1-16 | I56: 武蔵野 | J56: 入取替（KF） 非開削 | L56: - | M56: 中止26/3/3 | AC56: 40054438
A57: 56 | B57: 45567 | C57: 10 | D57: 410329 | E57: 311-543256X | F57: 西部 | G57: 上松 一雄 | H57: 東久留米市幸町3-5 | I57: 東久留 | J57: 入取替（KF） | L57: - | M57: 45734 | N57: 3 | U57: セニア | V57: 45931 | X57: 45981 | Z57: 25.11 | AA57: 5169 | AB57: 25.11 | AC57: 40054482 | AD57: 11 | AF57: 35 | AG57: 7529
A58: 57 | B58: 45567 | C58: 10 | D58: 410330 | E58: 311-543258X | F58: 西部 | G58: 上松 一雄 | H58: 東久留米市本町2-6 | I58: 東久留 | J58: 入取替（KF） | L58: - | M58: 45721 | N58: 3 | U58: セニア | V58: 45931 | X58: 45981 | Z58: 25.11 | AA58: 5169 | AB58: 25.11 | AC58: 40054483 | AD58: 11 | AF58: 35 | AG58: 7529
A59: 58 | B59: 45568 | C59: 10 | D59: 410337 | E59: 113-542644X | F59: 南部 | G59: 古川 智基 | H59: 大田区南馬込1-58-11 | I59: 大田区 | J59: 入取替（KF） | M59: 45721 | N59: 3 | P59: 共立 | Q59: 45685 | R59: 12/23古川 | S59: 25.1 | AB59: - | AC59: 中止・請求なし
A60: 59 | B60: 45571 | C60: 10 | D60: 410344 | E60: 311-543259X | F60: 西部 | G60: 茂木 政寛 | H60: 東久留米市東本町4 | I60: 東久留 | J60: 入取替（KF） 非開削 | L60: - | M60: 中止 | AC60: 40055028
A61: 60 | B61: 45574 | C61: 10 | D61: 410347 | E61: 311-543260X | F61: 西部 | G61: 茂木 政寛 | H61: 東久留米市新川町1-15 | I61: 東久留 | J61: 入取替（KF） 非開削 | L61: - | M61: 中止 | AC61: 40055147
A62: 61 | B62: 45335 | C62: 2 | D62: 410356 | E62: 311-377206X | F62: 西部 | G62: 茂木 政寛 | H62: 武蔵野市吉祥寺北町4-11 | I62: 武蔵野 | J62: 他受 移設 | L62: - | M62: 45576 | N62: 10 | AB62: 25.6 | AC62: 30043239 | AD62: 6 | AF62: 35 | AG62: 70650
A63: 62 | B63: 45614 | C63: 11 | D63: 410440 | E63: 113-575233X | F63: 南部 | G63: 藤田 雄也 | H63: 大田区平和島6-1-1 | I63: 大田区 | J63: 他受 中圧移設 | L63: 済 | M63: 45999 | N63: 12 | P63: 共立 | Q63: 45685 | R63: 12/23古川 | S63: 25.1 | AB63: 25.12 | AC63: 40059923 | AD63: 12 | AF63: 16 | AG63: 599448 | AH63: 66
A64: 63 | B64: 45630 | C64: 12 | D64: 410475 | E64: 311-542032F | F64: 西部 | G64: 茂木 政寛 | H64: 東久留米市小山2-3-4 | I64: 東久留 | J64: 申請業務 | L64: 不要 | M64: 中止 | AC64: 日鉄P＆E
A65: 64 | B65: 45680 | C65: 1 | D65: 410574 | E65: 311-143012I | F65: 西部 | G65: 茂木 政寛 | H65: 世田谷区駒沢2-9 | I65: 世田谷 | J65: 変更 新設口径変更 | L65: 不要 | M65: 45708 | N65: 2 | AC65: 40067173
A66: 65 | B66: 45700 | C66: 2 | D66: 410589 | E66: 311-586300X | F66: 西部 | G66: 鈴木 怜於名 | H66: 三鷹市下連雀6-2-8 | I66: 三鷹市 | J66: 他受 拡幅移設 | L66: - | M66: 45744 | N66: 3 | AB66: 25.7 | AC66: 40069635 | AD66: 7 | AF66: 35 | AG66: 46252
A67: 66 | B67: 45688 | C67: 1 | D67: 410606 | E67: 113-581204X | F67: 南部 | G67: 上松 一雄 | H67: 大田区中央2-11-2 | I67: 大田区 | J67: 他受 拡幅移設 | M67: 45856 | N67: 7 | V67: 45688 | X67: 45856 | Z67: 25.8 | AA67: 211582 | AB67: 25.8 | AC67: 40068271 | AD67: 8 | AF67: 16 | AG67: 329963 | AH67: 21
A68: 67 | B68: 45688 | C68: 1 | D68: 410607 | E68: 113-471219X | F68: 南部 | G68: 古川 智基 | H68: 大田区石川町2-16-10 | I68: 大田区 | J68: 他受 本設計（概算済） | M68: 45797 | N68: 5 | AB68: 25.8 | AC68: 40068278 | AD68: 8 | AF68: 16 | AG68: 231479 | AH68: 42
A69: 68 | B69: 45649 | C69: 12 | D69: 410656 | E69: 313-543003X | F69: 多摩 | G69: 茂木 政寛 | H69: 小平市津田町1-3 | I69: 小平市 | J69: 入取替（KF） | M69: 45757 | N69: 4 | AC69: 40063601
A70: 69 | B70: 45650 | C70: 12 | D70: 410658 | E70: 313-543040X | F70: 多摩 | G70: 古川 智基 | H70: 立川市錦町5-14 | I70: 立川市 | J70: 入取替（KF） | M70: 45758 | N70: 4 | AC70: 40064240
A71: 70 | B71: 45650 | C71: 12 | D71: 410659 | E71: 313-543046X | F71: 多摩 | G71: 黒須 雄也 | H71: 立川市若葉町2-6 | I71: 立川市 | J71: 入取替（KF） | M71: 45755 | N71: 4 | AC71: 40064245
A72: 71 | B72: 45716 | C72: 2 | D72: 410682 | E72: 113-600230X | F72: 南部 | G72: 黒須 雄也 | H72: 大田区田園調布4-43 | I72: 大田区 | J72: 除却 件名もの概算・架管対策 | M72: 45786 | N72: 5 | AB72: 25.7 | AC72: 40071756 | AD72: 7 | AF72: 16 | AG72: 287577 | AH72: 12
A73: 72 | B73: 45720 | C73: 3 | D73: 410687 | E73: 411-442507A | F73: 北部 | G73: 茂木 政寛 | H73: 新座市石神5-5-24 | I73: 新座市 | J73: 入取替（KF） | L73: 済 | M73: 中止 | AC73: 40072086
A74: 73 | B74: 45721 | C74: 3 | D74: 410693 | E74: 113-695375X | F74: 南部 | G74: 藤田 雄也 | H74: 大田区東雪谷2-2 | I74: 大田区 | J74: その他 件名もの・中圧点検 | M74: 45777 | N74: 4 | AB74: 25.6 | AC74: 40072484 | AD74: 6 | AF74: 16 | AG74: 121977
A75: 74 | B75: 45722 | C75: 3 | D75: 410694 | E75: 113-690302X | F75: 南部 | G75: 古川 智基 | H75: 大田区東雪谷3-14-2 | I75: 大田区 | J75: 中圧関連 件名もの・中圧反転 | N75: 1 | AC75: 40072548
A76: 75 | B76: 45733 | C76: 3 | D76: 410716 | E76: 113-676202X | F76: 南部 | G76: 鈴木 怜於名 | H76: 大田区池上1-33-1 | I76: 大田区 | J76: 他受 本設計（概算済） | N76: 1 | AC76: 40074005
A77: 76 | B77: 45734 | C77: 3 | D77: 410724 | E77: 113- | F77: 南部 | G77: 藤田 雄也 | H77: 大田区羽田6-2-3 | I77: 大田区 | J77: 他受 資料精査・作成 | M77: 45813 | N77: 6 | AB77: 25.6 | AC77: 40074321 | AD77: 6 | AF77: 13 | AG77: 181489
A78: 77 | B78: 45735 | C78: 3 | D78: 410733 | E78: 311-443204X | F78: 西部 | G78: 上松 一雄 | H78: 武蔵野市吉祥寺東町3-14 | I78: 武蔵野 | J78: 入取替（KF） | L78: - | M78: 45755 | N78: 4 | AC78: 40074492
A79: 78 | B79: 45735 | C79: 3 | D79: 410734 | E79: 311-443207X | F79: 西部 | G79: 上松 一雄 | H79: 武蔵野市西久保2-15 | I79: 武蔵野 | J79: 入取替（KF） | L79: - | M79: 45755 | N79: 4 | AC79: 40074493
A80: 79 | B80: 45735 | C80: 3 | D80: 410735 | E80: 311-443208X | F80: 西部 | G80: 上松 一雄 | H80: 武蔵野市西久保2-8 | I80: 武蔵野 | J80: 入取替（KF） | L80: - | M80: 45755 | N80: 4 | AC80: 40074494
A81: 80 | B81: 45735 | C81: 3 | D81: 410736 | E81: 311-443209X | F81: 西部 | G81: 上松 一雄 | H81: 武蔵野市西久保2-4 | I81: 武蔵野 | J81: 入取替（KF） | L81: - | M81: 45755 | N81: 4 | AC81: 40074495
A82: 81 | B82: 45735 | C82: 3 | D82: 410737 | E82: 311-343032X | F82: 西部 | G82: 鈴木 怜於名 | H82: 武蔵野市吉祥寺北町4-5 | I82: 武蔵野 | J82: 入取替（KF） | L82: - | N82: 1 | AC82: 40074496
A83: 82 | B83: 45740 | C83: 3 | D83: 410754 | E83: 311-516051X | F83: 西部 | G83: 安藤 嶺 | H83: 東久留米市金山町1-22 | I83: 東久留 | J83: 需要 | L83: 済 | M83: 45777 | N83: 4 | AB83: 25.6 | AC83: 40075028 | AD83: 6 | AF83: 30 | AG83: 243606 | AH83: 57
A84: 83 | B84: 45741 | C84: 3 | D84: 410760 | E84: 311-342142M | F84: 西部 | G84: 茂木 政寛 | H84: 武蔵野市境南町1-3 | I84: 武蔵野 | J84: 変更 休止範囲変更 | L84: 不要 | M84: 45818 | N84: 6 | AB84: 25.8 | AC84: 40074953 | AD84: 8 | AF84: 35 | AG84: 195290
A85: 84 | B85: 45741 | C85: 3 | D85: 410761 | E85: 311-343061X | F85: 西部 | G85: 上松 一雄 | H85: 武蔵野市境南町4-22 | I85: 武蔵野 | J85: 入取替（KF） | L85: - | N85: 1 | AC85: 40074967
A86: 85 | B86: 44657 | C86: 4 | D86: 410777 | E86: 311-243001I | F86: 西部 | G86: 安藤 嶺 | H86: 世田谷区弦巻3-14 | I86: 世田谷 | J86: 入取替（KF） | L86: - | M86: 45590 | N86: 10 | AC86: 20000544
A87: 86 | B87: 44659 | C87: 4 | D87: 410778 | E87: 311-243060I | F87: 西部 | G87: 安藤 嶺 | H87: 世田谷区三宿2-35 | I87: 世田谷 | J87: 入取替（KF） | L87: - | M87: 45590 | N87: 10 | AC87: 20000700
A88: 87 | B88: 44662 | C88: 4 | D88: 410779 | E88: 311-243063I | F88: 西部 | G88: 茂木 政寛 | H88: 世田谷区若林4-27 | I88: 世田谷 | J88: 入取替（KF） | L88: - | M88: 45391 | N88: 4 | AC88: 20000884
A89: 88 | B89: 44662 | C89: 4 | D89: 410780 | E89: 311-243064I | F89: 西部 | G89: 鈴木 怜於名 | H89: 世田谷区太子堂3-19 | I89: 世田谷 | J89: 入取替（KF） | L89: - | M89: 45383 | N89: 4 | AC89: 20000886
A90: 89 | B90: 45747 | C90: 3 | D90: 410782 | E90: 113-511077X | F90: 南部 | G90: 大田 佳弥 | H90: 大田区中央4-32-10 | I90: 大田区 | J90: 需要 | M90: 45805 | N90: 5 | AB90: 25.6 | AC90: 40075798 | AD90: 6 | AF90: 10 | AG90: 182503 | AH90: 15
A91: 90 | B91: 45748 | C91: 4 | D91: 410787 | E91: 113-582212X | F91: 南部 | G91: 黒須 雄也 | H91: 大田区羽田旭町4-11 | I91: 大田区 | J91: 他受 拡幅移設 | M91: 45849 | N91: 7 | AB91: 25.7 | AC91: 50000128 | AD91: 7 | AF91: 16 | AG91: 657196 | AH91: 258
A92: 91 | B92: 45748 | C92: 4 | D92: 410789 | E92: 113-514043X | F92: 南部 | G92: 藤田 雄也 | H92: 大田区羽田5-25 | I92: 大田区 | J92: 需要 | M92: 45807 | N92: 5 | AB92: 25.6 | AC92: 40075809 | AD92: 6 | AF92: 10 | AG92: 275507 | AH92: 35
A93: 92 | B93: 45748 | C93: 4 | D93: 410790 | E93: 113-575234X | F93: 南部 | G93: 大田 佳弥 | H93: 大田区西蒲田7-12 | I93: 大田区 | J93: 他受 沈下管入取替 | M93: 45799 | N93: 5 | AB93: 25.6 | AC93: 50000106 | AD93: 6 | AF93: 16 | AG93: 141625 | AH93: 19
A94: 93 | B94: 45749 | C94: 4 | D94: 410792 | E94: 411-591651E | F94: 北部 | G94: 鈴木 怜於名 | H94: 和光市白子2-24 | I94: 和光市 | J94: その他 架管修理 | M94: 45978 | N94: 11 | P94: 共立 | Q94: 45793 | R94: 4/15古川 | S94: 25.5 | AB94: 25.12 | AC94: 50000252 | AD94: 12 | AF94: 37 | AG94: 528713 | AH94: 10
A95: 94 | B95: 45751 | C95: 4 | D95: 410797 | E95: 113-Z88098X | F95: 南部 | G95: 藤田 雄也 | H95: 大田区京浜島1-2 | I95: 大田区 | J95: 需要 埋設可否検討 | M95: 45799 | N95: 5 | AB95: 25.6 | AC95: 50000819 | AD95: 6 | AF95: 16 | AG95: 680834 | AH95: 388
A96: 95 | B96: 45755 | C96: 4 | D96: 410802 | E96: 411-432008V | F96: 北部 | G96: 中山 晃嗣 | H96: 和光市西大和団地1-3 | I96: 和光市 | J96: 申請業務 残置申請 | M96: 45792 | N96: 5 | AB96: 25.10 | AC96: 50001227 | AD96: 10 | AF96: 30 | AG96: 50284
A97: 96 | B97: 45729 | C97: 3 | D97: 410803 | E97: 311-042395X | F97: 西部 | G97: 茂木 政寛 | H97: 世田谷区北烏山6-11 | I97: 世田谷 | J97: 変更 試掘後設計 | L97: 不要 | N97: 1 | AC97: 40073524
A98: 97 | B98: 45758 | C98: 4 | D98: 410814 | E98: 311-516066X | F98: 西部 | G98: 上松 一雄 | H98: 三鷹市牟礼5-11 | I98: 三鷹市 | J98: 需要 | L98: - | M98: 45775 | N98: 4 | V98: 45758 | X98: 45775 | Z98: 25.7 | AA98: 3423 | AB98: 25.7 | AC98: 50002699 | AD98: 7 | AF98: 30 | AG98: 375467 | AH98: 84
A99: 98 | B99: 45762 | C99: 4 | D99: 410818 | E99: 113-690302X | F99: 南部 | G99: 古川 智基 | H99: 大田区東雪谷3-14-2 | I99: 大田区 | J99: その他 中圧反転 | N99: 1 | AC99: 50002798
A100: 99 | B100: 45765 | C100: 4 | D100: 410825 | E100: 113-514047X | F100: 南部 | G100: 藤田 雄也 | H100: 大田区羽田6-28 | I100: 大田区 | J100: 需要 多摩川河川区域 | M100: 45807 | N100: 5 | P100: 共立 | Q100: 45784 | R100: 4/18古川 | S100: 25.5 | AB100: 25.6 | AC100: 50003358 | AD100: 6 | AF100: 10 | AG100: 400039 | AH100: 18
...

Sheet ISO台帳(神)
A1: 整理番号 | B1: 受注日 | C1: 受注月 | D1: 受注番号 | E1: 工事番号 | F1: ＮＣ区分 | G1: 担当者 | H1: 工 事 場 所 | I1: 住所（行政区） | J1: 件名 | K1: 件名区分 | L1: 現場日 | M1: 顧客引渡 実施日 | N1: 納品月 | O1: 繁閑調整 | P1: 委託業者名(外注) | Q1: 外注納品 実施日 | R1: 外注支払月 | S1: 外注費 | T1: 委託業者名(外注)2 | U1: 外注発注日2 | V1: 外注納品 予定日2 | W1: 外注納品 実施日2 | X1: 部門長2 | Y1: 外注支払月2 | Z1: 外注費2 | AA1: 入金月 | AB1: 請求書発行番号 | AC1: 入金月（月のみ） | AD1: 事務所/分室 | AE1: 精算 グループ | AF1: 金額 | AG1: 精算延長 | AH1: 繁閑調整金 | AI1: 事業所 | AL1: =AF176+AF508+AF511+AF582+AF608+AF732 -> 778454
A2: 1 | B2: 45762 | C2: 4 | D2: 420995 | E2: 512 | F2: 神奈川 | G2: 吉田・有賀 | H2: 川崎市 | I2: 川崎市 | J2: 道調資料作成・修正作業 | L2: 不要 | M2: 45819 | N2: 6 | AA2: 25.6 | AB2: 520604 | AC2: 6 | AD2: 神 | AE2: 100 | AF2: 61154 | AI2: 神奈川
A3: 2 | B3: 45810 | C3: 6 | D3: 420996 | E3: 512 | F3: 神奈川 | G3: 鈴木 照子 | H3: 川崎市 | I3: 川崎市 | J3: 供給管申請（ROADIS） | L3: 不要 | M3: 45838 | N3: 6 | AA3: 25.6 | AB3: 520601 | AC3: 6 | AD3: 神 | AE3: 100 | AF3: 261773 | AI3: 神奈川
A4: 3 | B4: 45810 | C4: 6 | D4: 420997 | E4: 512 | F4: 神奈川 | G4: 鈴木 照子 | H4: 川崎市 | I4: 川崎市 | J4: 供給管申請（手申請/GALILEOⅡ） | L4: 不要 | M4: 45838 | N4: 6 | AA4: 25.6 | AB4: 520602 | AC4: 6 | AD4: 神 | AE4: 100 | AF4: 193701 | AI4: 神奈川
A5: 4 | B5: 45810 | C5: 6 | D5: 420998 | E5: 512 | F5: 神奈川 | G5: 鈴木 照子 | H5: 川崎市 | I5: 川崎市 | J5: 申請業務 | L5: 不要 | M5: 45834 | N5: 6 | AA5: 25.6 | AB5: 520603 | AC5: 6 | AD5: 神 | AE5: 100 | AF5: 48041 | AI5: 神奈川
A6: 5 | B6: 45810 | C6: 6 | D6: 420999 | E6: 553 | F6: 神奈川 | G6: 鈴木 照子 | H6: 川崎市 | I6: 川崎市 | J6: 漏洩修理他申請（ROADIS） | L6: 不要 | M6: 45834 | N6: 6 | AA6: 25.6 | AB6: 50009679 | AC6: 6 | AD6: 神 | AE6: 50 | AF6: 196296 | AI6: 神奈川
A7: 7 | B7: 45089 | C7: 6 | D7: 320046 | E7: 513-119143X | F7: 神奈川 | G7: 米山 直人 | H7: 高津区溝口2-14 | I7: 高津区 | J7: 変更申請 | L7: 済 | M7: 46055 | N7: 2 | AA7: 26.2 | AB7: 20031347 | AC7: 2 | AD7: 湘 | AE7: 21 | AF7: 14680 | AI7: 神奈川
A8: 8 | B8: 45219 | C8: 10 | D8: 320712 | E8: 513-435003K | F8: 神奈川 | G8: 佐藤 竜 | H8: 高津区梶ヶ谷6-8 | I8: 高津区 | J8: 供給改善A（中圧） | L8: 済 | M8: 45259 | N8: 11 | AB8: 30028858 | AI8: 神奈川
A9: 10 | B9: 45264 | C9: 12 | D9: 320895 | E9: 513-435003Q | F9: 神奈川 | G9: 水上 知輝 | H9: 麻生区上麻生6-29 | I9: 麻生区 | J9: 供給改善A | L9: 済 | M9: 45471 | N9: 6 | AB9: 30034703 | AI9: 神奈川
A10: 11 | B10: 45343 | C10: 2 | D10: 321169 | E10: 513-481002T | F10: 神奈川 | G10: 山田 敏雄 | H10: 麻生区片平4-5 | I10: 麻生区 | J10: 他受（無償）（道路工事） | L10: 済 | M10: 45856 | N10: 7 | P10: みつば | Q10: 45381 | R10: 24.3 | AA10: 25.7 | AB10: 30044283 | AC10: 7 | AD10: 神 | AE10: 27 | AF10: 660123 | AG10: 333 | AI10: 神奈川
A11: 12 | B11: 45398 | C11: 4 | D11: 321463 | E11: 512-553101J | F11: 神奈川 | G11: 佐藤 竜 | H11: 神奈川区三枚町698 | I11: 神奈川 | J11: ＤＧ入取替（大規模一括件名） | L11: 済 | M11: 45504 | N11: 7 | AA11: 25.7 | AB11: 40006161 | AC11: 7 | AD11: 神 | AE11: 27 | AF11: 114810 | AG11: 35 | AI11: 神奈川
A12: 13 | B12: 45083 | C12: 6 | D12: 321477 | E12: 513-311002A | F12: 神奈川 | G12: 水上 知輝 | H12: 中原区小杉町1 | I12: 中原区 | J12: 工区分割 | L12: 済 | M12: 45771 | N12: 4 | AA12: 25.6 | AB12: 30009593 | AC12: 6 | AD12: 神 | AE12: 27 | AF12: 296772 | AG12: 79 | AI12: 神奈川
A13: 14 | B13: 45400 | C13: 4 | D13: 321483 | E13: 513-419024X | F13: 神奈川 | G13: 有賀 真之介 | H13: 宮前区平4-17 | I13: 宮前区 | J13: 道路復旧 | L13: 済 | M13: 中止 | AB13: 40008390 | AI13: 神奈川
A14: 15 | B14: 45453 | C14: 6 | D14: 420040 | E14: 513-553113J | F14: 神奈川 | G14: 廣瀬 達 | H14: 宮前区南野川3-12 | I14: 宮前区 | J14: ＤＧ入取替（大規模一括件名） | L14: 済 | M14: 45688 | N14: 1 | P14: 共立 | Q14: 45652 | R14: 25.1 | AA14: 25.6 | AB14: 40040654 | AC14: 6 | AD14: 神 | AE14: 27 | AF14: 515612 | AG14: 203 | AI14: 神奈川
A15: 16 | B15: 45453 | C15: 6 | D15: 420045 | E15: 513-553118J | F15: 神奈川 | G15: 有賀 真之介 | H15: 中原区井田2-33 | I15: 中原区 | J15: ＤＧ入取替（大規模一括件名） | L15: 済 | M15: 45728 | N15: 3 | P15: 共立 | Q15: 45652 | R15: 25.1 | AB15: 40040677 | AI15: 神奈川
A16: 17 | B16: 45453 | C16: 6 | D16: 420052 | E16: 512-553124J | F16: 神奈川 | G16: 青柳 亨 | H16: 鶴見区鶴見中央1-22 | I16: 鶴見区 | J16: ＤＧ入取替（大規模一括件名） | L16: 済 | M16: 45750 | N16: 4 | AA16: 25.6 | AB16: 40040748 | AC16: 6 | AD16: 神 | AE16: 27 | AF16: 289758 | AG16: 84 | AI16: 神奈川
A17: 18 | B17: 45455 | C17: 6 | D17: 420060 | E17: 512-553122J | F17: 神奈川 | G17: 廣瀬 達 | H17: 鶴見区矢向1-13 | I17: 鶴見区 | J17: ＤＧ入取替（大規模一括件名） | L17: 済 | M17: 45856 | N17: 7 | P17: みつば | Q17: 45569 | R17: 24.1 | AA17: 25.8 | AB17: 40041083 | AC17: 8 | AD17: 神 | AE17: 27 | AF17: 382105 | AG17: 229 | AI17: 神奈川
A18: 19 | B18: 45455 | C18: 6 | D18: 420069 | E18: 513-653111J | F18: 神奈川 | G18: 有賀 真之介 | H18: 川崎区小田4-27 | I18: 川崎区 | J18: ＤＧ入取替（大規模一括件名） | L18: 済 | M18: 45768 | N18: 4 | P18: みつば | Q18: 45681 | R18: 25.1 | AA18: 25.6 | AB18: 40041182 | AC18: 6 | AD18: 神 | AE18: 27 | AF18: 372606 | AG18: 263 | AI18: 神奈川
A19: 20 | B19: 45455 | C19: 6 | D19: 420071 | E19: 513-653103J | F19: 神奈川 | G19: 水上 知輝 | H19: 高津区梶ヶ谷2-12 | I19: 高津区 | J19: ＤＧ入取替（大規模一括件名） | L19: 済 | M19: 45751 | N19: 4 | O19: 設備 | P19: 本社 | Q19: 45589 | AB19: 40041100 | AI19: 神奈川
A20: 21 | B20: 45455 | C20: 6 | D20: 420075 | E20: 513-653108J | F20: 神奈川 | G20: 青柳 亨 | H20: 中原区今井仲町11 | I20: 中原区 | J20: ＤＧ入取替（大規模一括件名） | L20: 済 | M20: 45737 | N20: 3 | P20: みつば | Q20: 45713 | R20: 25.2 | AA20: 25.7 | AB20: 40041136 | AC20: 7 | AD20: 神 | AE20: 27 | AF20: 376692 | AG20: 254 | AI20: 神奈川
A21: 22 | B21: 45455 | C21: 6 | D21: 420076 | E21: 513-653109J | F21: 神奈川 | G21: 有賀 真之介 | H21: 川崎区伊勢町6 | I21: 川崎区 | J21: ＤＧ入取替（大規模一括件名） | L21: 済 | M21: 45806 | N21: 5 | P21: みつば | Q21: 45713 | R21: 25.2 | AA21: 26.1 | AB21: 40041141 | AC21: 1 | AD21: 神 | AE21: 27 | AF21: 363920 | AG21: 365 | AI21: 神奈川
A22: 23 | B22: 45460 | C22: 6 | D22: 420088 | E22: 512-553131J | F22: 神奈川 | G22: 山田 敏雄 | H22: 神奈川区松見町3-532 | I22: 神奈川 | J22: ＤＧ入取替（大規模一括件名） | L22: 済 | M22: 45744 | N22: 3 | P22: 共立 | Q22: 45631 | R22: 24.12 | AA22: 25.8 | AB22: 40041684 | AC22: 8 | AD22: 神 | AE22: 27 | AF22: 600548 | AG22: 454 | AI22: 神奈川
A23: 24 | B23: 45460 | C23: 6 | D23: 420092 | E23: 512-553136J | F23: 神奈川 | G23: 佐藤 竜 | H23: 神奈川区西寺尾2-24 | I23: 神奈川 | J23: ＤＧ入取替（大規模一括件名） | L23: 済 | M23: 45721 | N23: 3 | AA23: 25.11 | AB23: 40041705 | AC23: 11 | AD23: 神 | AE23: 27 | AF23: 331739 | AG23: 168 | AI23: 神奈川
A24: 25 | B24: 45460 | C24: 6 | D24: 420107 | E24: 512-553145J | F24: 神奈川 | G24: 佐藤 竜 | H24: 青葉区美しが丘1-19 | I24: 青葉区 | J24: ＤＧ入取替（大規模一括件名） | L24: 済 | M24: 45743 | N24: 3 | O24: 西部 | P24: みつば | Q24: 45652 | R24: 25.1 | AA24: 25.7 | AB24: 40041900 | AC24: 7 | AD24: 神 | AE24: 27 | AF24: 434052 | AG24: 426 | AH24: 237593 | AI24: 神奈川
A25: 26 | B25: 45462 | C25: 6 | D25: 420111 | E25: 512-653113J | F25: 神奈川 | G25: 廣瀬 達 | H25: 神奈川区旭ヶ丘23 | I25: 神奈川 | J25: ＤＧ入取替（大規模一括件名） | L25: 済 | M25: 45645 | N25: 12 | P25: 共立 | Q25: 45568 | R25: 24.1 | AA25: 25.6 | AB25: 40042110 | AC25: 6 | AD25: 神 | AE25: 27 | AF25: 481908 | AG25: 364 | AI25: 神奈川
A26: 27 | B26: 45461 | C26: 6 | D26: 420113 | E26: 512-653115J | F26: 神奈川 | G26: 山田 智史 | H26: 神奈川区神奈川本町7 | I26: 神奈川 | J26: FLEX | L26: 済 | M26: 45853 | N26: 7 | P26: 共立 | Q26: 45716 | R26: 25.3 | AA26: 25.9 | AB26: 50011434 | AC26: 9 | AD26: 湘 | AE26: 301 | AF26: 381779 | AG26: 187 | AI26: 神奈川
A27: 28 | B27: 45461 | C27: 6 | D27: 420114 | E27: 512-653116J | F27: 神奈川 | G27: 廣瀬 達 | H27: 神奈川区六角橋6-24 | I27: 神奈川 | J27: ＤＧ入取替（大規模一括件名） | L27: 済 | M27: 45805 | N27: 5 | P27: みつば | Q27: 45713 | R27: 25.2 | AA27: 25.10 | AB27: 40042126 | AC27: 10 | AD27: 神 | AE27: 27 | AF27: 398145 | AG27: 198 | AI27: 神奈川
A28: 29 | B28: 45462 | C28: 6 | D28: 420115 | E28: 512-653120J | F28: 神奈川 | G28: 廣瀬 達 | H28: 青葉区桜台26 | I28: 青葉区 | J28: ＤＧ入取替（大規模一括件名） | L28: 済 | M28: 45721 | N28: 3 | P28: みつば | Q28: 45652 | R28: 25.1 | AA28: 25.6 | AB28: 40042161 | AC28: 6 | AD28: 神 | AE28: 27 | AF28: 395132 | AG28: 257 | AI28: 神奈川
A29: 30 | B29: 45462 | C29: 6 | D29: 420117 | E29: 512-653121J | F29: 神奈川 | G29: 廣瀬 達 | H29: 青葉区桜台38 | I29: 青葉区 | J29: ＤＧ入取替（大規模一括件名） | L29: 済 | M29: 45715 | N29: 2 | AA29: 25.7 | AB29: 40042277 | AC29: 7 | AD29: 神 | AE29: 27 | AF29: 373060 | AG29: 209 | AI29: 神奈川
A30: 31 | B30: 45462 | C30: 6 | D30: 420118 | E30: 512-653122J | F30: 神奈川 | G30: 山田 智史 | H30: 青葉区榎が丘7 | I30: 青葉区 | J30: ＤＧ入取替（大規模一括件名） | L30: 済 | M30: 45796 | N30: 5 | P30: 共立 | Q30: 45629 | R30: 24.12 | AA30: 25.6 | AB30: 40042283 | AC30: 6 | AD30: 湘 | AE30: 27 | AF30: 369152 | AG30: 246 | AI30: 神奈川
A31: 32 | B31: 45462 | C31: 6 | D31: 420119 | E31: 512-653123J | F31: 神奈川 | G31: 有賀 真之介 | H31: 青葉区市ヶ尾町1169 | I31: 青葉区 | J31: ＤＧ入取替（大規模一括件名） | L31: 済 | M31: 45868 | N31: 7 | P31: 共立 | Q31: 45716 | R31: 25.3 | AB31: 40042315 | AI31: 神奈川
A32: 33 | B32: 45464 | C32: 6 | D32: 420153 | E32: 513-553125F | F32: 神奈川 | G32: 山田 智史 | H32: 幸区東古市場121 | I32: 幸区東 | J32: FLEX | L32: 済 | M32: 45602 | N32: 11 | AA32: 25.8 | AB32: 40042450 | AC32: 8 | AD32: 湘 | AE32: 301 | AF32: 301077 | AG32: 55 | AI32: 神奈川
A33: 34 | B33: 45471 | C33: 6 | D33: 420214 | E33: 513-553140P | F33: 神奈川 | G33: 山田 智史 | H33: 川崎区駅前本町4-2 | I33: 川崎区 | J33: ＤＧ入取替 | L33: 済 | M33: 45594 | N33: 10 | AA33: 25.10 | AB33: 40044019 | AC33: 10 | AD33: 湘 | AE33: 27 | AF33: 207850 | AG33: 24 | AI33: 神奈川
A34: 35 | B34: 45476 | C34: 7 | D34: 420238 | E34: 513-553144P | F34: 神奈川 | G34: 青柳 亨 | H34: 中原区新丸子町922 | I34: 中原区 | J34: ＤＧ入取替 | L34: 済 | M34: 45706 | N34: 2 | AA34: 25.10 | AB34: 40044587 | AC34: 10 | AD34: 神 | AE34: 27 | AF34: 232196 | AG34: 52 | AI34: 神奈川
A35: 36 | B35: 45476 | C35: 7 | D35: 420241 | E35: 513-653107J | F35: 神奈川 | G35: 山田 智史 | H35: 中原区今井仲町12 | I35: 中原区 | J35: ＤＧ入取替（大規模一括件名） | L35: 済 | M35: 45806 | N35: 5 | P35: みつば | Q35: 45713 | R35: 25.2 | AA35: 25.9 | AB35: 40044610 | AC35: 9 | AD35: 湘 | AE35: 27 | AF35: 361117 | AG35: 278 | AI35: 神奈川
A36: 37 | B36: 45539 | C36: 9 | D36: 420465 | E36: 512-542153J | F36: 神奈川 | G36: 山田 智史 | H36: 鶴見区上末吉1-21 | I36: 鶴見区 | J36: 申請書作成 | L36: 済 | M36: 45813 | N36: 6 | AA36: 25.6 | AB36: 40051389 | AC36: 6 | AD36: 湘 | AE36: 27 | AF36: 115333 | AI36: 神奈川
A37: 39 | B37: 45602 | C37: 11 | D37: 420677 | E37: 512-544101Y | F37: 神奈川 | G37: 山田 智史 | H37: 鶴見区弁天町2 | I37: 鶴見区 | J37: バルブ取替 | L37: 済 | M37: 45761 | N37: 4 | AA37: 25.6 | AB37: 40058400 | AC37: 6 | AD37: 湘 | AE37: 27 | AF37: 195035 | AG37: 10 | AI37: 神奈川
A38: 40 | B38: 45602 | C38: 11 | D38: 420678 | E38: 513-544407Y | F38: 神奈川 | G38: 佐藤 竜 | H38: 多摩区枡形2-3 | I38: 多摩区 | J38: ガバナ取替 | L38: 済 | M38: 45804 | N38: 5 | AA38: 25.7 | AB38: 40058405 | AC38: 7 | AD38: 神 | AE38: 27 | AF38: 263684 | AG38: 12 | AI38: 神奈川
A39: 42 | B39: 45623 | C39: 11 | D39: 420751 | E39: 513-532103X | F39: 神奈川 | G39: 髙橋 篤史 | H39: 高津区下作延5-9 | I39: 高津区 | J39: 供給改善（A) | L39: 済 | M39: 45811 | N39: 6 | AA39: 25.7 | AB39: 40060840 | AC39: 7 | AD39: 神 | AE39: 27 | AF39: 106466 | AI39: 神奈川
A40: 44 | B40: 45639 | C40: 12 | D40: 420804 | E40: 512-541002A | F40: 神奈川 | G40: 安藤 俊輔 | H40: 青葉区新石川2-13 | I40: 青葉区 | J40: 中圧入取替（MA化） | L40: 済 | M40: 45827 | N40: 6 | P40: 共立 | Q40: 45686 | R40: 25.2 | AA40: 26.1 | AB40: 40062724 | AC40: 1 | AD40: 湘 | AE40: 27 | AF40: 700528 | AG40: 338 | AI40: 神奈川
A41: 45 | B41: 45639 | C41: 12 | D41: 420805 | E41: 512-541002B | F41: 神奈川 | G41: 安藤 俊輔 | H41: 青葉区美しが丘2-7 | I41: 青葉区 | J41: 中圧除却（MA化） | L41: 45831 | M41: 46044 | N41: 1 | AA41: 26.1 | AB41: 40062735 | AC41: 1 | AD41: 湘 | AE41: 27 | AF41: 96303 | AI41: 神奈川
A42: 46 | B42: 45639 | C42: 12 | D42: 420807 | E42: 512-541002J | F42: 神奈川 | G42: 安藤 俊輔 | H42: 宮前区有馬6-6 | I42: 宮前区 | J42: 中圧入取替（MA化） | L42: 済 | M42: 46035 | N42: 1 | AA42: 26.1 | AB42: 40062750 | AC42: 1 | AD42: 湘 | AE42: 27 | AF42: 165632 | AI42: 神奈川
A43: 47 | B43: 45639 | C43: 12 | D43: 420808 | E43: 512-541002E | F43: 神奈川 | G43: 安藤 俊輔 | H43: 宮前区鷺沼1-24 | I43: 宮前区 | J43: 中圧入取替（MA化） | L43: 済 | M43: 46035 | N43: 1 | AA43: 26.1 | AB43: 40062762 | AC43: 1 | AD43: 湘 | AE43: 27 | AF43: 102286 | AI43: 神奈川
A44: 48 | B44: 45639 | C44: 12 | D44: 420809 | E44: 512-541002F | F44: 神奈川 | G44: 佐藤 竜 | H44: 宮前区有馬5-2 | I44: 宮前区 | J44: 中圧入取替（MA化） | L44: 済 | M44: 46035 | N44: 1 | AA44: 26.1 | AB44: 40062766 | AC44: 1 | AD44: 神 | AE44: 27 | AF44: 120419 | AI44: 神奈川
A45: 49 | B45: 45639 | C45: 12 | D45: 420810 | E45: 512-541002G | F45: 神奈川 | G45: 佐藤 竜 | H45: 宮前区有馬8-22 | I45: 宮前区 | J45: 中圧入取替（MA化） | L45: 済 | M45: 46035 | N45: 1 | AA45: 26.1 | AB45: 40062770 | AC45: 1 | AD45: 神 | AE45: 27 | AF45: 123667 | AI45: 神奈川
A46: 50 | B46: 45639 | C46: 12 | D46: 420812 | E46: 512-471038X | F46: 神奈川 | G46: 安藤 俊輔 | H46: 港北区篠原東1-11 | I46: 港北区 | J46: 他受（有償）水道 | L46: 済 | M46: 45870 | N46: 8 | AA46: 25.8 | AB46: 40062669 | AC46: 8 | AD46: 湘 | AE46: IB | AF46: 255097 | AG46: 21 | AI46: 神奈川
A47: 51 | B47: 45643 | C47: 12 | D47: 420820 | E47: 513-653112J | F47: 神奈川 | G47: 安藤 俊輔 | H47: 中原区小杉陣屋町1-15 | I47: 中原区 | J47: 入取替(ガバナ出管対策) | L47: 済 | M47: 45807 | N47: 5 | AB47: 40063105 | AI47: 神奈川
A48: 52 | B48: 45644 | C48: 12 | D48: 420829 | E48: 512-653148P | F48: 神奈川 | G48: 有賀 真之介 | H48: 鶴見区北寺尾6-1 | I48: 鶴見区 | J48: 入取替(ガバナ出管対策) | L48: 済 | M48: 45756 | N48: 4 | AB48: 40063310 | AI48: 神奈川
A49: 53 | B49: 45644 | C49: 12 | D49: 420831 | E49: 513-653113P | F49: 神奈川 | G49: 佐藤 竜 | H49: 宮前区宮前平3-10 | I49: 宮前区 | J49: 入取替(ガバナ出管対策) | L49: 済 | M49: 45786 | N49: 5 | AB49: 40063376 | AI49: 神奈川
A50: 54 | B50: 45644 | C50: 12 | D50: 420832 | E50: 513-653114P | F50: 神奈川 | G50: 廣瀬 達 | H50: 宮前区土橋1-9 | I50: 宮前区 | J50: 入取替(ガバナ出管対策) | L50: 済 | M50: 45775 | N50: 4 | AB50: 40063379 | AI50: 神奈川
A51: 55 | B51: 45645 | C51: 12 | D51: 420846 | E51: 512-653145J | F51: 神奈川 | G51: 佐藤 竜 | H51: 青葉区大場町285 | I51: 青葉区 | J51: 入取替(ガバナ出管対策) | L51: 済 | M51: 45806 | N51: 5 | AB51: 40063639 | AI51: 神奈川
A52: 56 | B52: 45645 | C52: 12 | D52: 420847 | E52: 512-653146J | F52: 神奈川 | G52: 安藤 俊輔 | H52: 青葉区市ヶ尾町1171 | I52: 青葉区 | J52: 入取替(ガバナ出管対策) | L52: 済 | M52: 45806 | N52: 5 | AB52: 40063646 | AI52: 神奈川
A53: 57 | B53: 45652 | C53: 12 | D53: 420879 | E53: 513-505004X | F53: 神奈川 | G53: 髙橋 篤史 | H53: 川崎区富士見2-5 | I53: 川崎区 | J53: 供給管新設工事（社内他受） | L53: 済 | M53: 45770 | N53: 4 | AA53: 25.6 | AB53: 40064723 | AC53: 6 | AD53: 神 | AE53: IB | AF53: 192798 | AG53: 10 | AI53: 神奈川
A54: 58 | B54: 45665 | C54: 1 | D54: 420902 | E54: 513-505005X | F54: 神奈川 | G54: 髙橋 篤史 | H54: 川崎区夜光1-2 | I54: 川崎区 | J54: 社内他受 | L54: 済 | M54: 45733 | N54: 3 | AA54: 25.6 | AB54: 40065242 | AC54: 6 | AD54: 神 | AE54: IB | AF54: 159679 | AG54: 10 | AI54: 神奈川
A55: 59 | B55: 45666 | C55: 1 | D55: 420911 | E55: 513-543101X | F55: 神奈川 | G55: 髙橋 篤史 | H55: 高津区溝口2-28 | I55: 高津区 | J55: 入取替 | L55: 済 | M55: 45817 | N55: 6 | AA55: 25.9 | AB55: 40065665 | AC55: 9 | AD55: 神 | AE55: 27 | AF55: 191554 | AG55: 14 | AI55: 神奈川
A56: 60 | B56: 45667 | C56: 1 | D56: 420914 | E56: 515-512003X | F56: 湘南 | G56: 米山 直人 | H56: 海老名市河原口1-3 | I56: 海老名 | J56: 海老名市河原口１丁目計画 | L56: 済 | M56: 45743 | N56: 3 | AA56: 25.6 | AB56: 40066073 | AC56: 6 | AD56: 湘 | AE56: 46 | AF56: 291683 | AG56: 166 | AI56: 神奈川
A57: 61 | B57: 45667 | C57: 1 | D57: 420915 | E57: 513-511005X | F57: 神奈川 | G57: 髙橋 篤史 | H57: 麻生区上麻生6-11 | I57: 麻生区 | J57: 需要 | L57: 済 | M57: 45755 | N57: 4 | AA57: 25.6 | AB57: 40065878 | AC57: 6 | AD57: 神 | AE57: 21 | AF57: 257955 | AG57: 44 | AI57: 神奈川
A58: 62 | B58: 45672 | C58: 1 | D58: 420927 | E58: 515-471041X | F58: 湘南 | G58: 萬條 秀馬 | H58: 海老名市中新田213 | I58: 海老名 | J58: 他受有償(中圧) | L58: 済 | M58: 45814 | N58: 6 | AA58: 25.8 | AB58: 40065848 | AC58: 8 | AD58: 湘 | AE58: 46 | AF58: 175617 | AG58: 46 | AI58: 神奈川
A59: 63 | B59: 45677 | C59: 1 | D59: 420947 | E59: 515-510001X | F59: 湘南 | G59: 萬條 秀馬 | H59: 海老名市社家5-10 | I59: 海老名 | J59: 海老名市立社家小学校屋内運動場大規模改修 | L59: 済 | M59: 45771 | N59: 4 | AA59: 25.6 | AB59: 40067568 | AC59: 6 | AD59: 湘 | AE59: 46 | AF59: 387101 | AG59: 87 | AI59: 神奈川
A60: 64 | B60: 45677 | C60: 1 | D60: 420948 | E60: 513-653117J | F60: 神奈川 | G60: 吉田 真人 | H60: 中原区宮内2-9 | I60: 中原区 | J60: ＤＧ入取替（大規模一括件名） | L60: 済 | M60: 45866 | N60: 7 | O60: 西部 | AA60: 26.1 | AB60: 40066628 | AC60: 1 | AD60: 神 | AE60: 27 | AF60: 280613 | AG60: 120 | AH60: 242635 | AI60: 神奈川
A61: 65 | B61: 45677 | C61: 1 | D61: 420949 | E61: 513-653118J | F61: 神奈川 | G61: 有賀 真之介 | H61: 中原区宮内3-9 | I61: 中原区 | J61: ＤＧ入取替（大規模一括件名） | L61: 済 | M61: 45863 | N61: 7 | O61: 西部 | AA61: 25.12 | AB61: 40066636 | AC61: 12 | AD61: 神 | AE61: 27 | AF61: 266856 | AG61: 122 | AH61: 243788 | AI61: 神奈川
A62: 66 | B62: 45677 | C62: 1 | D62: 420950 | E62: 513-653119J | F62: 神奈川 | G62: 青柳 亨 | H62: 中原区井田杉山町14 | I62: 中原区 | J62: ＤＧ入取替（大規模一括件名） | L62: 済 | M62: 45861 | N62: 7 | O62: 西部 | AA62: 25.12 | AB62: 40066638 | AC62: 12 | AD62: 神 | AE62: 27 | AF62: 314781 | AG62: 162 | AH62: 228365 | AI62: 神奈川
A63: 67 | B63: 45677 | C63: 1 | D63: 420952 | E63: 513-653115J | F63: 神奈川 | G63: 青柳 亨 | H63: 川崎区京町1-15 | I63: 川崎区 | J63: ＤＧ入取替（大規模一括件名） | L63: 済 | M63: 45785 | N63: 5 | P63: みつば | Q63: 45741 | R63: 25.3 | AA63: 26.1 | AB63: 40066623 | AC63: 1 | AD63: 神 | AE63: 27 | AF63: 515193 | AG63: 387 | AI63: 神奈川
A64: 68 | B64: 45677 | C64: 1 | D64: 420953 | E64: 513-653116J | F64: 神奈川 | G64: 廣瀬 達 | H64: 川崎区京町2-5 | I64: 川崎区 | J64: ＤＧ入取替（大規模一括件名） | L64: 済 | M64: 45952 | N64: 10 | P64: みつば | Q64: 45741 | R64: 25.3 | AB64: 40066626 | AI64: 神奈川
A65: 69 | B65: 45678 | C65: 1 | D65: 420958 | E65: 513-543102X | F65: 神奈川 | G65: 星 善輝 | H65: 幸区南幸町3-3 | I65: 幸区南 | J65: ジュート入取替 | L65: 済 | M65: 46055 | N65: 2 | AA65: 26.2 | AB65: 40066850 | AC65: 2 | AD65: 湘 | AE65: 23 | AF65: 66175 | AG65: 10 | AI65: 神奈川
A66: 70 | B66: 45679 | C66: 1 | D66: 420964 | E66: 512-544001X | F66: 神奈川 | G66: 佐藤 竜 | H66: 鶴見区安善町1-1 | I66: 鶴見区 | J66: 外電取替 | L66: 済 | M66: 45856 | N66: 7 | AA66: 25.8 | AB66: 40067104 | AC66: 8 | AD66: 神 | AE66: 27 | AF66: 239474 | AI66: 神奈川
A67: 71 | B67: 45681 | C67: 1 | D67: 420972 | E67: 512-642501X | F67: 神奈川 | G67: 有賀 真之介 | H67: 神奈川区台町3-2 | I67: 神奈川 | J67: 入取替 | L67: 45881 | M67: 中止 | AB67: 40067394 | AI67: 神奈川
A68: 72 | B68: 45684 | C68: 1 | D68: 420976 | E68: 513-553147P | F68: 神奈川 | G68: 廣瀬 達 | H68: 幸区古市場1752 | I68: 幸区古 | J68: ＤＧ入取替 | L68: 済 | M68: 45785 | N68: 5 | O68: 設備 | P68: 本社 | AA68: 25.8 | AB68: 40067517 | AC68: 8 | AD68: 神 | AE68: 27 | AF68: 192159 | AG68: 54 | AH68: 56276 | AI68: 神奈川
A69: 73 | B69: 45684 | C69: 1 | D69: 420977 | E69: 513-553151P | F69: 神奈川 | G69: 廣瀬 達 | H69: 中原区井田2-17 | I69: 中原区 | J69: ＤＧ入取替 | L69: 済 | M69: 45756 | N69: 4 | AA69: 25.7 | AB69: 40067529 | AC69: 7 | AD69: 神 | AE69: 27 | AF69: 196279 | AG69: 55 | AI69: 神奈川
A70: 74 | B70: 45684 | C70: 1 | D70: 420978 | E70: 513-653123J | F70: 神奈川 | G70: 齋藤 航汰 | H70: 高津区梶ヶ谷4-8 | I70: 高津区 | J70: ＤＧ入取替（大規模一括件名） | L70: 済 | M70: 45833 | N70: 6 | P70: みつば | Q70: 45741 | R70: 25.3 | AA70: 25.10 | AB70: 40067464 | AC70: 10 | AD70: 神 | AE70: 27 | AF70: 385467 | AG70: 316 | AI70: 神奈川
A71: 75 | B71: 45685 | C71: 1 | D71: 420980 | E71: 512-419105X | F71: 神奈川 | G71: 水上 知輝 | H71: 都筑区東山田270 | I71: 都筑区 | J71: 設計変更 | L71: 済 | M71: 45743 | N71: 3 | AA71: 25.7 | AB71: 40067560 | AC71: 7 | AD71: 神 | AE71: 27 | AF71: 35755 | AI71: 神奈川
A72: 76 | B72: 45687 | C72: 1 | D72: 421001 | E72: 513-553149P | F72: 神奈川 | G72: 萬條 秀馬 | H72: 麻生区細山2-10 | I72: 麻生区 | J72: ＤＧ入取替 | L72: 済 | M72: 45805 | N72: 5 | AA72: 25.6 | AB72: 40068160 | AC72: 6 | AD72: 湘 | AE72: 27 | AF72: 191362 | AG72: 54 | AI72: 神奈川
A73: 77 | B73: 45688 | C73: 1 | D73: 421002 | E73: 513-653122J | F73: 神奈川 | G73: 齋藤 航汰 | H73: 宮前区宮前平3-11 | I73: 宮前区 | J73: ＤＧ入取替（大規模一括件名） | L73: 済 | M73: 45807 | N73: 5 | P73: 共立 | Q73: 45742 | R73: 25.3 | AA73: 25.9 | AB73: 40068176 | AC73: 9 | AD73: 神 | AE73: 27 | AF73: 380765 | AG73: 285 | AI73: 神奈川
A74: 78 | B74: 45688 | C74: 1 | D74: 421004 | E74: 513-553150P | F74: 神奈川 | G74: 米山 直人 | H74: 中原区井田2-23 | I74: 中原区 | J74: ＤＧ入取替 | L74: 済 | M74: 45807 | N74: 5 | AA74: 25.6 | AB74: 40068242 | AC74: 6 | AD74: 湘 | AE74: 27 | AF74: 177977 | AG74: 20 | AI74: 神奈川
A75: 79 | B75: 45692 | C75: 2 | D75: 421015 | E75: 512-044103X | F75: 神奈川 | G75: 水上 知輝 | H75: 港北区菊名1-17 | I75: 港北区 | J75: 入取替 | L75: 済 | M75: 45784 | N75: 5 | AB75: 40068738 | AI75: 神奈川
A76: 80 | B76: 45693 | C76: 2 | D76: 421018 | E76: 513-514107X | F76: 神奈川 | G76: 米山 直人 | H76: 宮前区初山2-6 | I76: 宮前区 | J76: 需要 | L76: 済 | M76: 45803 | N76: 5 | AA76: 25.6 | AB76: 40069768 | AC76: 6 | AD76: 湘 | AE76: 27 | AF76: 231245 | AG76: 112 | AI76: 神奈川
A77: 81 | B77: 45700 | C77: 2 | D77: 421043 | E77: 512-514220X | F77: 神奈川 | G77: 佐藤 竜 | H77: 港北区新吉田東5-45 | I77: 港北区 | J77: 需要 | L77: 済 | M77: 45721 | N77: 3 | AA77: 25.10 | AB77: 40069720 | AC77: 10 | AD77: 神 | AE77: 20 | AF77: 171464 | AG77: 28 | AI77: 神奈川
A78: 82 | B78: 45700 | C78: 2 | D78: 421051 | E78: 512-514222X | F78: 神奈川 | G78: 落合 晃平 | H78: 鶴見区駒岡4-41 | I78: 鶴見区 | J78: 需要 | L78: 済 | M78: 45761 | N78: 4 | P78: 共立 | Q78: 45743 | R78: 25.4 | AA78: 25.6 | AB78: 40070885 | AC78: 6 | AD78: 神 | AE78: 27 | AF78: 473878 | AG78: 107 | AI78: 神奈川
A79: 83 | B79: 45702 | C79: 2 | D79: 421062 | E79: 513-342114X | F79: 神奈川 | G79: 山田 智史 | H79: 宮前区平5-10 | I79: 宮前区 | J79: 申請書作成 | L79: 済 | M79: 45924 | N79: 9 | AA79: 25.10 | AB79: 40070009 | AC79: 10 | AD79: 湘 | AE79: 27 | AF79: 163487 | AI79: 神奈川
A80: 84 | B80: 45709 | C80: 2 | D80: 421091 | E80: 513-516002X | F80: 神奈川 | G80: 髙橋 篤史 | H80: 川崎区南渡田町13 | I80: 川崎区 | J80: 需要 | L80: 済 | M80: 45860 | N80: 7 | AA80: 25.8 | AB80: 40071307 | AC80: 8 | AD80: 神 | AE80: 27 | AF80: 138210 | AG80: 214 | AI80: 神奈川
A81: 85 | B81: 45705 | C81: 2 | D81: 421100 | E81: 513-653121F | F81: 神奈川 | G81: 佐藤 竜 | H81: 宮前区宮崎5-5 | I81: 宮前区 | J81: FLEX | L81: 済 | M81: 45811 | N81: 6 | AA81: 25.9 | AB81: 40068170 | AC81: 9 | AD81: 神 | AE81: 301 | AF81: 282703 | AG81: 112 | AI81: 神奈川
A82: 86 | B82: 45705 | C82: 2 | D82: 421101 | E82: 513-653120F | F82: 神奈川 | G82: 青柳 亨 | H82: 宮前区土橋3-7 | I82: 宮前区 | J82: FLEX | L82: 済 | M82: 45799 | N82: 5 | P82: 共立 | Q82: 45742 | R82: 25.3 | AA82: 25.8 | AB82: 40068166 | AC82: 8 | AD82: 神 | AE82: 301 | AF82: 362973 | AG82: 206 | AI82: 神奈川
A83: 87 | B83: 45716 | C83: 2 | D83: 421116 | E83: 512-505001X | F83: 神奈川 | G83: 髙橋 篤史 | H83: 鶴見区大黒町18 | I83: 鶴見区 | J83: 中圧供給管新設（社内他受） | L83: 済 | M83: 45747 | N83: 3 | AA83: 25.6 | AB83: 40071822 | AC83: 6 | AD83: 神 | AE83: IB | AF83: 201250 | AG83: 10 | AI83: 神奈川
A84: 88 | B84: 45719 | C84: 3 | D84: 421122 | E84: 515-510001X | F84: 湘南 | G84: 萬條 秀馬 | H84: 海老名市社家5-10 | I84: 海老名 | J84: 別ルート | L84: 済 | M84: 45791 | N84: 5 | AA84: 25.6 | AB84: 40072040 | AC84: 6 | AD84: 湘 | AE84: 46 | AF84: 202523 | AG84: 196 | AI84: 神奈川
A85: 89 | B85: 45727 | C85: 3 | D85: 421152 | E85: 513-514124X | F85: 神奈川 | G85: 青柳 亨 | H85: 川崎区大師河原2-4 | I85: 川崎区 | J85: 需要 | L85: 済 | M85: 45763 | N85: 4 | AA85: 25.6 | AB85: 40073837 | AC85: 6 | AD85: 神 | AE85: 27 | AF85: 245882 | AG85: 118 | AI85: 神奈川
A86: 90 | B86: 45727 | C86: 3 | D86: 421153 | E86: 513-514123X | F86: 神奈川 | G86: 星 善輝 | H86: 宮前区菅生4-5 | I86: 宮前区 | J86: 需要 | L86: 済 | M86: 45790 | N86: 5 | AA86: 25.6 | AB86: 40073539 | AC86: 6 | AD86: 湘 | AE86: 27 | AF86: 339351 | AG86: 200 | AI86: 神奈川
A87: 91 | B87: 45733 | C87: 3 | D87: 421178 | E87: 513-553153P | F87: 神奈川 | G87: 廣瀬 達 | H87: 高津区二子4-12 | I87: 高津区 | J87: ＤＧ入取替 | L87: 済 | M87: 45771 | N87: 4 | AA87: 25.8 | AB87: 40074015 | AC87: 8 | AD87: 神 | AE87: 27 | AF87: 213359 | AG87: 65 | AI87: 神奈川
A88: 92 | B88: 45733 | C88: 3 | D88: 421179 | E88: 513-553154P | F88: 神奈川 | G88: 青柳 亨 | H88: 中原区井田3-32 | I88: 中原区 | J88: ＤＧ入取替 | L88: 済 | M88: 45803 | N88: 5 | AA88: 25.6 | AB88: 40074017 | AC88: 6 | AD88: 神 | AE88: 27 | AF88: 199489 | AG88: 58 | AI88: 神奈川
A89: 93 | B89: 45733 | C89: 3 | D89: 421180 | E89: 513-553156P | F89: 神奈川 | G89: 青柳 亨 | H89: 中原区木月3-47 | I89: 中原区 | J89: ＤＧ入取替 | L89: 済 | M89: 45763 | N89: 4 | AA89: 25.6 | AB89: 40074021 | AC89: 6 | AD89: 神 | AE89: 27 | AF89: 197754 | AG89: 63 | AI89: 神奈川
A90: 94 | B90: 45733 | C90: 3 | D90: 421181 | E90: 513-553131P | F90: 神奈川 | G90: 米山 直人 | H90: 川崎区浜町3-3 | I90: 川崎区 | J90: ＤＧ入取替 | L90: 済 | M90: 45838 | N90: 6 | O90: 設備 | P90: 本社 | AA90: 25.9 | AB90: 40074024 | AC90: 9 | AD90: 湘 | AE90: 27 | AF90: 207752 | AG90: 62 | AH90: 57979 | AI90: 神奈川
A91: 95 | B91: 45733 | C91: 3 | D91: 421182 | E91: 513-553157P | F91: 神奈川 | G91: 萬條 秀馬 | H91: 高津区下作延1-7 | I91: 高津区 | J91: ＤＧ入取替 | L91: 済 | M91: 45869 | N91: 7 | AA91: 25.9 | AB91: 40074026 | AC91: 9 | AD91: 湘 | AE91: 27 | AF91: 271724 | AG91: 72 | AI91: 神奈川
A92: 96 | B92: 45733 | C92: 3 | D92: 421183 | E92: 513-653127J | F92: 神奈川 | G92: 廣瀬 達 | H92: 川崎区渡田3-16 | I92: 川崎区 | J92: ＤＧ入取替（大規模一括件名） | L92: 45861 | M92: 45887 | N92: 8 | P92: 共立 | Q92: 45827 | R92: 25.6 | S92: 103490 | AA92: 25.12 | AB92: 40074032 | AC92: 12 | AD92: 神 | AE92: 27 | AF92: 439146 | AG92: 423 | AI92: 神奈川
A93: 97 | B93: 45734 | C93: 3 | D93: 421184 | E93: 513-042215X | F93: 神奈川 | G93: 水上 知輝 | H93: 幸区南幸町3-125 | I93: 幸区南 | J93: 設計変更 | L93: 済 | M93: 45768 | N93: 4 | AA93: 25.7 | AB93: 40073855 | AC93: 7 | AD93: 神 | AE93: 27 | AF93: 42649 | AI93: 神奈川
A94: 98 | B94: 45734 | C94: 3 | D94: 421186 | E94: 512-553201P | F94: 神奈川 | G94: 廣瀬 達 | H94: 青葉区しらとり台38 | I94: 青葉区 | J94: ＤＧ入取替 | L94: 済 | M94: 45775 | N94: 4 | AA94: 25.6 | AB94: 40074217 | AC94: 6 | AD94: 神 | AE94: 27 | AF94: 283137 | AG94: 87 | AI94: 神奈川
A95: 99 | B95: 45734 | C95: 3 | D95: 421191 | E95: 515-519270X | F95: 湘南 | G95: 山田 智史 | H95: 海老名市大谷北3-4 | I95: 海老名 | J95: 海老名市大谷北３－４地区 | L95: 済 | M95: 45771 | N95: 4 | AA95: 25.7 | AB95: 40074583 | AC95: 7 | AD95: 湘 | AE95: 46 | AF95: 380638 | AG95: 243 | AI95: 神奈川
A96: 100 | B96: 45735 | C96: 3 | D96: 421193 | E96: 512-342183P | F96: 神奈川 | G96: 水上 知輝 | H96: 港北区綱島西4-8 | I96: 港北区 | J96: 設計変更 | L96: 済 | M96: 45743 | N96: 3 | AA96: 25.7 | AB96: 40074275 | AC96: 7 | AD96: 神 | AE96: 27 | AF96: 45152 | AI96: 神奈川
A97: 101 | B97: 45735 | C97: 3 | D97: 421195 | E97: 512-653153J | F97: 神奈川 | G97: 佐藤 竜 | H97: 港北区日吉本町1-13 | I97: 港北区 | J97: ＤＧ入取替（大規模一括件名） | L97: 済 | M97: 45833 | N97: 6 | P97: みつば | Q97: 45768 | R97: 25.4 | AA97: 25.7 | AB97: 40074363 | AC97: 7 | AD97: 神 | AE97: 27 | AF97: 362548 | AG97: 215 | AI97: 神奈川
A98: 102 | B98: 45737 | C98: 3 | D98: 421197 | E98: 512-553203P | F98: 神奈川 | G98: 山田 敏雄 | H98: 鶴見区下末吉1-9 | I98: 鶴見区 | J98: ＤＧ入取替 | L98: 済 | M98: 45821 | N98: 6 | AA98: 25.8 | AB98: 40074483 | AC98: 8 | AD98: 神 | AE98: 27 | AF98: 283424 | AG98: 56 | AI98: 神奈川
A99: 103 | B99: 45737 | C99: 3 | D99: 421198 | E99: 512-553204P | F99: 神奈川 | G99: 星 善輝 | H99: 鶴見区豊岡町22 | I99: 鶴見区 | J99: ＤＧ入取替 | L99: 済 | M99: 45807 | N99: 5 | O99: 設備 | P99: 本社 | AA99: 25.7 | AB99: 40074478 | AC99: 7 | AD99: 湘 | AE99: 27 | AF99: 251631 | AG99: 66 | AH99: 58617 | AI99: 神奈川
A100: 104 | B100: 45737 | C100: 3 | D100: 421199 | E100: 512-653156J | F100: 神奈川 | G100: 青柳 亨 | H100: 鶴見区北寺尾6-14 | I100: 鶴見区 | J100: ＤＧ入取替（大規模一括件名） | L100: 済 | M100: 45799 | N100: 5 | P100: みつば | Q100: 45768 | R100: 25.4 | AA100: 25.12 | AB100: 40074486 | AC100: 12 | AD100: 神 | AE100: 27 | AF100: 422751 | AG100: 229 | AI100: 神奈川
...

Sheet 杭台帳(多)
A1: 整理番号 | B1: 工事番号 | C1: 住 所 | D1: NC区分 | E1: 住所（行政区） | F1: 受注日 | G1: 受注月 | H1: 受注番号 | I1: 区分 | J1: 発行番号 | K1: 外注先 | L1: 納品月 | M1: 外注 発注月 | N1: 外注納品月 | O1: 工期 | P1: 製本受領 | Q1: 多摩フリ3 | R1: 外注支払月 | S1: 外注支払月(月のみ) | T1: 外注支払額 | U1: 入金月 | V1: 入金月（月のみ） | W1: 精算 グループ | X1: 入金額 | Y1: 復元杭引渡日 | Z1: 製本受領2 | AA1: 市提出 | AB1: 杭購入金額 | AF1: =SUM(X:X) -> 1.2674893e+08
A2: 1 | B2: 313-343065X | C2: 国分寺市本多5-25 | D2: 多摩 | E2: 国分寺 | F2: 44936 | G2: 1 | H2: 233513 | I2: 事前 | J2: 20036825 | K2: みつば | L2: 6 | M2: 2 | N2: 5 | P2: 45827 | R2: 45828 | S2: 6 | T2: 162000 | U2: 25.6 | V2: 6 | W2: 40 | X2: 273547
A3: 2 | B3: 313-343014X | C3: 立川市栄町3-24 | D3: 多摩 | E3: 立川市 | F3: 44942 | G3: 1 | H3: 233581 | I3: 事前 | J3: 20038319 | K3: みつば | L3: 7 | M3: 5 | N3: 7 | R3: 45861 | S3: 7 | T3: 85490 | U3: 25.7 | V3: 7 | W3: 40 | X3: 173514
A4: 3 | B4: 313-343017X | C4: 東村山市秋津町5-6 | D4: 多摩 | E4: 東村山 | F4: 44942 | G4: 1 | H4: 233590 | I4: 事前 | J4: 20038404
A5: 4 | B5: 313-242114E | C5: 八王子市中野山王1-5 | D5: 多摩 | E5: 八王子 | H5: 234013 | I5: 事前 | Y5: 45742 | AA5: 46035
A6: 5 | B6: 313-042102X | C6: 八王子市平岡町36 | D6: 多摩 | E6: 八王子 | H6: 330155 | I6: 事前 | AB6: 7050
A7: 6 | B7: 313-986704X | C7: 八王子市南町3 | D7: 多摩 | E7: 八王子 | H7: 330185 | I7: 事前 | Z7: 45908 | AA7: 45909
A8: 7 | B8: 313-486721C | C8: 東村山市本町1-16 | D8: 多摩 | E8: 東村山 | F8: 45309 | G8: 1 | H8: 330732 | I8: 事前 | J8: 30037925
A9: 8 | B9: 313-443034X | C9: 小平市仲町291 | D9: 多摩 | E9: 小平市 | F9: 45313 | G9: 1 | H9: 330737 | I9: 事前 | J9: 30040330
A10: 9 | B10: 313-443033X | C10: 小平市小川西町3-12 | D10: 多摩 | E10: 小平市 | F10: 45313 | G10: 1 | H10: 330738 | I10: 事前 | J10: 30040332
A11: 10 | B11: 313-443032X | C11: 小平市花小金井1-17 | D11: 多摩 | E11: 小平市 | F11: 45313 | G11: 1 | H11: 330739 | I11: 事前 | J11: 30040335 | K11: 共立 | L11: 9 | M11: 9 | N11: 9 | R11: 45922 | S11: 9 | T11: 76420 | U11: 25.9 | V11: 9 | W11: 40 | X11: 165891
A12: 11 | B12: 313-443031X | C12: 小平市学園東町3-1 | D12: 多摩 | E12: 小平市 | F12: 45313 | G12: 1 | H12: 330740 | I12: 事前 | J12: 30040338 | K12: みつば | L12: 7 | M12: 5 | N12: 7 | P12: 45873 | R12: 45861 | S12: 7 | T12: 90480 | U12: 25.7 | V12: 7 | W12: 40 | X12: 195028
A13: 12 | B13: 313-443038X | C13: 国分寺市泉町1-10 | D13: 多摩 | E13: 国分寺 | F13: 45327 | G13: 2 | H13: 330772 | I13: 事前 | J13: 30042239
A14: 13 | B14: 313-443043X | C14: 国立市中1-14 | D14: 多摩 | E14: 国立市 | F14: 45327 | G14: 2 | H14: 330773 | I14: 事前 | J14: 30042264
A15: 14 | B15: 313-443044X | C15: 国立市西2-3 | D15: 多摩 | E15: 国立市 | F15: 45327 | G15: 2 | H15: 330774 | I15: 事前 | J15: 30042261
A16: 15 | B16: 313-443015X | C16: 八王子市めじろ台1-41 | D16: 多摩 | E16: 八王子 | F16: 45327 | G16: 2 | H16: 330776 | I16: 事前 | J16: 30042236 | K16: 共立 | L16: 12 | M16: 11 | N16: 12 | R16: 46022 | S16: 12 | T16: 42920 | U16: 25.12 | V16: 12 | W16: 40 | X16: 87307
A17: 16 | B17: 313-443048X | C17: 東大和市南街2-101 | D17: 多摩 | E17: 東大和 | F17: 45328 | G17: 2 | H17: 330785 | I17: 事前 | J17: 30042191 | K17: 共立 | L17: 10 | M17: 9 | N17: 10 | U17: 25.1 | V17: 10 | W17: 40 | X17: 138194
A18: 17 | B18: 313-443040X | C18: 国分寺市東元町2-7 | D18: 多摩 | E18: 国分寺 | F18: 45328 | G18: 2 | H18: 330786 | I18: 事前 | J18: 30042215 | K18: みつば | L18: 6 | M18: 5 | N18: 6 | P18: 45834 | R18: 45828 | S18: 6 | T18: 254000 | U18: 25.6 | V18: 6 | W18: 40 | X18: 433462
A19: 18 | B19: 313-443039X | C19: 国分寺市東元町2-14 | D19: 多摩 | E19: 国分寺 | F19: 45328 | G19: 2 | H19: 330787 | I19: 事前 | J19: 30042219 | K19: みつば | L19: 6 | M19: 5 | N19: 6 | P19: 45834 | R19: 45828 | S19: 6 | T19: 242000 | U19: 25.6 | V19: 6 | W19: 40 | X19: 400443
A20: 19 | B20: 313-443049X | C20: 東大和市萩山町2-20 | D20: 多摩 | E20: 東大和 | F20: 45328 | G20: 2 | H20: 330791 | I20: 事前 | J20: 30042269
A21: 20 | B21: 313-242014M | C21: 国分寺市東恋ヶ窪2-23 | D21: 多摩 | E21: 国分寺 | F21: 45866 | G21: 7 | H21: 330811 | I21: 事前 | J21: 50021651 | K21: 共立 | L21: 8 | M21: 7 | N21: 7 | R21: 45891 | S21: 8 | T21: 57880 | U21: 25.8 | V21: 8 | W21: 40 | X21: 121416 | Y21: 45344
A22: 21 | B22: 313-486723A | C22: 多摩市鶴牧5-31 | D22: 多摩 | E22: 多摩市 | F22: 45356 | G22: 3 | H22: 330847 | I22: 事前 | J22: 30045999
A23: 22 | B23: 313-471713X | C23: 多摩市関戸5-16 | D23: 多摩 | E23: 多摩市 | F23: 45420 | G23: 5 | H23: 330987 | I23: 事前 | J23: 40018132 | K23: みつば | L23: 11 | M23: 7 | N23: 11 | O23: 46027 | R23: 45991 | S23: 11 | T23: 41750 | U23: 25.11 | V23: 11 | W23: 40 | X23: 86360
A24: 23 | B24: 313-342033M | C24: 日野市東平山1-7 | D24: 多摩 | E24: 日野市 | H24: 330997 | I24: 事前
A25: 24 | B25: 313-342043X | C25: 小平市学園西町3-23 | D25: 多摩 | E25: 小平市 | H25: 331087 | I25: 事前
A26: 25 | B26: 313-443051X | C26: 国分寺市東元町3-21 | D26: 多摩 | E26: 国分寺 | F26: 45454 | G26: 6 | H26: 430050 | I26: 事前 | J26: 40040729
A27: 26 | B27: 313-541001X | C27: 八王子市中野上町4-28 | D27: 多摩 | E27: 八王子 | F27: 45469 | G27: 6 | H27: 430100 | I27: 事前 | J27: 40043441 | K27: みつば | L27: 11 | M27: 7 | N27: 11 | R27: 45991 | S27: 11 | T27: 177010 | U27: 25.11 | V27: 11 | W27: 40 | X27: 366419
A28: 27 | B28: 313-541003X | C28: 八王子市中野上町5-10 | D28: 多摩 | E28: 八王子 | F28: 45469 | G28: 6 | H28: 430101 | I28: 事前 | J28: 40043446 | K28: みつば | L28: 11 | M28: 7 | N28: 11 | P28: 46001 | R28: 45991 | S28: 11 | T28: 207925 | U28: 25.11 | V28: 11 | W28: 40 | X28: 362384
A29: 28 | B29: 313-541004X | C29: 八王子市中野上町5-1 | D29: 多摩 | E29: 八王子 | F29: 45469 | G29: 6 | H29: 430102 | I29: 事前 | J29: 40043443 | K29: みつば | L29: 11 | M29: 7 | N29: 11 | P29: 46001 | R29: 45991 | S29: 11 | T29: 308215 | U29: 25.11 | V29: 11 | W29: 40 | X29: 529975
A30: 29 | B30: 313-541005X | C30: 八王子市中野上町5-5 | D30: 多摩 | E30: 八王子 | F30: 45469 | G30: 6 | H30: 430103 | I30: 事前 | J30: 40043442
A31: 30 | B31: 313-541012X | C31: 八王子市中野上町3-18 | D31: 多摩 | E31: 八王子 | F31: 45469 | G31: 6 | H31: 430104 | I31: 事前 | J31: 40043445 | K31: 共立 | L31: 11 | M31: 8 | N31: 11 | R31: 45991 | S31: 11 | T31: 62070 | U31: 25.11 | V31: 11 | W31: 40 | X31: 128457
A32: 31 | B32: 313-541013X | C32: 八王子市中野山王3-20 | D32: 多摩 | E32: 八王子 | F32: 45469 | G32: 6 | H32: 430105 | I32: 事前 | J32: 40043444 | K32: 共立 | L32: 11 | M32: 8 | N32: 11 | R32: 45991 | S32: 11 | T32: 63110 | U32: 25.11 | V32: 11 | W32: 40 | X32: 130614
A33: 32 | B33: 313-541017X | C33: 小平市大沼町4-43 | D33: 多摩 | E33: 小平市 | F33: 45469 | G33: 6 | H33: 430106 | I33: 事前 | J33: 40043530 | K33: みつば | L33: 12 | M33: 7 | P33: 46001 | R33: 46022 | S33: 12 | T33: 344425 | U33: 25.12 | V33: 12 | W33: 40 | X33: 596382
A34: 33 | B34: 313-541020F | C34: 国分寺市東元町2-20 | D34: 多摩 | E34: 国分寺 | F34: 45469 | G34: 6 | H34: 430107 | I34: 事前 | J34: 40043463 | K34: 共立 | L34: 12 | M34: 8 | N34: 12 | P34: 46016 | R34: 46022 | S34: 12 | T34: 133590 | U34: 25.12 | V34: 12 | W34: 40 | X34: 226883
A35: 34 | B35: 313-541002X | C35: 八王子市中野上町4-24 | D35: 多摩 | E35: 八王子 | F35: 45470 | G35: 6 | H35: 430112 | I35: 事前 | J35: 40043577 | K35: みつば | L35: 11 | M35: 7 | N35: 11 | R35: 45991 | S35: 11 | T35: 111790 | U35: 25.11 | V35: 11 | W35: 40 | X35: 231338
A36: 35 | B36: 313-541006F | C36: 八王子市中野上町2-24 | D36: 多摩 | E36: 八王子 | F36: 45470 | G36: 6 | H36: 430113 | I36: 事前 | J36: 40043609 | K36: みつば | L36: 11 | M36: 7 | N36: 11 | P36: 46001 | R36: 45991 | S36: 11 | T36: 188745 | U36: 25.11 | V36: 11 | W36: 40 | X36: 340152
A37: 36 | B37: 313-541007X | C37: 八王子市中野上町4-43 | D37: 多摩 | E37: 八王子 | F37: 45470 | G37: 6 | H37: 430114 | I37: 事前 | J37: 40043568 | K37: みつば | L37: 11 | M37: 7 | N37: 11 | R37: 45991 | S37: 11 | T37: 82830 | U37: 25.11 | V37: 11 | W37: 40 | X37: 171399
A38: 37 | B38: 313-541008X | C38: 八王子市中野上町4-40 | D38: 多摩 | E38: 八王子 | F38: 45470 | G38: 6 | H38: 430115 | I38: 事前 | J38: 40043598 | K38: みつば | L38: 11 | M38: 7 | N38: 11 | R38: 45991 | S38: 11 | T38: 100490 | U38: 25.11 | V38: 11 | W38: 40 | X38: 207972
A39: 38 | B39: 313-541009F | C39: 八王子市中野上町2-32 | D39: 多摩 | E39: 八王子 | F39: 45470 | G39: 6 | H39: 430116 | I39: 事前 | J39: 40043602 | K39: 共立 | L39: 11 | M39: 8 | N39: 11 | R39: 45991 | S39: 11 | T39: 70250 | U39: 25.11 | V39: 11 | W39: 40 | X39: 145351
A40: 39 | B40: 313-541010X | C40: 八王子市中野上町4-10 | D40: 多摩 | E40: 八王子 | F40: 45470 | G40: 6 | H40: 430117 | I40: 事前 | J40: 40043590 | K40: 共立 | L40: 10 | M40: 8 | N40: 10 | U40: 25.1 | V40: 10 | W40: 40 | X40: 96622
A41: 40 | B41: 313-541011X | C41: 八王子市中野山王3-1 | D41: 多摩 | E41: 八王子 | F41: 45470 | G41: 6 | H41: 430118 | I41: 事前 | J41: 40043612 | K41: 共立 | L41: 11 | M41: 8 | N41: 11 | R41: 45991 | S41: 11 | T41: 55710 | U41: 25.11 | V41: 11 | W41: 40 | X41: 115251
A42: 41 | B42: 313-541014X | C42: 八王子市大和田町6-12 | D42: 多摩 | E42: 八王子 | F42: 45470 | G42: 6 | H42: 430119 | I42: 事前 | J42: 40043641 | K42: みつば | L42: 11 | M42: 7 | N42: 11 | P42: 46001 | R42: 45991 | S42: 11 | T42: 188745 | U42: 25.11 | V42: 11 | W42: 40 | X42: 340152
A43: 42 | B43: 313-541015X | C43: 八王子市台町3-19 | D43: 多摩 | E43: 八王子 | F43: 45470 | G43: 6 | H43: 430120 | I43: 事前 | J43: 40043618 | K43: みつば | L43: 12 | M43: 7 | P43: 46001 | R43: 46022 | S43: 12 | T43: 138600 | U43: 25.12 | V43: 12 | W43: 40 | X43: 246983
A44: 43 | B44: 313-541019X | C44: 東村山市萩山町1-11 | D44: 多摩 | E44: 東村山 | F44: 45477 | G44: 7 | H44: 430161 | I44: 事前 | J44: 40044711 | K44: 共立 | L44: 12 | M44: 8 | N44: 11 | P44: 46000 | R44: 46022 | S44: 12 | T44: 134735 | U44: 25.12 | V44: 12 | W44: 40 | X44: 240345
A45: 44 | B45: 313-541018X | C45: 東村山市萩山町5-6 | D45: 多摩 | E45: 東村山 | F45: 45477 | G45: 7 | H45: 430162 | I45: 事前 | J45: 40044712 | K45: 共立 | L45: 10 | M45: 8 | N45: 10 | U45: 25.1 | V45: 10 | W45: 40 | X45: 68678
A46: 45 | B46: 313-443054X | C46: 東村山市青葉町2-5 | D46: 多摩 | E46: 東村山 | F46: 45477 | G46: 7 | H46: 430163 | I46: 事前 | J46: 40044710 | K46: 共立 | M46: 5
A47: 46 | B47: 313-541016X | C47: 小平市学園西町1-2 | D47: 多摩 | E47: 小平市 | F47: 45478 | G47: 7 | H47: 430173 | I47: 事前 | J47: 40044992 | K47: 共立 | L47: 10 | M47: 8 | N47: 10 | P47: 45952 | U47: 25.1 | V47: 10 | W47: 40 | X47: 105594
A48: 47 | B48: 313-442008I | C48: 小平市学園西町3-8 | D48: 多摩 | E48: 小平市 | H48: 430247 | I48: 事前 | Y48: 45604
A49: 48 | B49: 313-442009I | C49: 小平市学園西町3-5 | D49: 多摩 | E49: 小平市 | H49: 430248 | I49: 事前 | Y49: 45524
A50: 49 | B50: 313-586717X | C50: 八王子市大船町182 | D50: 多摩 | E50: 八王子 | F50: 45510 | G50: 8 | H50: 430251 | I50: 事前 | J50: 40048320
A51: 50 | B51: 313-400481S | C51: 立川市曙町3-27-8 | D51: 多摩 | E51: 立川市 | H51: 430296 | I51: 事前 | Z51: 45980
A52: 51 | B52: 313-412023X | C52: 八王子市下柚木2-31 | D52: 多摩 | E52: 八王子 | H52: 430400 | I52: 事前 | Z52: 45861 | AA52: 45876
A53: 52 | B53: 313-671706X | C53: 立川市柴崎町1-1 | D53: 多摩 | E53: 立川市 | F53: 45589 | G53: 10 | H53: 430466 | I53: 事前 | J53: 40056925 | K53: みつば | M53: 2
A54: 53 | B54: 313-541025X | C54: 国分寺市戸倉2-5 | D54: 多摩 | E54: 国分寺 | F54: 45604 | G54: 11 | H54: 430525 | I54: 事前 | J54: 40058559
A55: 54 | B55: 313-541026X | C55: 国分寺市西恋ヶ窪1-46 | D55: 多摩 | E55: 国分寺 | F55: 45604 | G55: 11 | H55: 430526 | I55: 事前 | J55: 40058557
A56: 55 | B56: 313-541028X | C56: 国分寺市戸倉1-7 | D56: 多摩 | E56: 国分寺 | F56: 45604 | G56: 11 | H56: 430527 | I56: 事前 | J56: 40058556
A57: 56 | B57: 313-541029X | C57: 日野市新井3-1 | D57: 多摩 | E57: 日野市 | F57: 45602 | G57: 11 | H57: 430528 | I57: 事前 | J57: 40058423
A58: 57 | B58: 313-541030X | C58: 東村山市美住町1-13 | D58: 多摩 | E58: 東村山 | F58: 45603 | G58: 11 | H58: 430529 | I58: 事前 | J58: 40058395
A59: 58 | B59: 313-541031X | C59: 東村山市富士見町1-14 | D59: 多摩 | E59: 東村山 | F59: 45603 | G59: 11 | H59: 430530 | I59: 事前 | J59: 40058393
A60: 59 | B60: 313-541032X | C60: 東村山市美住町1-4 | D60: 多摩 | E60: 東村山 | F60: 45603 | G60: 11 | H60: 430531 | I60: 事前 | J60: 40058392
A61: 60 | B61: 313-541033X | C61: 東大和市清水5-1003 | D61: 多摩 | E61: 東大和 | F61: 45603 | G61: 11 | H61: 430532 | I61: 事前 | J61: 40058375
A62: 61 | B62: 313-541035X | C62: 小平市花小金井3-43 | D62: 多摩 | E62: 小平市 | F62: 45604 | G62: 11 | H62: 430533 | I62: 事前 | J62: 40058750
A63: 62 | B63: 313-541036X | C63: 小平市喜平町3-2 | D63: 多摩 | E63: 小平市 | F63: 45604 | G63: 11 | H63: 430534 | I63: 事前 | J63: 40058741
A64: 63 | B64: 313-541037X | C64: 小平市喜平町3-3 | D64: 多摩 | E64: 小平市 | F64: 45604 | G64: 11 | H64: 430535 | I64: 事前 | J64: 40058738
A65: 64 | B65: 313-541038X | C65: 八王子市大和田町4-12 | D65: 多摩 | E65: 八王子 | F65: 45602 | G65: 11 | H65: 430536 | I65: 事前 | J65: 40058411
... A83: 82 | B83: 313-541024X | C83: 小平市喜平町3-3 | D83: 多摩 | E83: 小平市 | F83: 45621 | G83: 11 | H83: 430581 | I83: 事前 | J83: 40060360
A84: 83 | B84: 313-544002X | C84: 八王子市中野上町2-14 | D84: 多摩 | E84: 八王子 | F84: 45621 | G84: 11 | H84: 430582 | I84: 事前 | J84: 40060558 | K84: みつば | L84: 6 | M84: 5 | N84: 6 | P84: 45827 | R84: 45828 | S84: 6 | T84: 100000 | U84: 25.6 | V84: 6 | W84: 40 | X84: 198639
A85: 84 | B85: 313-316489X | C85: 日野市落川577 | D85: 多摩 | E85: 日野市 | H85: 430583 | I85: 事前 | Y85: 45625 | Z85: 45954 | AA85: 45958
A86: 85 | B86: 313-412003X | C86: 小平市小川町1-2438 | D86: 多摩 | E86: 小平市 | H86: 430601 | I86: 事前 | Z86: 46042 | AA86: 46052
A87: 86 | B87: 313-576801X | C87: 国分寺市南町3-25 | D87: 多摩 | E87: 国分寺 | F87: 45630 | G87: 12 | H87: 430616 | I87: 事前 | J87: 40061471 | K87: みつば | L87: 7 | M87: 1 | N87: 7 | P87: 45873 | R87: 45861 | S87: 7 | T87: 121635 | U87: 25.7 | V87: 7 | W87: 40 | X87: 261486 | Z87: 46042 | AA87: 46052
A88: 87 | B88: 313-541063X | C88: 多摩市一ノ宮3-9 | D88: 多摩 | E88: 多摩市 | F88: 45643 | G88: 12 | H88: 430651 | I88: 事前 | J88: 40063189
A89: 88 | B89: 313-543013X | C89: 国立市東1-20 | D89: 多摩 | E89: 国立市 | F89: 45645 | G89: 12 | H89: 430663 | I89: 事前 | J89: 40063471 | K89: みつば | L89: 11 | M89: 10 | N89: 11 | P89: 45978 | R89: 45991 | S89: 11 | T89: 76200 | U89: 25.11 | V89: 11 | W89: 40 | X89: 165093
A90: 89 | B90: 313-543040X | C90: 立川市錦町5-14 | D90: 多摩 | E90: 立川市 | F90: 45645 | G90: 12 | H90: 430667 | I90: 事前 | J90: 40063462 | K90: みつば | L90: 6 | M90: 5 | N90: 6 | P90: 45834 | R90: 45828 | S90: 6 | T90: 285925 | U90: 25.6 | V90: 6 | W90: 40 | X90: 607771
A91: 90 | B91: 313-543041X | C91: 立川市錦町5-2 | D91: 多摩 | E91: 立川市 | F91: 45645 | G91: 12 | H91: 430668 | I91: 事前 | J91: 40063463 | K91: みつば | L91: 6 | M91: 5 | N91: 6 | R91: 45828 | S91: 6 | T91: 56290 | U91: 25.6 | V91: 6 | W91: 40 | X91: 120200
A92: 91 | B92: 313-543042X | C92: 立川市柴崎町3-13 | D92: 多摩 | E92: 立川市 | F92: 45645 | G92: 12 | H92: 430669 | I92: 事前 | J92: 40063464 | K92: 共立 | L92: 8 | M92: 6 | N92: 8 | P92: 45910 | R92: 45891 | S92: 8 | T92: 53860 | U92: 25.8 | V92: 8 | W92: 40 | X92: 128099
A93: 92 | B93: 313-543043X | C93: 立川市柴崎町3-17 | D93: 多摩 | E93: 立川市 | F93: 45645 | G93: 12 | H93: 430670 | I93: 事前 | J93: 40063465
A94: 93 | B94: 313-543044X | C94: 立川市柴崎町3-18 | D94: 多摩 | E94: 立川市 | F94: 45645 | G94: 12 | H94: 430671 | I94: 事前 | J94: 40063466
A95: 94 | B95: 313-543045X | C95: 立川市柴崎町3-15 | D95: 多摩 | E95: 立川市 | F95: 45645 | G95: 12 | H95: 430672 | I95: 事前 | J95: 40063467
A96: 94 | B96: 442-408193 | C96: 小平市学園西町1-11 | D96: 多摩 | E96: 小平市 | H96: 530104 | I96: 事前 | Z96: 45905 | AA96: 45911
A97: 95 | B97: 313-543046X | C97: 立川市若葉町2-6 | D97: 多摩 | E97: 立川市 | F97: 45645 | G97: 12 | H97: 430673 | I97: 事前 | J97: 40063468 | K97: みつば | L97: 7 | M97: 5 | N97: 7 | R97: 45861 | S97: 7 | T97: 108210 | U97: 25.7 | V97: 7 | W97: 40 | X97: 231178
A98: 96 | B98: 313-543047X | C98: 立川市若葉町2-19 | D98: 多摩 | E98: 立川市 | F98: 45645 | G98: 12 | H98: 430674 | I98: 事前 | J98: 40063469
A99: 97 | B99: 313-543048X | C99: 立川市若葉町2-32 | D99: 多摩 | E99: 立川市 | F99: 45645 | G99: 12 | H99: 430675 | I99: 事前 | J99: 40063470 | K99: みつば | L99: 7 | M99: 5 | N99: 7 | R99: 45861 | S99: 7 | T99: 83650 | U99: 25.7 | V99: 7 | W99: 40 | X99: 178701
A100: 98 | B100: 313-543024X | C100: 八王子市明神町4-23 | D100: 多摩 | E100: 八王子 | F100: 45645 | G100: 12 | H100: 430676 | I100: 事前 | J100: 40063562 | K100: みつば | L100: 5 | M100: 2 | N100: 5 | P100: 45827 | R100: 25 | S100: 1 | U100: 25.6 | V100: 6 | W100: 40 | X100: 566445
A101: 99 | B101: 313-543022X | C101: 東大和市向原1-1881 | D101: 多摩 | E101: 東大和 | F101: 45645 | G101: 12 | H101: 430678 | I101: 事前 | J101: 40063458 | K101: みつば | L101: 6 | M101: 5 | N101: 6 | P101: 45834 | R101: 45828 | S101: 6 | T101: 210000 | U101: 25.6 | V101: 6 | W101: 40 | X101: 371586
A102: 100 | B102: 313-543025X | C102: 八王子市富士見町20 | D102: 多摩 | E102: 八王子 | F102: 45645 | G102: 12 | H102: 430682 | I102: 事前 | J102: 40063563 | K102: みつば | L102: 9 | M102: 7 | N102: 9 | P102: 45947 | R102: 45926 | S102: 9 | T102: 100000 | U102: 25.9 | V102: 9 | W102: 40 | X102: 190744
A103: 101 | B103: 313-543026X | C103: 八王子市富士見町23 | D103: 多摩 | E103: 八王子 | F103: 45645 | G103: 12 | H103: 430683 | I103: 事前 | J103: 40063564 | K103: みつば | L103: 9 | M103: 7 | N103: 9 | P103: 45947 | R103: 45926 | S103: 9 | T103: 100000 | U103: 25.9 | V103: 9 | W103: 40 | X103: 200534
A104: 102 | B104: 313-543029X | C104: 八王子市暁町1-5 | D104: 多摩 | E104: 八王子 | F104: 45645 | G104: 12 | H104: 430686 | I104: 事前 | J104: 40063588 | K104: みつば | L104: 5 | M104: 2 | N104: 5 | P104: 45827 | R104: 25 | S104: 1 | U104: 25.6 | V104: 6 | W104: 40 | X104: 408724
A105: 103 | B105: 313-543034X | C105: 八王子市中野町2546 | D105: 多摩 | E105: 八王子 | F105: 45645 | G105: 12 | H105: 430690 | I105: 事前 | J105: 40063615 | K105: みつば | L105: 6 | M105: 5 | N105: 6 | R105: 45828 | S105: 6 | T105: 46830 | U105: 25.6 | V105: 6 | W105: 40 | X105: 99981
A106: 104 | B106: 313-543035X | C106: 八王子市中野町2550 | D106: 多摩 | E106: 八王子 | F106: 45645 | G106: 12 | H106: 430691 | I106: 事前 | J106: 40063616 | K106: みつば | L106: 6 | M106: 5 | N106: 6 | R106: 45828 | S106: 6 | T106: 88370 | U106: 25.6 | V106: 6 | W106: 40 | X106: 188777
A107: 105 | B107: 313-543036X | C107: 八王子市中野山王2-32 | D107: 多摩 | E107: 八王子 | F107: 45645 | G107: 12 | H107: 430692 | I107: 事前 | J107: 40063623 | K107: みつば | L107: 7 | M107: 5 | N107: 7 | R107: 45861 | S107: 7 | T107: 94610 | U107: 25.7 | V107: 7 | W107: 40 | X107: 202127
A108: 106 | B108: 313-543037X | C108: 八王子市みつい台1-3 | D108: 多摩 | E108: 八王子 | F108: 45645 | G108: 12 | H108: 430693 | I108: 事前 | J108: 40063630 | K108: みつば | L108: 9 | M108: 7 | N108: 9 | P108: 45947 | R108: 45926 | S108: 9 | T108: 143000 | U108: 25.9 | V108: 9 | W108: 40 | X108: 271711
A109: 107 | B109: 313-543038X | C109: 八王子市みつい台1-27 | D109: 多摩 | E109: 八王子 | F109: 45645 | G109: 12 | H109: 430694 | I109: 事前 | J109: 40063636 | K109: みつば | L109: 9 | M109: 7 | N109: 9 | R109: 45926 | S109: 9 | T109: 50410 | U109: 25.9 | V109: 9 | W109: 40 | X109: 107637
A110: 108 | B110: 313-543039X | C110: 八王子市丸山町15 | D110: 多摩 | E110: 八王子 | F110: 45645 | G110: 12 | H110: 430695 | I110: 事前 | J110: 40063640 | K110: みつば | L110: 9 | M110: 7 | N110: 9 | P110: 45947 | R110: 45926 | S110: 9 | T110: 100000 | U110: 25.9 | V110: 9 | W110: 40 | X110: 190744
A111: 109 | B111: 313-541059X | C111: 八王子市大和田町5-2 | D111: 多摩 | E111: 八王子 | F111: 45649 | G111: 12 | H111: 430705 | I111: 事前 | J111: 40063923
A112: 110 | B112: 313-541061X | C112: 八王子市明神町2-20 | D112: 多摩 | E112: 八王子 | F112: 45649 | G112: 12 | H112: 430706 | I112: 事前 | J112: 40063926
A113: 111 | B113: 313-543023X | C113: 八王子市明神町4-9 | D113: 多摩 | E113: 八王子 | F113: 45649 | G113: 12 | H113: 430707 | I113: 事前 | J113: 40063927 | K113: みつば | L113: 9 | M113: 7 | N113: 9 | P113: 45947 | R113: 45926 | S113: 9 | T113: 100000 | U113: 25.9 | V113: 9 | W113: 40 | X113: 200534
A114: 112 | B114: 313-543005X | C114: 小平市学園東町3-6 | D114: 多摩 | E114: 小平市 | F114: 45649 | G114: 12 | H114: 430708 | I114: 事前 | J114: 40063938 | K114: 共立 | L114: 7 | M114: 6 | N114: 7 | P114: 45890 | R114: 45860 | S114: 7 | T114: 114760 | U114: 25.7 | V114: 7 | W114: 40 | X114: 251318
A115: 113 | B115: 313-541064X | C115: 多摩市和田1261 | D115: 多摩 | E115: 多摩市 | F115: 45649 | G115: 12 | H115: 430709 | I115: 事前 | J115: 40063940
A116: 114 | B116: 313-541066X | C116: 日野市日野本町5-11 | D116: 多摩 | E116: 日野市 | F116: 45649 | G116: 12 | H116: 430710 | I116: 事前 | J116: 40063943
A117: 115 | B117: 313-541068X | C117: 日野市落川334 | D117: 多摩 | E117: 日野市 | F117: 45649 | G117: 12 | H117: 430711 | I117: 事前 | J117: 40063946
...

Sheet 杭台帳(西)
A1: 整理番号 | B1: 工事番号 | C1: 住 所 | D1: NC区分 | E1: 住所（行政区） | F1: 受注日 | G1: 受注月 | H1: 受注番号 | I1: 区分 | J1: 発行番号 | K1: 外注先 | L1: 納品月 | M1: 外注 発注月 | N1: 外注納品月 | O1: 工期 | P1: 現場完了 予定日 | Q1: 現場予定日 | R1: 外注支払月 | S1: 外注支払月(月のみ) | T1: 外注支払額 | U1: 入金月 | V1: 入金月（月のみ） | W1: 精算 グループ | X1: 入金額 | Y1: 顧客会社担当者(後) | Z1: 申請 提出日 (ガスor役所)2 | AA1: 現場完了 予定日3 | AB1: 現場予定日（後） | AC1: 杭購入金額 | AE1: =SUM(W:W) -> 62611
A2: 1 | B2: 311-242242X | C2: 世田谷区玉川4-29 | D2: 西部 | E2: 世田谷 | F2: 44767 | G2: 7 | H2: 410001 | I2: 事前 | J2: 20015548 | K2: みつば | L2: 6 | M2: 4 | N2: 6 | O2: 未定 | P2: 45789 | R2: 45838 | S2: 6 | T2: 103235 | U2: 25.6 | V2: 6 | W2: 30 | X2: 252391
A3: 2 | B3: 311-042334X | C3: 三鷹市牟礼6-25 | D3: 西部 | E3: 三鷹市 | H3: 410002
A4: 3 | B4: 311-142157J | C4: 世田谷区赤堤1-36 | D4: 西部 | E4: 世田谷 | H4: 410003
A5: 4 | B5: 311-145026B | C5: 世田谷区玉川台2-28 | D5: 西部 | E5: 世田谷 | H5: 410004
A6: 5 | B6: 332-116370 | C6: 大田区東蒲田2-30 | D6: 南部 | E6: 大田区 | H6: 410005 | Y6: 8700
A7: 6 | B7: 311-042493X | C7: 世田谷区駒沢2-7 | D7: 西部 | E7: 世田谷 | H7: 410006
A8: 7 | B8: 311-042079W | C8: 世田谷区等々力2-9 | D8: 西部 | E8: 世田谷 | H8: 410007
A9: 8 | B9: 311-142137I | C9: 世田谷区経堂3-29 | D9: 西部 | E9: 世田谷 | H9: 410008
A10: 9 | B10: 113-041152Y | C10: 大田区大森中3-15-18 | D10: 南部 | E10: 大田区 | H10: 410009
A11: 10 | B11: 113-212032X | C11: 大田区中央4-13-8 | D11: 南部 | E11: 大田区 | H11: 410010
A12: 11 | B12: 311-443203X | C12: 三鷹市井の頭2-34 | D12: 西部 | E12: 三鷹市 | F12: 45324 | G12: 2 | H12: 410011 | I12: 事前 | J12: 30042041 | K12: 星 | L12: 7 | M12: 4 | N12: 7 | O12: 45566 | R12: 45869 | S12: 7 | T12: 109610 | U12: 25.7 | V12: 7 | W12: 30 | X12: 189640
A13: 12 | B13: 311-242100F | C13: 世田谷区用賀1-20 | D13: 西部 | E13: 世田谷 | H13: 410012
A14: 13 | B14: 113-342532X | C14: 大田区山王1-37-6 | D14: 南部 | E14: 大田区 | H14: 410013
A15: 14 | B15: 113-342533X | C15: 大田区山王1-29-9 | D15: 南部 | E15: 大田区 | H15: 410014
A16: 15 | B16: 113-319020X | C16: 大田区東糀谷4-10 | D16: 南部 | E16: 大田区 | H16: 410015
A17: 16 | B17: 332-105530 | C17: 大田区山王1-38 | D17: 南部 | E17: 大田区 | H17: 410016 | Y17: 8700
A18: 17 | B18: 113-311064X | C18: 大田区大森本町2-29-1 | D18: 南部 | E18: 大田区 | H18: 410017
A19: 18 | B19: 411-319094A | C19: 和光市下新倉4-4 | D19: 北部 | E19: 和光市 | H19: 410018
A20: 19 | B20: 113-541508X | C20: 大田区西六郷1-5-3 | D20: 南部 | E20: 大田区 | F20: 45433 | G20: 5 | H20: 410019 | I20: 事前 | J20: 40033208 | K20: みつば | M20: 2 | O20: 45931 | P20: -
A21: 20 | B21: 113-590023X | C21: 大田区蒲田3-24-4 | D21: 南部 | E21: 大田区 | F21: 45433 | G21: 5 | H21: 410020 | I21: 事前 | J21: 40036427 | K21: みつば | M21: 10 | O21: 45931 | P21: -
A22: 21 | B22: 113-590024X | C22: 大田区羽田4-4-29 | D22: 南部 | E22: 大田区 | F22: 45433 | G22: 5 | H22: 410021 | I22: 事前 | J22: 40036424 | K22: みつば | L22: 10 | M22: 9 | N22: 10 | O22: 45931 | R22: 45961 | S22: 10 | T22: 32750 | U22: 25.1 | V22: 10 | W22: 10 | X22: 58910
A23: 22 | B23: 113-541509X | C23: 大田区東蒲田2-29-16 | D23: 南部 | E23: 大田区 | F23: 45433 | G23: 5 | H23: 410022 | I23: 事前 | J23: 40036422 | K23: みつば | L23: 10 | M23: 7 | N23: 10 | O23: 45931 | P23: - | Q23: 8/18 | R23: 45961 | S23: 10 | T23: 106680 | U23: 25.11 | V23: 11 | W23: 10 | X23: 152876
A24: 23 | B24: 113-541512X | C24: 大田区東糀谷4-6-5 | D24: 南部 | E24: 大田区 | F24: 45433 | G24: 5 | H24: 410023 | I24: 事前 | J24: 40036423 | K24: みつば | L24: 10 | M24: 7 | N24: 10 | O24: 45931 | P24: - | Q24: 8/18 | R24: 45961 | S24: 10 | T24: 49300 | U24: 25.11 | V24: 11 | W24: 10 | X24: 83405
A25: 24 | B25: 113-541506X | C25: 大田区千鳥3-15-1 | D25: 南部 | E25: 大田区 | F25: 45435 | G25: 5 | H25: 410024 | I25: 事前 | J25: 40038124 | K25: みつば | L25: 9 | M25: 7 | N25: 9 | O25: 45931 | P25: - | Q25: 8/18 | R25: 45930 | S25: 9 | T25: 60270 | U25: 25.9 | V25: 9 | W25: 10 | X25: 102698
A26: 25 | B26: 113-541507X | C26: 大田区西蒲田7-60-9 | D26: 南部 | E26: 大田区 | F26: 45435 | G26: 5 | H26: 410025 | I26: 事前 | J26: 40038231 | K26: みつば | L26: 2 | M26: 7 | N26: 2 | O26: 45931 | P26: - | Q26: 8/18 | R26: 46081 | S26: 2 | T26: 123580 | U26: 26.2 | V26: 2 | W26: 10 | X26: 216005
A27: 26 | B27: 113-590022X | C27: 大田区大森北3-30-5 | D27: 南部 | E27: 大田区 | F27: 45440 | G27: 5 | H27: 410026 | I27: 事前 | J27: 40038797 | K27: みつば | L27: 8 | M27: 7 | N27: 8 | O27: 45931 | P27: - | Q27: 8/9 | R27: 45891 | S27: 8 | T27: 58310 | U27: 25.8 | V27: 8 | W27: 10 | X27: 99369
A28: 27 | B28: 113-541511X | C28: 大田区大森南3-8-1 | D28: 南部 | E28: 大田区 | F28: 45440 | G28: 5 | H28: 410027 | I28: 事前 | J28: 40038798 | K28: みつば | L28: 10 | M28: 7 | N28: 10 | O28: 45931 | P28: - | Q28: 7/25 | R28: 45961 | S28: 10 | T28: 213505 | U28: 25.11 | V28: 11 | W28: 10 | X28: 299306
A29: 28 | B29: 113-315022X | C29: 大田区多摩川2-12-25 | D29: 南部 | E29: 大田区 | H29: 410028
A30: 29 | B30: 113-312092X | C30: 大田区田園調布5-15-23 | D30: 南部 | E30: 大田区 | H30: 410029
A31: 30 | B31: 113-541510F | C31: 大田区大森東2-19-10 | D31: 南部 | E31: 大田区 | F31: 45448 | G31: 6 | H31: 410030 | I31: 事前 | J31: 40039941 | K31: みつば | M31: 6
A32: 31 | B32: 113-541505F | C32: 大田区西馬込2-34-1 | D32: 南部 | E32: 大田区 | F32: 45448 | G32: 6 | H32: 410031 | I32: 事前 | J32: 40039920 | K32: みつば | M32: 6
A33: 32 | B33: 411-316233A | C33: 新座市西堀1-11 | D33: 北部 | E33: 新座市 | H33: 410032 | Y33: 松田 | Z33: 8/5JP
A34: 33 | B34: 311-541030X | C34: 清瀬市元町2-10 | D34: 西部 | E34: 清瀬市 | F34: 45461 | G34: 6 | H34: 410033 | I34: 事前 | J34: 40041970 | K34: 星 | L34: 6 | M34: 4 | N34: 6 | O34: 45931 | P34: 45789 | R34: 45838 | S34: 6 | T34: 234250 | U34: 25.6 | V34: 6 | W34: 30 | X34: 401642
A35: 34 | B35: 311-541011X | C35: 東久留米市滝山6-2 | D35: 西部 | E35: 東久留 | F35: 45461 | G35: 6 | H35: 410034 | I35: 事前 | J35: 40041993 | K35: 星 | O35: 45931 | P35: -
A36: 35 | B36: 311-541010X | C36: 東久留米市滝山6-2 | D36: 西部 | E36: 東久留 | F36: 45461 | G36: 6 | H36: 410035 | I36: 事前 | J36: 40041995 | K36: 星 | O36: 45931 | P36: -
A37: 36 | B37: 311-641019X | C37: 東久留米市南沢3-1 | D37: 西部 | E37: 東久留 | F37: 45461 | G37: 6 | H37: 410036 | I37: 事前 | J37: 40041998 | K37: 星 | L37: 10 | M37: 7 | N37: 10 | O37: 46113 | R37: 45961 | S37: 10 | T37: 195030 | U37: 25.11 | V37: 11 | W37: 30 | X37: 337994
A38: 37 | B38: 311-641028X | C38: 東久留米市滝山6-1 | D38: 西部 | E38: 東久留 | F38: 45461 | G38: 6 | H38: 410037 | I38: 事前 | J38: 40042003 | K38: 星 | O38: 46113 | P38: -
A39: 38 | B39: 311-641029X | C39: 東久留米市滝山6-1 | D39: 西部 | E39: 東久留 | F39: 45461 | G39: 6 | H39: 410038 | I39: 事前 | J39: 40042005 | K39: 共立 | L39: 6 | M39: 4 | N39: 6 | O39: 46113 | P39: 45803 | R39: 45838 | S39: 6 | T39: 87760 | U39: 25.6 | V39: 6 | W39: 30 | X39: 151569
A40: 39 | B40: 311-641030X | C40: 東久留米市滝山7-19 | D40: 西部 | E40: 東久留 | F40: 45461 | G40: 6 | H40: 410039 | I40: 事前 | J40: 40042007 | K40: 共立 | L40: 6 | M40: 4 | N40: 6 | O40: 46113 | P40: 45803 | R40: 45838 | S40: 6 | T40: 81450 | U40: 25.6 | V40: 6 | W40: 30 | X40: 141740
A41: 40 | B41: 311-641033F | C41: 東久留米市本町4-9 | D41: 西部 | E41: 東久留 | F41: 45474 | G41: 7 | H41: 410040 | I41: 事前 | J41: 40044343 | K41: 星 | L41: 1 | M41: 12 | N41: 1 | O41: 46113 | R41: 46053 | S41: 1 | T41: 206930 | U41: 26.1 | V41: 1 | W41: 30 | X41: 352388
A42: 41 | B42: 311-641020F | C42: 東久留米市南沢3-5 | D42: 西部 | E42: 東久留 | F42: 45474 | G42: 7 | H42: 410041 | I42: 事前 | J42: 40044345 | K42: 星 | L42: 11 | M42: 7 | N42: 11 | O42: 46113 | R42: 45991 | S42: 11 | T42: 119080 | U42: 25.11 | V42: 11 | W42: 30 | X42: 204895
A43: 42 | B43: 311-641018F | C43: 東久留米市中央町1-1 | D43: 西部 | E43: 東久留 | F43: 45474 | G43: 7 | H43: 410042 | I43: 事前 | J43: 40044346 | K43: 星 | L43: 10 | M43: 7 | N43: 10 | O43: 46113 | R43: 45961 | S43: 10 | T43: 115970 | U43: 25.11 | V43: 11 | W43: 30 | X43: 200489
A44: 43 | B44: 311-641012F | C44: 東久留米市八幡町3-3 | D44: 西部 | E44: 東久留 | F44: 45474 | G44: 7 | H44: 410043 | I44: 事前 | J44: 40044347 | K44: 星 | L44: 11 | M44: 7 | N44: 10 | O44: 46113 | R44: 45961 | S44: 10 | T44: 100490 | U44: 25.11 | V44: 11 | W44: 30 | X44: 174120
A45: 44 | B45: 311-641016F | C45: 東久留米市前沢5-11 | D45: 西部 | E45: 東久留 | F45: 45474 | G45: 7 | H45: 410044 | I45: 事前 | J45: 40044349 | K45: 星 | L45: 10 | M45: 7 | N45: 10 | O45: 46113 | R45: 45961 | S45: 10 | T45: 147470 | U45: 25.11 | V45: 11 | W45: 30 | X45: 254052
A46: 45 | B46: 311-641014F | C46: 東久留米市滝山4-11 | D46: 西部 | E46: 東久留 | F46: 45474 | G46: 7 | H46: 410045 | I46: 事前 | J46: 40044351 | K46: 星 | L46: 10 | M46: 7 | N46: 10 | O46: 46113 | R46: 45961 | S46: 10 | T46: 103600 | U46: 25.11 | V46: 11 | W46: 30 | X46: 178526
A47: 46 | B47: 311-042488X | C47: 世田谷区太子堂2-6 | D47: 西部 | E47: 世田谷 | H47: 410046
A48: 47 | B48: 311-442182M | C48: 武蔵野市境南5-3 | D48: 西部 | E48: 武蔵野 | H48: 410047
A49: 48 | B49: 311-442183M | C49: 武蔵野市境南5-1 | D49: 西部 | E49: 武蔵野 | H49: 410048 | Y49: 赤羽 | Z49: JP
A50: 49 | B50: 113-533504X | C50: 大田区羽田旭町11-1 | D50: 南部 | E50: 大田区 | F50: 45523 | G50: 8 | H50: 410049 | I50: 事前 | J50: 40049490 | K50: みつば | O50: 45809 | P50: -
A51: 50 | B51: 332-403647 | C51: 大田区蒲田4-28-5 | D51: 南部 | E51: 大田区 | H51: 410050 | Y51: 8700
A52: 51 | B52: 113-400709H | C52: 大田区中央7-4-3 | D52: 南部 | E52: 大田区 | F52: 45554 | G52: 9 | H52: 410051 | I52: 事前 | K52: みつば | L52: 11 | M52: 9 | N52: 11 | O52: 45569 | P52: 45562 | R52: 45597 | S52: 11
A53: 52 | B53: 113-542644X | C53: 大田区南馬込1-58-11 | D53: 南部 | E53: 大田区 | F53: 45566 | G53: 10 | H53: 410052 | I53: 事前 | J53: 40054509 | K53: みつば | L53: 9 | M53: 4 | N53: 9 | O53: 45748 | P53: 45768 | R53: 45930 | S53: 9 | T53: 87530 | U53: 25.9 | V53: 9 | W53: 10 | X53: 153844
A54: 53 | B54: 113-542641X | C54: 大田区大森北6-16-6 | D54: 南部 | E54: 大田区 | F54: 45567 | G54: 10 | H54: 410053 | I54: 事前 | J54: 40054508 | K54: みつば | L54: 9 | M54: 4 | N54: 9 | O54: 2025/4/1→10/1 | R54: 45930 | S54: 9 | T54: 87410 | U54: 25.9 | V54: 9 | W54: 10 | X54: 153628
A55: 54 | B55: 311-543243X | C55: 武蔵野市桜堤1-1 | D55: 西部 | E55: 武蔵野 | F55: 45567 | G55: 10 | H55: 410054 | I55: 事前 | J55: 40054378 | K55: 共立 | O55: 45748 | P55: -
A56: 55 | B56: 311-543244X | C56: 武蔵野市関前5-8 | D56: 西部 | E56: 武蔵野 | F56: 45567 | G56: 10 | H56: 410055 | I56: 事前 | J56: 40054355 | K56: 共立 | O56: 45748 | P56: -
A57: 56 | B57: 311-543246X | C57: 武蔵野市西久保2-1 | D57: 西部 | E57: 武蔵野 | F57: 45567 | G57: 10 | H57: 410056 | I57: 事前 | J57: 40054357 | K57: 共立 | M57: 2 | N57: 3 | O57: 45748 | P57: 45719 | R57: 45717 | S57: 3
A58: 57 | B58: 311-543247X | C58: 武蔵野市境南町1-2 | D58: 西部 | E58: 武蔵野 | F58: 45567 | G58: 10 | H58: 410057 | I58: 事前 | J58: 40054359 | K58: 共立 | O58: 45748 | P58: -
A59: 58 | B59: 311-543248X | C59: 武蔵野市吉祥寺南町3-10 | D59: 西部 | E59: 武蔵野 | F59: 45567 | G59: 10 | H59: 410058 | I59: 事前 | J59: 40054360 | K59: 共立 | O59: 45748 | P59: -
A60: 59 | B60: 311-543252X | C60: 武蔵野市境1-20 | D60: 西部 | E60: 武蔵野 | F60: 45567 | G60: 10 | H60: 410059 | I60: 事前 | J60: 40054364 | K60: 共立 | O60: 45748 | P60: -
A61: 60 | B61: 311-543253X | C61: 武蔵野市境1-16 | D61: 西部 | E61: 武蔵野 | F61: 45567 | G61: 10 | H61: 410060 | I61: 事前 | J61: 40054365 | K61: 共立 | O61: 45748 | P61: -
A62: 61 | B62: 311-543254X | C62: 武蔵野市関前4-2 | D62: 西部 | E62: 武蔵野 | F62: 45567 | G62: 10 | H62: 410061 | I62: 事前 | J62: 40054372 | K62: 共立 | O62: 45748 | P62: -
A63: 62 | B63: 311-543255X | C63: 武蔵野市西久保1-16 | D63: 西部 | E63: 武蔵野 | F63: 45567 | G63: 10 | H63: 410062 | I63: 事前 | J63: 40054376 | K63: 共立 | O63: 45748 | P63: -
A64: 63 | B64: 311-543257X | C64: 東久留米市小山5-1 | D64: 西部 | E64: 東久留 | F64: 45568 | G64: 10 | H64: 410063 | I64: 事前 | J64: 40054615 | K64: 星 | O64: 45748 | P64: -
A65: 64 | B65: 311-543259X | C65: 東久留米市東本町4 | D65: 西部 | E65: 東久留 | F65: 45568 | G65: 10 | H65: 410064 | I65: 事前 | J65: 40054613 | K65: 星 | O65: 45748 | P65: -
A66: 65 | B66: 311-543260X | C66: 東久留米市新川1-15 | D66: 西部 | E66: 東久留 | F66: 45568 | G66: 10 | H66: 410065 | I66: 事前 | J66: 40054612 | K66: 星 | O66: 45748 | P66: -
A67: 66 | B67: 311-543261X | C67: 東久留米市本町1-6 | D67: 西部 | E67: 東久留 | F67: 45568 | G67: 10 | H67: 410066 | I67: 事前 | J67: 40054611 | K67: 星 | O67: 45748 | P67: -
A68: 67 | B68: 311-543259X | C68: 東久留米市東本町4 | D68: 西部 | E68: 東久留 | F68: 45594 | G68: 10 | H68: 410067 | I68: 事前 | J68: 40057346 | K68: 中止 | O68: 中止
A69: 68 | B69: 113-412066X | C69: 大田区東六郷3-3 | D69: 南部 | E69: 大田区 | H69: 410068 | Z69: なし
A70: 69 | B70: 113-672201X | C70: 大田区東雪谷2-9-1 | D70: 南部 | E70: 大田区 | F70: 45595 | G70: 10 | H70: 410069 | I70: 事前 | J70: 40057843 | K70: みつば | O70: 46328 | P70: -
A71: 70 | B71: 311-142143I | C71: 世田谷区経堂5-21 | D71: 西部 | E71: 世田谷 | H71: 410070
A72: 71 | B72: 311-242091M | C72: 世田谷区用賀4-36 | D72: 西部 | E72: 世田谷 | H72: 410071 | Z72: TG
A73: 72 | B73: 113-574201X | C73: 大田区蒲田5-39-3 | D73: 南部 | E73: 大田区 | F73: 45608 | G73: 11 | H73: 410072 | I73: 事前 | J73: 40058872 | K73: みつば | L73: 6 | M73: 4 | N73: 6 | O73: 45784 | P73: 45768 | R73: 45838 | S73: 6 | T73: 61770 | U73: 25.6 | V73: 6 | W73: 10 | X73: 108620
A74: 73 | B74: 512-412621 | C74: 和光市中央1-2 | D74: 北部 | E74: 和光市 | F74: 45622 | G74: 11 | H74: 410073 | I74: 事前 | K74: 塩川 | L74: 12 | M74: 12 | N74: 12 | O74: 45687 | R74: 45627 | S74: 12 | Y74: 保全 大久保
A75: 74 | B75: 311-242102F | C75: 世田谷区瀬田2-11 | D75: 西部 | E75: 世田谷 | H75: 410074
A76: 75 | B76: 311-342137M | C76: 武蔵野市緑町1-5 | D76: 西部 | E76: 武蔵野 | H76: 410075 | Y76: 赤羽 | Z76: JP
A77: 76 | B77: 113-419005X | C77: 大田区下丸子2-22 | D77: 南部 | E77: 大田区 | H77: 410076
A78: 77 | B78: 332-108603 | C78: 大田区山王4-9-26 | D78: 南部 | E78: 大田区 | H78: 410077 | Y78: 保全千葉
A79: 78 | B79: 332-403095 | C79: 大田区山王2-2-7 | D79: 南部 | E79: 大田区 | H79: 410078 | Y79: 保全千葉
A80: 79 | B80: 311-586300X | C80: 三鷹市下連雀6-2-6 | D80: 西部 | E80: 三鷹市 | F80: 45685 | G80: 1 | H80: 410079 | I80: 事前 | J80: 40067602 | K80: 星 | L80: 8 | M80: 7 | N80: 8 | O80: 45887 | P80: - | R80: 45900 | S80: 8 | T80: 56290 | U80: 25.8 | V80: 8 | W80: 30 | X80: 102119
A81: 80 | B81: 113-415028X | C81: 大田区多摩川1-16 | D81: 南部 | E81: 大田区 | H81: 410080
A82: 81 | B82: 311-342202X | C82: 武蔵野市境南町2-23 | D82: 西部 | E82: 武蔵野 | H82: 410081 | Y82: 赤羽 | Z82: JP
A83: 82 | B83: 113-312100X | C83: 大田区鵜木1-10 | D83: 南部 | E83: 大田区 | H83: 410082
A84: 83 | B84: 113-471219X | C84: 大田区石川町2-16-10 | D84: 南部 | E84: 大田区 | F84: 45692 | G84: 2 | H84: 410083 | I84: 事前 | J84: 40068438 | K84: みつば | M84: 7 | O84: 45922 | P84: - | Q84: 8/6
A85: 84 | B85: 113-471217Y | C85: 大田区鵜の木1-12-7 | D85: 南部 | E85: 大田区 | F85: 45694 | G85: 2 | H85: 410084 | I85: 事前 | J85: 40068703 | K85: みつば | L85: 7 | M85: 7 | N85: 7 | O85: 45870 | P85: - | R85: 45869 | S85: 7 | T85: 53690 | U85: 25.7 | V85: 7 | W85: 10 | X85: 94427
A86: 85 | B86: 113-514039X | C86: 大田区田園調布5-55-5 | D86: 南部 | E86: 大田区 | F86: 45694 | G86: 2 | H86: 410085 | I86: 事前 | J86: 40068888 | K86: みつば | L86: 7 | M86: 6 | N86: 7 | O86: 45845 | P86: - | R86: 45869 | S86: 7 | T86: 43710 | U86: 25.7 | V86: 7 | W86: 10 | X86: 80025
A87: 86 | B87: 113-581204X | C87: 大田区中央2-11-2 | D87: 南部 | E87: 大田区 | F87: 45700 | G87: 2 | H87: 410086 | I87: 事前 | J87: 40069267 | K87: みつば | L87: 10 | M87: 8 | N87: 10 | O87: 45901 | P87: - | Q87: 8/18 | R87: 45961 | S87: 10 | T87: 58660 | U87: 25.11 | V87: 11 | W87: 10 | X87: 102491 | Y87: 岩重 | Z87: 2/17JP
A88: 87 | B88: 311-843325K | C88: 世田谷区尾山台3-5 | D88: 西部 | E88: 世田谷 | F88: 45702 | G88: 2 | H88: 410087 | I88: 事前 | J88: 40069855 | K88: 共立 | L88: 9 | M88: 8 | N88: 9 | O88: 45931 | P88: - | R88: 45930 | S88: 9 | T88: 54210 | U88: 25.1 | V88: 10 | W88: 30 | X88: 141673
A89: 88 | B89: 311-142102M | C89: 世田谷区瀬田4-16 | D89: 西部 | E89: 世田谷 | F89: 45706 | G89: 2 | H89: 410088 | I89: 家屋調査 | J89: 40069960 | K89: みつば | M89: 2 | O89: 44348 | P89: -
A90: 89 | B90: 332-401952 | C90: 大田区中央4-20-9 | D90: 南部 | E90: 大田区 | H90: 410089 | Y90: 8700
A91: 90 | B91: 113-412074X | C91: 大田区大森西2-22-20 | D91: 南部 | E91: 大田区 | H91: 410090
A92: 91 | B92: 311-342136M | C92: 武蔵野市緑町1-5 | D92: 西部 | E92: 武蔵野 | H92: 410091
A93: 92 | B93: 311-243083J | C93: 西東京市中町4-6 | D93: 西部 | E93: 西東京 | H93: 410092
A94: 93 | B94: 311-242138J | C94: 西東京市富士町5-7 | D94: 西部 | E94: 西東京 | H94: 410093
A95: 94 | B95: 113-519004X | C95: 大田区鵜の木2-29-7 | D95: 南部 | E95: 大田区 | F95: 45716 | G95: 2 | H95: 410094 | I95: 事前 | J95: 40071321 | K95: みつば | L95: 6 | M95: 4 | N95: 6 | O95: 45794 | P95: 45765 | R95: 45838 | S95: 6 | T95: 69000 | U95: 25.6 | V95: 6 | W95: 10 | X95: 105120 | Y95: 仲川
A96: 95 | B96: 411-519012A | C96: 新座市野火止8-1-24 | D96: 北部 | E96: 新座市 | F96: 45716 | G96: 2 | H96: 410095 | I96: 事前 | J96: 40071353 | K96: 塩川 | L96: 6 | M96: 4 | N96: 5 | O96: 45796 | P96: 45765 | R96: 45778 | S96: 5 | U96: 25.6 | V96: 6 | W96: 30 | X96: 82608
A97: 96 | B97: 113-411048X | C97: 大田区矢口3-17-13 | D97: 南部 | E97: 大田区 | H97: 410096
A98: 97 | B98: 113-419019X | C98: 大田区千鳥3-11-1 | D98: 南部 | E98: 大田区 | H98: 410097
A99: 98 | B99: 332-401848 | C99: 大田区上池台4-2-15 | D99: 南部 | E99: 大田区 | H99: 410098 | Y99: 8700
A100: 99 | B100: 332-407345 | C100: 大田区上池台1-53 | D100: 南部 | E100: 大田区 | H100: 410099 | Y100: 8700
...

Sheet 杭台帳(神)
A1: 整理番号 | B1: 工事番号 | C1: 住 所 | D1: NC区分 | E1: 住所（行政区） | F1: 受注日 | G1: 受注月 | H1: 受注番号 | I1: 区分 | J1: 発行番号 | K1: 外注先 | L1: 納品月 | M1: 外注 発注月 | N1: 外注納品月 | O1: 外注支払月 | P1: 外注支払月(月のみ) | Q1: 外注支払額 | R1: 入金月 | S1: 入金月（月のみ） | T1: 精算 グループ | U1: 入金額 | V1: 杭購入金額 | X1: =U646+U647+U724+U791 -> 730368
A2: 1 | B2: 622-108485 | C2: 幸区中幸町4-29-3 | D2: 神奈川 | E2: 幸区中 | H2: 425001
A3: 2 | B3: 512-042227X | C3: 港北区篠原町81 | D3: 神奈川 | E3: 港北区 | H3: 425003
A4: 3 | B4: 512-312060X | C4: 港北区富士塚1-9-3 | D4: 神奈川 | E4: 港北区 | F4: 45156 | G4: 8 | H4: 425005 | I4: 事前 | J4: 30017367 | K4: 共立 | M4: 8
A5: 4 | B5: 512-311041X | C5: 鶴見区矢向4-7-4 | D5: 神奈川 | E5: 鶴見区 | F5: 45156 | G5: 8 | H5: 425006 | I5: 事前 | J5: 30017032 | K5: 共立 | M5: 8
A6: 5 | B6: 511-219156X | C6: 横須賀市長沢3-7 | D6: 神奈川 | E6: 横須賀 | H6: 425008
A7: 6 | B7: 513-214018X | C7: 宮前区平5-8-35 | D7: 神奈川 | E7: 宮前区 | H7: 425010
A8: 7 | B8: 622-301632 | C8: 麻生区王禅寺西3-27 | D8: 神奈川 | E8: 麻生区 | H8: 425011
A9: 8 | B9: 512-443101T | C9: 神奈川区白幡向町17-15 | D9: 神奈川 | E9: 神奈川 | F9: 45359 | G9: 3 | H9: 425022 | I9: 事前 | J9: 30041252 | K9: みつば | M9: 3
A10: 9 | B10: 513-214006X | C10: 中原区今井仲町8-30 | D10: 神奈川 | E10: 中原区 | H10: 425031
A11: 10 | B11: 512-843145X | C11: 港北区篠原東3-17-4 | D11: 神奈川 | E11: 港北区 | H11: 425036
A12: 11 | B12: 513-314146X | C12: 宮前区西野川1-38 | D12: 神奈川 | E12: 宮前区 | H12: 425042
A13: 12 | B13: 513-214132X | C13: 宮前区有馬8-7 | D13: 神奈川 | E13: 宮前区 | H13: 425058
A14: 13 | B14: 513-219176X | C14: 宮前区潮見台9-2 | D14: 神奈川 | E14: 宮前区 | H14: 425059
A15: 14 | B15: 513-311010X | C15: 高津区下野毛3-14-5 | D15: 神奈川 | E15: 高津区 | H15: 425060
A16: 15 | B16: 513-314005X | C16: 多摩区宿河原7-8-1 | D16: 神奈川 | E16: 多摩区 | F16: 45391 | G16: 4 | H16: 425064 | I16: 事前 | J16: 40001018 | K16: みつば | M16: 4 | N16: 4 | O16: 45402 | P16: 4 | Q16: 48990
A17: 16 | B17: 513-219155X | C17: 宮前区菅生6-2-4 | D17: 神奈川 | E17: 宮前区 | H17: 425077
A18: 17 | B18: 513-212007X | C18: 宮前区馬絹4-11-37 | D18: 神奈川 | E18: 宮前区 | H18: 425094
A19: 18 | B19: 513-412016X | C19: 宮前区鷺沼1-18-10 | D19: 神奈川 | E19: 宮前区 | F19: 45413 | G19: 5 | H19: 425101 | I19: 事前 | J19: 30049159 | K19: 共立 | L19: 5 | M19: 5 | N19: 5 | O19: 45432 | P19: 5 | Q19: 33860 | R19: 25.8 | S19: 8 | T19: 27 | U19: 65097
A20: 19 | B20: 622-400802 | C20: 高津区溝口5-7-10 | D20: 神奈川 | E20: 高津区 | F20: 45432 | G20: 5 | H20: 425125 | I20: 事前 | J20: 40027244 | K20: 共立 | L20: 6 | M20: 5 | N20: 5
A21: 20 | B21: 512-411028X | C21: 神奈川区入江1-11-3 | D21: 神奈川 | E21: 神奈川 | F21: 45443 | G21: 5 | H21: 425157 | I21: 事前 | J21: 40026948 | K21: 共立 | L21: 6 | M21: 5 | N21: 6 | R21: 25.9 | S21: 9 | T21: 21 | U21: 73776
A22: 21 | B22: 622-400946 | C22: 高津区下野毛3-5-10 | D22: 神奈川 | E22: 高津区 | F22: 45443 | G22: 5 | H22: 425161 | I22: 事前 | J22: 40039216 | K22: 共立 | L22: 6 | M22: 5 | N22: 6
A23: 22 | B23: 513-214194X | C23: 宮前区西野川1-18 | D23: 神奈川 | E23: 宮前区 | H23: 425162
A24: 23 | B24: 512-403008M | C24: 港北区蓑輪町1-25-25 | D24: 神奈川 | E24: 港北区 | F24: 45432 | G24: 5 | H24: 425163 | I24: 事前 | J24: 40027288 | K24: みつば | L24: 5 | M24: 5 | N24: 6 | O24: 45463 | P24: 6 | Q24: 31950 | R24: 25.9 | S24: 9 | T24: 23 | U24: 59683
A25: 24 | B25: 513-211063X | C25: 多摩区宿河原1-23-5 | D25: 神奈川 | E25: 多摩区 | H25: 425165
A26: 25 | B26: 622-211100 | C26: 中原区上平間594 | D26: 神奈川 | E26: 中原区 | H26: 425172
A27: 26 | B27: 622-210020 | C27: 中原区新城1-9 | D27: 神奈川 | E27: 中原区 | H27: 425173
A28: 27 | B28: 513-142161X | C28: 川崎区大島1-26-7 | D28: 神奈川 | E28: 川崎区 | H28: 425205
A29: 28 | B29: 512-319282A | C29: 都筑区池辺町2352 | D29: 神奈川 | E29: 都筑区 | H29: 425269
A30: 29 | B30: 513-403014M | C30: 多摩区登戸918-6 | D30: 神奈川 | E30: 多摩区 | F30: 45482 | G30: 7 | H30: 425376 | I30: 事前 | J30: 40044507 | K30: 共立 | L30: 12 | M30: 7 | N30: 12 | O30: 46022 | P30: 12 | Q30: 28000 | R30: 25.12 | S30: 12 | T30: 23 | U30: 46413
A31: 30 | B31: 513-314111X | C31: 宮前区馬絹4-13-13 | D31: 神奈川 | E31: 宮前区 | H31: 425404
A32: 31 | B32: 513-319044X | C32: 宮前区梶ヶ谷1385 | D32: 神奈川 | E32: 宮前区 | F32: 45485 | G32: 7 | H32: 425408 | I32: 事前 | J32: 40045533 | K32: 共立 | M32: 7 | N32: 8
A33: 32 | B33: 513-142286X | C33: 高津区溝口5-10-9 | D33: 神奈川 | E33: 高津区 | H33: 425433
A34: 33 | B34: 513-142122X | C34: 幸区鹿島田1-5-16 | D34: 神奈川 | E34: 幸区鹿 | H34: 425458
A35: 34 | B35: 511-243139S | C35: 横須賀市西逸見町2-79～2-75 | D35: 神奈川 | E35: 横須賀 | H35: 425459
A36: 35 | B36: 512-219229X | C36: 都筑区牛久保町1893-7 | D36: 神奈川 | E36: 都筑区 | H36: 425460
A37: 36 | B37: 513-014094A | C37: 多摩区菅北浦1-11 | D37: 神奈川 | E37: 多摩区 | H37: 425463
A38: 37 | B38: 511-342110J | C38: 横須賀市小川町3-4 | D38: 神奈川 | E38: 横須賀 | H38: 425512
A39: 38 | B39: 513-342108P | C39: 麻生区百合丘1-24-38 | D39: 神奈川 | E39: 麻生区 | H39: 425532
A40: 39 | B40: 513-214129A | C40: 宮前区西野川1-12 | D40: 神奈川 | E40: 宮前区 | H40: 425542
A41: 40 | B41: 513-111032X | C41: 多摩区堰2-1-9 | D41: 神奈川 | E41: 多摩区 | H41: 425543
A42: 41 | B42: 512-400962N | C42: 港北区箕輪町1-12-3 | D42: 神奈川 | E42: 港北区 | H42: 425594
A43: 42 | B43: 513-419071X | C43: 多摩区菅5-12-23 | D43: 神奈川 | E43: 多摩区 | F43: 45545 | G43: 9 | H43: 425690 | I43: 事前 | J43: 40051921 | K43: 共立 | M43: 9
A44: 43 | B44: 511-242179X | C44: 戸塚区上倉田町350-1 | D44: 神奈川 | E44: 戸塚区 | H44: 425702
A45: 44 | B45: 513-342141F | C45: 中原区中丸子258-13 | D45: 神奈川 | E45: 中原区 | H45: 425733
A46: 45 | B46: 513-242210W | C46: 麻生区王禅寺西2-1-3 | D46: 神奈川 | E46: 麻生区 | H46: 425749
A47: 46 | B47: 513-114136X | C47: 多摩区生田1-1-1 | D47: 神奈川 | E47: 多摩区 | H47: 425752
A48: 47 | B48: 513-319038X | C48: 宮前区平3-17 | D48: 神奈川 | E48: 宮前区 | H48: 425754
A49: 48 | B49: 512-342200T | C49: 神奈川区三ツ沢南町1 | D49: 神奈川 | E49: 神奈川 | H49: 425758
A50: 49 | B50: 513-119095X | C50: 川崎区浜町4-15-5 | D50: 神奈川 | E50: 川崎区 | H50: 425764
A51: 50 | B51: 513-342153P | C51: 川崎区大島5-21-10 | D51: 神奈川 | E51: 川崎区 | H51: 425908
A52: 51 | B52: 512-414357X | C52: 神奈川区入江1-11-31 | D52: 神奈川 | E52: 神奈川 | F52: 45621 | G52: 11 | H52: 425985 | I52: 事前 | J52: 40057487 | K52: みつば | M52: 11
A53: 52 | B53: 513-014072X | C53: 多摩区登戸2851-15 | D53: 神奈川 | E53: 多摩区 | H53: 426002
A54: 53 | B54: 513-411005X | C54: 川崎区殿町3-18-5 | D54: 神奈川 | E54: 川崎区 | H54: 426003
A55: 54 | B55: 513-414029X | C55: 多摩区中野島4-8 | D55: 神奈川 | E55: 多摩区 | H55: 426004
A56: 55 | B56: 513-414007X | C56: 麻生区百合丘2-12 | D56: 神奈川 | E56: 麻生区 | H56: 426005
A57: 56 | B57: 512-314349X | C57: 鶴見区獅子ヶ谷3-19 | D57: 神奈川 | E57: 鶴見区 | H57: 426006
A58: 57 | B58: 513-214105X | C58: 宮前区野川本町1-34 | D58: 神奈川 | E58: 宮前区 | H58: 426007
A59: 58 | B59: 513-312220X | C59: 川崎区浅田2-12-22 | D59: 神奈川 | E59: 川崎区 | H59: 426008
A60: 59 | B60: 513-319096X | C60: 宮前区神木本町4-20 | D60: 神奈川 | E60: 宮前区 | H60: 426009
A61: 60 | B61: 513-219128X | C61: 多摩区宿河原2-48 | D61: 神奈川 | E61: 多摩区 | H61: 426010
A62: 61 | B62: 512-043220S | C62: 鶴見区寺谷1-17-25 | D62: 神奈川 | E62: 鶴見区 | H62: 426011
A63: 62 | B63: 622-110731 | C63: 宮前区犬蔵3-14 | D63: 神奈川 | E63: 宮前区 | H63: 426012
A64: 63 | B64: 512-314328X | C64: 神奈川区片倉5-36-6 | D64: 神奈川 | E64: 神奈川 | H64: 426079
... A81: 80 | B81: 512-414344X | C81: 鶴見区上の宮2-10 | D81: 神奈川 | E81: 鶴見区 | H81: 426413
A82: 81 | B82: 513-514106X | C82: 宮前区平5-4 | D82: 神奈川 | E82: 宮前区 | F82: 45728 | G82: 3 | H82: 426468 | I82: 事前 | J82: 40069136 | K82: みつば | L82: 5 | M82: 3 | N82: 5 | O82: 45797 | P82: 5 | Q82: 72230 | R82: 25.6 | S82: 6 | T82: 21 | U82: 140068
A83: 82 | B83: 512-419087X | C83: 鶴見区東寺尾1-29-27 | D83: 神奈川 | E83: 鶴見区 | H83: 426484
A84: 83 | B84: 513-410001X | C84: 幸区新小倉545-50 | D84: 神奈川 | E84: 幸区新 | H84: 426485
A85: 84 | B85: 512-419118X | C85: 港北区新吉田東1-60-7 | D85: 神奈川 | E85: 港北区 | H85: 426486
A86: 85 | B86: 513-414221X | C86: 高津区明津102 | D86: 神奈川 | E86: 高津区 | H86: 426487
A87: 86 | B87: 513-419074X | C87: 高津区下野毛3-15 | D87: 神奈川 | E87: 高津区 | H87: 426488
A88: 87 | B88: 512-403012X | C88: 神奈川区菅田町467-6 | D88: 神奈川 | E88: 神奈川 | H88: 426489
A89: 88 | B89: 512-414288X | C89: 都筑区牛久保町1918 | D89: 神奈川 | E89: 都筑区 | H89: 426490
A90: 89 | B90: 513-314140X | C90: 高津区明津106 | D90: 神奈川 | E90: 高津区 | H90: 426491
A91: 90 | B91: 513-212059X | C91: 高津区下作延7-7-34 | D91: 神奈川 | E91: 高津区 | H91: 426492
A92: 91 | B92: 512-312026X | C92: 港北区日吉3-11-13 | D92: 神奈川 | E92: 港北区 | H92: 426493
A93: 92 | B93: 512-919091X | C93: 鶴見区下末吉6-6-33 | D93: 神奈川 | E93: 鶴見区 | H93: 426494
A94: 93 | B94: 512-042140X | C94: 神奈川区鶴屋町2-25-1 | D94: 神奈川 | E94: 神奈川 | H94: 426495
... A104: 103 | B104: 513-319143X | C104: 高津区子母口751 | D104: 神奈川 | E104: 高津区 | H104: 426518
A105: 104 | B105: 513-505005X | C105: 川崎区夜光1-2-1 | D105: 神奈川 | E105: 川崎区 | F105: 45737 | G105: 3 | H105: 426533 | I105: 事前 | J105: 40065245 | K105: みつば | L105: 5 | M105: 3 | N105: 5 | O105: 45797 | P105: 5 | Q105: 32500 | R105: 25.1 | S105: 10 | T105: IB | U105: 81032
A106: 105 | B106: 513-511012X | C106: 幸区下平間115-19 | D106: 神奈川 | E106: 幸区下 | F106: 45737 | G106: 3 | H106: 426534 | I106: 事前 | J106: 40070900 | K106: みつば | L106: 5 | M106: 3 | N106: 5 | O106: 45797 | P106: 5 | Q106: 67490 | R106: 25.6 | S106: 6 | T106: 27 | U106: 130860
A107: 106 | B107: 513-511003X | C107: 高津区久末1861 | D107: 神奈川 | E107: 高津区 | F107: 45737 | G107: 3 | H107: 426543 | I107: 事前 | J107: 40064171 | K107: 共立 | L107: 5 | M107: 3 | N107: 5 | O107: 45797 | P107: 5 | Q107: 43805 | R107: 25.6 | S107: 6 | T107: 21 | U107: 83675
A108: 107 | B108: 512-514232X | C108: 神奈川区神大寺2-11 | D108: 神奈川 | E108: 神奈川 | F108: 45747 | G108: 3 | H108: 426566 | I108: 事前 | J108: 40072266 | K108: 共立 | L108: 5 | M108: 4 | N108: 5 | O108: 45797 | P108: 5 | Q108: 41145 | R108: 25.6 | S108: 6 | T108: 21 | U108: 78507
A109: 108 | B109: 513-511015X | C109: 多摩区東三田1-2-4 | D109: 神奈川 | E109: 多摩区 | F109: 45747 | G109: 3 | H109: 426577 | I109: 事前 | J109: 40071876 | K109: みつば | L109: 5 | M109: 4 | N109: 5 | O109: 45797 | P109: 5 | Q109: 58030 | R109: 25.6 | S109: 6 | T109: 27 | U109: 112504
A110: 109 | B110: 512-519049X | C110: 青葉区すみよし台19-22 | D110: 神奈川 | E110: 青葉区 | F110: 45747 | G110: 3 | H110: 426578 | I110: 事前 | J110: 40072432 | K110: みつば | L110: 5 | M110: 4 | N110: 5 | O110: 45797 | P110: 5 | Q110: 60015 | R110: 25.6 | S110: 6 | T110: 21 | U110: 112400
A111: 110 | B111: 512-511021X | C111: 青葉区市ヶ尾町1178-12 | D111: 神奈川 | E111: 青葉区 | F111: 45747 | G111: 3 | H111: 426579 | I111: 事前 | J111: 40072151 | K111: みつば | L111: 6 | M111: 4 | N111: 6 | O111: 45834 | P111: 6 | Q111: 72074 | R111: 25.6 | S111: 6 | T111: 21 | U111: 138376
A112: 111 | B112: 513-553135F | C112: 宮前区宮崎6-9-1 | D112: 神奈川 | E112: 宮前区 | F112: 45713 | G112: 2 | H112: 426581 | I112: 事前 | J112: 40043538 | K112: みつば | L112: 5 | M112: 4 | N112: 5 | O112: 45797 | P112: 5 | Q112: 197000 | R112: 25.6 | S112: 6 | T112: 27 | U112: 302289
A113: 112 | B113: 513-553136F | C113: 宮前区土橋7-1-5 | D113: 神奈川 | E113: 宮前区 | F113: 45737 | G113: 3 | H113: 426583 | I113: 事前 | J113: 40043542 | K113: みつば | L113: 7 | M113: 4 | N113: 7 | O113: 45867 | P113: 7 | Q113: 133000 | R113: 25.7 | S113: 7 | T113: 27 | U113: 205493
A114: 113 | B114: 512-553177F | C114: 青葉区藤が丘1-12-7 | D114: 神奈川 | E114: 青葉区 | F114: 45705 | G114: 2 | H114: 426584 | I114: 事前 | J114: 40043469 | K114: みつば | L114: 5 | M114: 4 | N114: 5 | O114: 45797 | P114: 5 | Q114: 106455 | R114: 25.6 | S114: 6 | T114: 27 | U114: 197884
A115: 114 | B115: 512-553174F | C115: 青葉区美しが丘1-18-1 | D115: 神奈川 | E115: 青葉区 | F115: 45673 | G115: 1 | H115: 426586 | I115: 事前 | J115: 40043456 | K115: みつば | L115: 6 | M115: 4 | N115: 6 | O115: 45834 | P115: 6 | Q115: 169000 | R115: 25.6 | S115: 6 | T115: 27 | U115: 260715
A116: 115 | B116: 512-553143J | C116: 青葉区藤が丘1-6-1 | D116: 神奈川 | E116: 青葉区 | F116: 45537 | G116: 9 | H116: 426588 | I116: 事前 | J116: 40041832 | K116: みつば | L116: 7 | M116: 4 | N116: 7 | O116: 45867 | P116: 7 | Q116: 180000 | R116: 25.7 | S116: 7 | T116: 27 | U116: 276839
A117: 116 | B117: 512-553168F | C117: 神奈川区六角橋1-6-15 | D117: 神奈川 | E117: 神奈川 | F117: 45673 | G117: 1 | H117: 426596 | I117: 事前 | J117: 40043418 | K117: 共立 | L117: 5 | M117: 4 | N117: 5 | O117: 45797 | P117: 5 | Q117: 82680 | R117: 25.6 | S117: 6 | T117: 27 | U117: 153011
... A134: 133 | B134: 513-511005X | C134: 麻生区上麻生6-11-22 | D134: 神奈川 | E134: 麻生区 | F134: 45769 | G134: 4 | H134: 426651 | I134: 事前 | J134: 40065875 | K134: みつば | L134: 7 | M134: 4 | N134: 6 | O134: 45834 | P134: 6 | Q134: 99430 | R134: 25.7 | S134: 7 | T134: 21 | U134: 180110
A135: 134 | B135: 512-419120X | C135: 綱島台27-17 | D135: 神奈川 | E135: 綱島台 | H135: 426654
A136: 135 | B136: 513-512016X | C136: 幸区南加瀬5-4-12 | D136: 神奈川 | E136: 幸区南 | F136: 45798 | G136: 5 | H136: 426659 | I136: 事前 | J136: 40074205 | K136: 共立 | L136: 5 | M136: 4 | N136: 5 | O136: 45797 | P136: 5 | Q136: 49580 | R136: 25.6 | S136: 6 | T136: 27 | U136: 95380
A137: 136 | B137: 513-503001M | C137: 中原区丸子通2-705 | D137: 神奈川 | E137: 中原区 | F137: 45813 | G137: 6 | H137: 426665 | I137: 事前 | J137: 50000800 | K137: 共立 | L137: 5 | M137: 4 | N137: 5 | O137: 45797 | P137: 5 | Q137: 56370 | R137: 25.6 | S137: 6 | T137: 23 | U137: 107552
A138: 137 | B138: 512-514245X | C138: 神奈川区三ツ沢上町8 | D138: 神奈川 | E138: 神奈川 | F138: 45821 | G138: 6 | H138: 426666 | I138: 事前 | J138: 40074766 | K138: 共立 | L138: 5 | M138: 4 | N138: 5 | O138: 45797 | P138: 5 | Q138: 38145 | R138: 25.6 | S138: 6 | T138: 21 | U138: 72686
A139: 138 | B139: 513-514158X | C139: 宮前区南野川1-13 | D139: 神奈川 | E139: 宮前区 | F139: 45838 | G139: 6 | H139: 426670 | I139: 事前 | J139: 40075225 | K139: 共立 | L139: 6 | M139: 4 | N139: 6 | O139: 45833 | P139: 6 | Q139: 38750 | R139: 25.6 | S139: 6 | T139: 21 | U139: 75080
A140: 139 | B140: 512-512031X | C140: 神奈川区菅田町1546-1 | D140: 神奈川 | E140: 神奈川 | F140: 45838 | G140: 6 | H140: 426671 | I140: 事前 | J140: 40074759 | K140: 共立 | L140: 5 | M140: 4 | N140: 5 | O140: 45797 | P140: 5 | Q140: 58820 | R140: 25.6 | S140: 6 | T140: 21 | U140: 113320
A141: 140 | B141: 512-514247X | C141: 青葉区あざみ野4-13 | D141: 神奈川 | E141: 青葉区 | F141: 45838 | G141: 6 | H141: 426672 | I141: 事前 | J141: 40075353 | K141: 共立 | L141: 5 | M141: 4 | N141: 5 | O141: 45797 | P141: 5 | Q141: 44740 | R141: 25.6 | S141: 6 | T141: 21 | U141: 85995
...

Sheet 杭台帳(事後)(多)
A1: 整理番号 | B1: 工事番号 | C1: 住 所 | D1: NC区分 | E1: 住所（行政区） | F1: 工期 | G1: 製本受領 | H1: 多摩フリ3 | I1: 受注日(後) | J1: 受注月(後) | K1: 受注番号(後) | L1: 区分(後) | M1: 発行番号(後) | N1: 外注先(後) | O1: 納品 月(後) | P1: 外注 発注月(後) | Q1: 外注納品月(後) | R1: 復元杭引渡日 | S1: 製本受領2 | T1: 市提出 | U1: 杭購入金額 | V1: 外注支払月(後) | W1: 外注支払月(後)(月のみ) | X1: 外注支払額(後) | Y1: 入金月(後) | Z1: 入金月(後)（月のみ） | AA1: 精算 グループ(後) | AB1: 入金額(後) | AF1: =SUM(AA:AA) -> 33752
A2: 1 | B2: 313-343065X | C2: 国分寺市本多5-25 | D2: 多摩 | E2: 国分寺 | G2: 45827 | L2: 事後 | AF2: =AF1+'杭台帳(多)'!AF1 -> 1.2678268e+08
A3: 2 | B3: 313-343014X | C3: 立川市栄町3-24 | D3: 多摩 | E3: 立川市 | L3: 事後
A4: 3 | B4: 313-343017X | C4: 東村山市秋津町5-6 | D4: 多摩 | E4: 東村山 | L4: 事後
A5: 4 | B5: 313-242114E | C5: 八王子市中野山王1-5 | D5: 多摩 | E5: 八王子 | I5: 45075 | J5: 5 | L5: 事後 | M5: 30001889 | N5: みつば | O5: 1 | P5: 8 | Q5: 1 | R5: 45742 | T5: 46035 | Y5: 26.1 | Z5: 1 | AA5: 40 | AB5: 688424
A6: 5 | B6: 313-042102X | C6: 八王子市平岡町36 | D6: 多摩 | E6: 八王子 | I6: 45141 | J6: 8 | L6: 事後 | M6: 30015796 | N6: 共立 | O6: 9 | P6: 9 | Q6: 9 | U6: 7050 | V6: 45922 | W6: 9 | X6: 516760 | Y6: 25.9 | Z6: 9 | AA6: 40 | AB6: 1048415
A7: 6 | B7: 313-986704X | C7: 八王子市南町3 | D7: 多摩 | E7: 八王子 | I7: 45152 | J7: 8 | L7: 事後 | M7: 30019061 | N7: みつば | O7: 8 | P7: 12 | Q7: 8 | S7: 45908 | T7: 45909 | V7: 45890 | W7: 8 | X7: 258000 | Y7: 25.8 | Z7: 8 | AA7: 40 | AB7: 451659
A8: 7 | B8: 313-486721C | C8: 東村山市本町1-16 | D8: 多摩 | E8: 東村山 | L8: 事後
A9: 8 | B9: 313-443034X | C9: 小平市仲町291 | D9: 多摩 | E9: 小平市 | L9: 事後
A10: 9 | B10: 313-443033X | C10: 小平市小川西町3-12 | D10: 多摩 | E10: 小平市 | L10: 事後
A11: 10 | B11: 313-443032X | C11: 小平市花小金井1-17 | D11: 多摩 | E11: 小平市 | L11: 事後
A12: 11 | B12: 313-443031X | C12: 小平市学園東町3-1 | D12: 多摩 | E12: 小平市 | G12: 45873 | L12: 事後
A13: 12 | B13: 313-443038X | C13: 国分寺市泉町1-10 | D13: 多摩 | E13: 国分寺 | L13: 事後
A14: 13 | B14: 313-443043X | C14: 国立市中1-14 | D14: 多摩 | E14: 国立市 | L14: 事後
A15: 14 | B15: 313-443044X | C15: 国立市西2-3 | D15: 多摩 | E15: 国立市 | L15: 事後
A16: 15 | B16: 313-443015X | C16: 八王子市めじろ台1-41 | D16: 多摩 | E16: 八王子 | L16: 事後
A17: 16 | B17: 313-443048X | C17: 東大和市南街2-101 | D17: 多摩 | E17: 東大和 | L17: 事後
A18: 17 | B18: 313-443040X | C18: 国分寺市東元町2-7 | D18: 多摩 | E18: 国分寺 | G18: 45834 | L18: 事後
A19: 18 | B19: 313-443039X | C19: 国分寺市東元町2-14 | D19: 多摩 | E19: 国分寺 | G19: 45834 | L19: 事後
A20: 19 | B20: 313-443049X | C20: 東大和市萩山町2-20 | D20: 多摩 | E20: 東大和 | L20: 事後
A21: 20 | B21: 313-242014M | C21: 国分寺市東恋ヶ窪2-23 | D21: 多摩 | E21: 国分寺 | I21: 45342 | J21: 2 | L21: 事後 | M21: 30044178 | N21: 共立 | P21: 11 | R21: 45344
A22: 21 | B22: 313-486723A | C22: 多摩市鶴牧5-31 | D22: 多摩 | E22: 多摩市 | L22: 事後
A23: 22 | B23: 313-471713X | C23: 多摩市関戸5-16 | D23: 多摩 | E23: 多摩市 | F23: 46027 | L23: 事後
A24: 23 | B24: 313-342033M | C24: 日野市東平山1-7 | D24: 多摩 | E24: 日野市 | I24: 45420 | J24: 5 | L24: 事後 | M24: 40019762 | N24: 共立 | O24: 7 | P24: 5 | Q24: 7 | V24: 45860 | W24: 7 | X24: 30550 | Y24: 25.7 | Z24: 7 | AA24: 40 | AB24: 65565
A25: 24 | B25: 313-342043X | C25: 小平市学園西町3-23 | D25: 多摩 | E25: 小平市 | I25: 45442 | J25: 5 | L25: 事後 | M25: 40038988 | N25: 西都 | P25: 6
A26: 25 | B26: 313-443051X | C26: 国分寺市東元町3-21 | D26: 多摩 | E26: 国分寺 | L26: 事後
A27: 26 | B27: 313-541001X | C27: 八王子市中野上町4-28 | D27: 多摩 | E27: 八王子 | L27: 事後
A28: 27 | B28: 313-541003X | C28: 八王子市中野上町5-10 | D28: 多摩 | E28: 八王子 | G28: 46001 | L28: 事後
A29: 28 | B29: 313-541004X | C29: 八王子市中野上町5-1 | D29: 多摩 | E29: 八王子 | G29: 46001 | L29: 事後
A30: 29 | B30: 313-541005X | C30: 八王子市中野上町5-5 | D30: 多摩 | E30: 八王子 | L30: 事後
A31: 30 | B31: 313-541012X | C31: 八王子市中野上町3-18 | D31: 多摩 | E31: 八王子 | L31: 事後
A32: 31 | B32: 313-541013X | C32: 八王子市中野山王3-20 | D32: 多摩 | E32: 八王子 | L32: 事後
A33: 32 | B33: 313-541017X | C33: 小平市大沼町4-43 | D33: 多摩 | E33: 小平市 | G33: 46001 | L33: 事後
A34: 33 | B34: 313-541020F | C34: 国分寺市東元町2-20 | D34: 多摩 | E34: 国分寺 | G34: 46016 | L34: 事後
A35: 34 | B35: 313-541002X | C35: 八王子市中野上町4-24 | D35: 多摩 | E35: 八王子 | L35: 事後
A36: 35 | B36: 313-541006F | C36: 八王子市中野上町2-24 | D36: 多摩 | E36: 八王子 | G36: 46001 | L36: 事後
A37: 36 | B37: 313-541007X | C37: 八王子市中野上町4-43 | D37: 多摩 | E37: 八王子 | L37: 事後
A38: 37 | B38: 313-541008X | C38: 八王子市中野上町4-40 | D38: 多摩 | E38: 八王子 | L38: 事後
A39: 38 | B39: 313-541009F | C39: 八王子市中野上町2-32 | D39: 多摩 | E39: 八王子 | L39: 事後
A40: 39 | B40: 313-541010X | C40: 八王子市中野上町4-10 | D40: 多摩 | E40: 八王子 | L40: 事後
A41: 40 | B41: 313-541011X | C41: 八王子市中野山王3-1 | D41: 多摩 | E41: 八王子 | L41: 事後
A42: 41 | B42: 313-541014X | C42: 八王子市大和田町6-12 | D42: 多摩 | E42: 八王子 | G42: 46001 | L42: 事後
A43: 42 | B43: 313-541015X | C43: 八王子市台町3-19 | D43: 多摩 | E43: 八王子 | G43: 46001 | L43: 事後
A44: 43 | B44: 313-541019X | C44: 東村山市萩山町1-11 | D44: 多摩 | E44: 東村山 | G44: 46000 | L44: 事後
A45: 44 | B45: 313-541018X | C45: 東村山市萩山町5-6 | D45: 多摩 | E45: 東村山 | L45: 事後
A46: 45 | B46: 313-443054X | C46: 東村山市青葉町2-5 | D46: 多摩 | E46: 東村山 | L46: 事後
A47: 46 | B47: 313-541016X | C47: 小平市学園西町1-2 | D47: 多摩 | E47: 小平市 | G47: 45952 | L47: 事後
A48: 47 | B48: 313-442008I | C48: 小平市学園西町3-8 | D48: 多摩 | E48: 小平市 | I48: 45509 | J48: 8 | L48: 事後 | M48: 40048202 | N48: 西都 | P48: 8 | R48: 45604
A49: 48 | B49: 313-442009I | C49: 小平市学園西町3-5 | D49: 多摩 | E49: 小平市 | I49: 45509 | J49: 8 | L49: 事後 | M49: 40048205 | N49: 西都 | P49: 8 | R49: 45524
A50: 49 | B50: 313-586717X | C50: 八王子市大船町182 | D50: 多摩 | E50: 八王子 | L50: 事後
A51: 50 | B51: 313-400481S | C51: 立川市曙町3-27-8 | D51: 多摩 | E51: 立川市 | I51: 45530 | J51: 8 | L51: 事後 | M51: 40060832 | N51: 西都 | O51: 11 | P51: 11 | Q51: 11 | S51: 45980 | V51: 45991 | W51: 11 | X51: 50955 | Y51: 25.11 | Z51: 11 | AA51: 42 | AB51: 105862
A52: 51 | B52: 313-412023X | C52: 八王子市下柚木2-31 | D52: 多摩 | E52: 八王子 | I52: 45565 | J52: 9 | L52: 事後 | M52: 40054104 | N52: 共立 | O52: 7 | P52: 9 | Q52: 7 | S52: 45861 | T52: 45876 | V52: 45860 | W52: 7 | X52: 68120 | Y52: 25.7 | Z52: 7 | AA52: 40 | AB52: 133929
A53: 52 | B53: 313-671706X | C53: 立川市柴崎町1-1 | D53: 多摩 | E53: 立川市 | L53: 事後
A54: 53 | B54: 313-541025X | C54: 国分寺市戸倉2-5 | D54: 多摩 | E54: 国分寺 | L54: 事後
A55: 54 | B55: 313-541026X | C55: 国分寺市西恋ヶ窪1-46 | D55: 多摩 | E55: 国分寺 | L55: 事後
A56: 55 | B56: 313-541028X | C56: 国分寺市戸倉1-7 | D56: 多摩 | E56: 国分寺 | L56: 事後
A57: 56 | B57: 313-541029X | C57: 日野市新井3-1 | D57: 多摩 | E57: 日野市 | L57: 事後
A58: 57 | B58: 313-541030X | C58: 東村山市美住町1-13 | D58: 多摩 | E58: 東村山 | L58: 事後
A59: 58 | B59: 313-541031X | C59: 東村山市富士見町1-14 | D59: 多摩 | E59: 東村山 | L59: 事後
A60: 59 | B60: 313-541032X | C60: 東村山市美住町1-4 | D60: 多摩 | E60: 東村山 | L60: 事後
A61: 60 | B61: 313-541033X | C61: 東大和市清水5-1003 | D61: 多摩 | E61: 東大和 | L61: 事後
A62: 61 | B62: 313-541035X | C62: 小平市花小金井3-43 | D62: 多摩 | E62: 小平市 | L62: 事後
A63: 62 | B63: 313-541036X | C63: 小平市喜平町3-2 | D63: 多摩 | E63: 小平市 | L63: 事後
A64: 63 | B64: 313-541037X | C64: 小平市喜平町3-3 | D64: 多摩 | E64: 小平市 | L64: 事後
... A83: 82 | B83: 313-541024X | C83: 小平市喜平町3-3 | D83: 多摩 | E83: 小平市 | L83: 事後
A84: 83 | B84: 313-544002X | C84: 八王子市中野上町2-14 | D84: 多摩 | E84: 八王子 | G84: 45827 | L84: 事後
A85: 84 | B85: 313-316489X | C85: 日野市落川577 | D85: 多摩 | E85: 日野市 | I85: 45622 | J85: 11 | L85: 事後 | M85: 40060687 | N85: みつば | O85: 10 | P85: 11 | Q85: 10 | R85: 45625 | S85: 45954 | T85: 45958 | Y85: 25.1 | Z85: 10 | AA85: 40 | AB85: 258979
A86: 85 | B86: 313-412003X | C86: 小平市小川町1-2438 | D86: 多摩 | E86: 小平市 | I86: 45628 | J86: 12 | L86: 事後 | M86: 40061339 | N86: 西都 | O86: 1 | P86: 12 | Q86: 1 | S86: 46042 | T86: 46052 | Y86: 26.1 | Z86: 1 | AA86: 40 | AB86: 126904
A87: 86 | B87: 313-576801X | C87: 国分寺市南町3-25 | D87: 多摩 | E87: 国分寺 | G87: 45873 | I87: 46016 | J87: 12 | L87: 事後 | M87: 50051521 | N87: みつば | O87: 1 | P87: 12 | Q87: 1 | S87: 46042 | T87: 46052 | Y87: 26.1 | Z87: 1 | AA87: 40 | AB87: 152721
A88: 87 | B88: 313-541063X | C88: 多摩市一ノ宮3-9 | D88: 多摩 | E88: 多摩市 | L88: 事後
A89: 88 | B89: 313-543013X | C89: 国立市東1-20 | D89: 多摩 | E89: 国立市 | G89: 45978 | L89: 事後
A90: 89 | B90: 313-543040X | C90: 立川市錦町5-14 | D90: 多摩 | E90: 立川市 | G90: 45834 | L90: 事後
A91: 90 | B91: 313-543041X | C91: 立川市錦町5-2 | D91: 多摩 | E91: 立川市 | L91: 事後
A92: 91 | B92: 313-543042X | C92: 立川市柴崎町3-13 | D92: 多摩 | E92: 立川市 | G92: 45910 | L92: 事後
A93: 92 | B93: 313-543043X | C93: 立川市柴崎町3-17 | D93: 多摩 | E93: 立川市 | L93: 事後
A94: 93 | B94: 313-543044X | C94: 立川市柴崎町3-18 | D94: 多摩 | E94: 立川市 | L94: 事後
A95: 94 | B95: 313-543045X | C95: 立川市柴崎町3-15 | D95: 多摩 | E95: 立川市 | L95: 事後
A96: 94 | B96: 442-408193 | C96: 小平市学園西町1-11 | D96: 多摩 | E96: 小平市 | I96: 45824 | J96: 6 | L96: 事後 | M96: 530910 | N96: 西都 | O96: 9 | P96: 6 | Q96: 9 | S96: 45905 | T96: 45911 | V96: 45922 | W96: 9 | X96: 106930 | Y96: 25.9 | Z96: 9 | AA96: 101 | AB96: 279214
A97: 95 | B97: 313-543046X | C97: 立川市若葉町2-6 | D97: 多摩 | E97: 立川市 | L97: 事後
A98: 96 | B98: 313-543047X | C98: 立川市若葉町2-19 | D98: 多摩 | E98: 立川市 | L98: 事後
A99: 97 | B99: 313-543048X | C99: 立川市若葉町2-32 | D99: 多摩 | E99: 立川市 | L99: 事後
A100: 98 | B100: 313-543024X | C100: 八王子市明神町4-23 | D100: 多摩 | E100: 八王子 | G100: 45827 | L100: 事後
A101: 99 | B101: 313-543022X | C101: 東大和市向原1-1881 | D101: 多摩 | E101: 東大和 | G101: 45834 | L101: 事後
A102: 100 | B102: 313-543025X | C102: 八王子市富士見町20 | D102: 多摩 | E102: 八王子 | G102: 45947 | L102: 事後
A103: 101 | B103: 313-543026X | C103: 八王子市富士見町23 | D103: 多摩 | E103: 八王子 | G103: 45947 | L103: 事後
A104: 102 | B104: 313-543029X | C104: 八王子市暁町1-5 | D104: 多摩 | E104: 八王子 | G104: 45827 | L104: 事後
A105: 103 | B105: 313-543034X | C105: 八王子市中野町2546 | D105: 多摩 | E105: 八王子 | L105: 事後
A106: 104 | B106: 313-543035X | C106: 八王子市中野町2550 | D106: 多摩 | E106: 八王子 | L106: 事後
A107: 105 | B107: 313-543036X | C107: 八王子市中野山王2-32 | D107: 多摩 | E107: 八王子 | L107: 事後
A108: 106 | B108: 313-543037X | C108: 八王子市みつい台1-3 | D108: 多摩 | E108: 八王子 | G108: 45947 | L108: 事後
A109: 107 | B109: 313-543038X | C109: 八王子市みつい台1-27 | D109: 多摩 | E109: 八王子 | L109: 事後
A110: 108 | B110: 313-543039X | C110: 八王子市丸山町15 | D110: 多摩 | E110: 八王子 | G110: 45947 | L110: 事後
A111: 109 | B111: 313-541059X | C111: 八王子市大和田町5-2 | D111: 多摩 | E111: 八王子 | L111: 事後
A112: 110 | B112: 313-541061X | C112: 八王子市明神町2-20 | D112: 多摩 | E112: 八王子 | L112: 事後
A113: 111 | B113: 313-543023X | C113: 八王子市明神町4-9 | D113: 多摩 | E113: 八王子 | G113: 45947 | L113: 事後
A114: 112 | B114: 313-543005X | C114: 小平市学園東町3-6 | D114: 多摩 | E114: 小平市 | G114: 45890 | L114: 事後
A115: 113 | B115: 313-541064X | C115: 多摩市和田1261 | D115: 多摩 | E115: 多摩市 | L115: 事後
A116: 114 | B116: 313-541066X | C116: 日野市日野本町5-11 | D116: 多摩 | E116: 日野市 | L116: 事後
A117: 115 | B117: 313-541068X | C117: 日野市落川334 | D117: 多摩 | E117: 日野市 | L117: 事後
A118: 116 | B118: 313-543006X | C118: 小平市花小金井7-21 | D118: 多摩 | E118: 小平市 | L118: 事後
...

Sheet 杭台帳(事後)(西)
A1: 整理番号 | B1: 工事番号 | C1: 住 所 | D1: NC区分 | E1: 住所（行政区） | F1: 工期 | G1: 現場完了 予定日 | H1: 現場予定日 | I1: 受注日(後) | J1: 受注月(後) | K1: 受注番号(後) | L1: 区分(後) | M1: 顧客会社担当者(後) | N1: 発行番号(後) | O1: 外注先(後) | P1: 納品 月(後) | Q1: 外注 発注月(後) | R1: 外注納品月(後) | S1: 申請 提出日 (ガスor役所)2 | T1: 現場完了 予定日3 | U1: 現場予定日（後） | V1: 杭購入金額 | W1: 外注支払月(後) | X1: 外注支払月(後)(月のみ) | Y1: 外注支払額(後) | Z1: 入金月(後) | AA1: 入金月(後)（月のみ） | AB1: 精算 グループ(後) | AC1: 入金額(後) | AE1: =SUM(Z:Z) -> 9088.09
A2: 1 | B2: 311-242242X | C2: 世田谷区玉川4-29 | D2: 西部 | E2: 世田谷 | F2: 未定 | G2: 45789 | AE2: =AE1+'杭台帳(西)'!AE1 -> 71699.09
A3: 2 | B3: 311-042334X | C3: 三鷹市牟礼6-25 | D3: 西部 | E3: 三鷹市 | I3: 44851 | J3: 10 | L3: 事後 | O3: 共立 | Q3: 10
A4: 3 | B4: 311-142157J | C4: 世田谷区赤堤1-36 | D4: 西部 | E4: 世田谷 | I4: 44908 | J4: 12 | L4: 事後 | O4: 共立 | Q4: 2
A5: 4 | B5: 311-145026B | C5: 世田谷区玉川台2-28 | D5: 西部 | E5: 世田谷 | I5: 44940 | J5: 1 | L5: 事後 | O5: 共立 | Q5: 1
A6: 5 | B6: 332-116370 | C6: 大田区東蒲田2-30 | D6: 南部 | E6: 大田区 | I6: 45019 | J6: 4 | L6: 事後 | M6: 8700 | O6: 共立 | Q6: 4
A7: 6 | B7: 311-042493X | C7: 世田谷区駒沢2-7 | D7: 西部 | E7: 世田谷 | I7: 45146 | J7: 8 | L7: 事後 | O7: みつば | Q7: 8
A8: 7 | B8: 311-042079W | C8: 世田谷区等々力2-9 | D8: 西部 | E8: 世田谷 | I8: 45216 | J8: 10 | L8: 事後 | N8: 300279776 | O8: 共立 | Q8: 10
A9: 8 | B9: 311-142137I | C9: 世田谷区経堂3-29 | D9: 西部 | E9: 世田谷 | I9: 45217 | J9: 10 | L9: 事後 | N9: 30028292 | O9: 共立 | Q9: 10
A10: 9 | B10: 113-041152Y | C10: 大田区大森中3-15-18 | D10: 南部 | E10: 大田区 | I10: 45300 | J10: 1 | L10: 事後 | N10: 30038651 | O10: 共立 | Q10: 1
A11: 10 | B11: 113-212032X | C11: 大田区中央4-13-8 | D11: 南部 | E11: 大田区 | I11: 45322 | J11: 1 | L11: 事後 | N11: 30041726 | O11: 共立 | Q11: 2
A12: 11 | B12: 311-443203X | C12: 三鷹市井の頭2-34 | D12: 西部 | E12: 三鷹市 | F12: 45566
A13: 12 | B13: 311-242100F | C13: 世田谷区用賀1-20 | D13: 西部 | E13: 世田谷 | I13: 45383 | J13: 4 | L13: 事後 | N13: 30043415 | O13: 共立 | Q13: 2
A14: 13 | B14: 113-342532X | C14: 大田区山王1-37-6 | D14: 南部 | E14: 大田区 | I14: 45384 | J14: 4 | L14: 事後 | N14: 40000155 | O14: 共立 | Q14: 4
A15: 14 | B15: 113-342533X | C15: 大田区山王1-29-9 | D15: 南部 | E15: 大田区 | I15: 45385 | J15: 4 | L15: 事後 | N15: 40000156 | O15: 共立 | Q15: 4
A16: 15 | B16: 113-319020X | C16: 大田区東糀谷4-10 | D16: 南部 | E16: 大田区 | I16: 45390 | J16: 4 | L16: 事後 | N16: 40000346 | O16: みつば | Q16: 4
A17: 16 | B17: 332-105530 | C17: 大田区山王1-38 | D17: 南部 | E17: 大田区 | I17: 45393 | J17: 4 | L17: 事後 | M17: 8700 | O17: みつば | P17: 6 | Q17: 4 | R17: 6 | W17: 45838 | X17: 6 | Y17: 139450 | Z17: 25.6 | AA17: 6 | AB17: 101 | AC17: 364416.01
A18: 17 | B18: 113-311064X | C18: 大田区大森本町2-29-1 | D18: 南部 | E18: 大田区 | I18: 45425 | J18: 5 | L18: 事後 | N18: 40003683 | O18: みつば | Q18: 4
A19: 18 | B19: 411-319094A | C19: 和光市下新倉4-4 | D19: 北部 | E19: 和光市 | I19: 45443 | J19: 5 | L19: 事後 | N19: 40023701 | O19: 共立 | Q19: 5
A20: 19 | B20: 113-541508X | C20: 大田区西六郷1-5-3 | D20: 南部 | E20: 大田区 | F20: 45931 | G20: -
A21: 20 | B21: 113-590023X | C21: 大田区蒲田3-24-4 | D21: 南部 | E21: 大田区 | F21: 45931 | G21: -
A22: 21 | B22: 113-590024X | C22: 大田区羽田4-4-29 | D22: 南部 | E22: 大田区 | F22: 45931
A23: 22 | B23: 113-541509X | C23: 大田区東蒲田2-29-16 | D23: 南部 | E23: 大田区 | F23: 45931 | G23: - | H23: 8/18
A24: 23 | B24: 113-541512X | C24: 大田区東糀谷4-6-5 | D24: 南部 | E24: 大田区 | F24: 45931 | G24: - | H24: 8/18
A25: 24 | B25: 113-541506X | C25: 大田区千鳥3-15-1 | D25: 南部 | E25: 大田区 | F25: 45931 | G25: - | H25: 8/18
A26: 25 | B26: 113-541507X | C26: 大田区西蒲田7-60-9 | D26: 南部 | E26: 大田区 | F26: 45931 | G26: - | H26: 8/18
A27: 26 | B27: 113-590022X | C27: 大田区大森北3-30-5 | D27: 南部 | E27: 大田区 | F27: 45931 | G27: - | H27: 8/9
A28: 27 | B28: 113-541511X | C28: 大田区大森南3-8-1 | D28: 南部 | E28: 大田区 | F28: 45931 | G28: - | H28: 7/25
A29: 28 | B29: 113-315022X | C29: 大田区多摩川2-12-25 | D29: 南部 | E29: 大田区 | I29: 45643 | J29: 12 | L29: 事後 | N29: 40039254 | O29: みつば | Q29: 5
A30: 29 | B30: 113-312092X | C30: 大田区田園調布5-15-23 | D30: 南部 | E30: 大田区 | I30: 45643 | J30: 12 | L30: 事後 | N30: 40039291 | O30: みつば | Q30: 5
A31: 30 | B31: 113-541510F | C31: 大田区大森東2-19-10 | D31: 南部 | E31: 大田区
A32: 31 | B32: 113-541505F | C32: 大田区西馬込2-34-1 | D32: 南部 | E32: 大田区
A33: 32 | B33: 411-316233A | C33: 新座市西堀1-11 | D33: 北部 | E33: 新座市 | I33: 45684 | J33: 1 | L33: 事後 | M33: 松田 | N33: 40040471 | O33: 共立 | P33: 8 | Q33: 6 | R33: 7 | S33: 8/5JP | W33: 45869 | X33: 7 | Y33: 68490 | Z33: 25.8 | AA33: 8 | AB33: 30 | AC33: 136391
A34: 33 | B34: 311-541030X | C34: 清瀬市元町2-10 | D34: 西部 | E34: 清瀬市 | F34: 45931 | G34: 45789
A35: 34 | B35: 311-541011X | C35: 東久留米市滝山6-2 | D35: 西部 | E35: 東久留 | F35: 45931 | G35: -
A36: 35 | B36: 311-541010X | C36: 東久留米市滝山6-2 | D36: 西部 | E36: 東久留 | F36: 45931 | G36: -
A37: 36 | B37: 311-641019X | C37: 東久留米市南沢3-1 | D37: 西部 | E37: 東久留 | F37: 46113
A38: 37 | B38: 311-641028X | C38: 東久留米市滝山6-1 | D38: 西部 | E38: 東久留 | F38: 46113 | G38: -
A39: 38 | B39: 311-641029X | C39: 東久留米市滝山6-1 | D39: 西部 | E39: 東久留 | F39: 46113 | G39: 45803
A40: 39 | B40: 311-641030X | C40: 東久留米市滝山7-19 | D40: 西部 | E40: 東久留 | F40: 46113 | G40: 45803
A41: 40 | B41: 311-641033F | C41: 東久留米市本町4-9 | D41: 西部 | E41: 東久留 | F41: 46113
A42: 41 | B42: 311-641020F | C42: 東久留米市南沢3-5 | D42: 西部 | E42: 東久留 | F42: 46113
A43: 42 | B43: 311-641018F | C43: 東久留米市中央町1-1 | D43: 西部 | E43: 東久留 | F43: 46113
A44: 43 | B44: 311-641012F | C44: 東久留米市八幡町3-3 | D44: 西部 | E44: 東久留 | F44: 46113
A45: 44 | B45: 311-641016F | C45: 東久留米市前沢5-11 | D45: 西部 | E45: 東久留 | F45: 46113
A46: 45 | B46: 311-641014F | C46: 東久留米市滝山4-11 | D46: 西部 | E46: 東久留 | F46: 46113
A47: 46 | B47: 311-042488X | C47: 世田谷区太子堂2-6 | D47: 西部 | E47: 世田谷 | I47: 45727 | J47: 3 | L47: 事後 | N47: 40046005 | O47: 共立 | Q47: 7
A48: 47 | B48: 311-442182M | C48: 武蔵野市境南5-3 | D48: 西部 | E48: 武蔵野 | I48: 45727 | J48: 3 | L48: 事後 | N48: 40046306 | O48: 共立 | Q48: 12
A49: 48 | B49: 311-442183M | C49: 武蔵野市境南5-1 | D49: 西部 | E49: 武蔵野 | I49: 45728 | J49: 3 | L49: 事後 | M49: 赤羽 | N49: 40046307 | O49: 共立 | Q49: 12 | R49: 3 | S49: JP | W49: 45717 | X49: 3
A50: 49 | B50: 113-533504X | C50: 大田区羽田旭町11-1 | D50: 南部 | E50: 大田区 | F50: 45809 | G50: -
A51: 50 | B51: 332-403647 | C51: 大田区蒲田4-28-5 | D51: 南部 | E51: 大田区 | I51: 45741 | J51: 3 | L51: 事後 | M51: 8700 | O51: みつば | P51: 10 | Q51: 9 | R51: 10 | W51: 45961 | X51: 10 | Y51: 30640 | Z51: 25.1 | AA51: 10 | AB51: 101 | AC51: 77250
A52: 51 | B52: 113-400709H | C52: 大田区中央7-4-3 | D52: 南部 | E52: 大田区 | F52: 45569 | G52: 45562 | I52: 45744 | J52: 3 | L52: 事後 | O52: みつば | P52: 3 | Q52: 11 | R52: 2 | W52: 45708 | X52: 2
A53: 52 | B53: 113-542644X | C53: 大田区南馬込1-58-11 | D53: 南部 | E53: 大田区 | F53: 45748 | G53: 45768
A54: 53 | B54: 113-542641X | C54: 大田区大森北6-16-6 | D54: 南部 | E54: 大田区 | F54: 2025/4/1→10/1
A55: 54 | B55: 311-543243X | C55: 武蔵野市桜堤1-1 | D55: 西部 | E55: 武蔵野 | F55: 45748 | G55: -
A56: 55 | B56: 311-543244X | C56: 武蔵野市関前5-8 | D56: 西部 | E56: 武蔵野 | F56: 45748 | G56: -
A57: 56 | B57: 311-543246X | C57: 武蔵野市西久保2-1 | D57: 西部 | E57: 武蔵野 | F57: 45748 | G57: 45719
A58: 57 | B58: 311-543247X | C58: 武蔵野市境南町1-2 | D58: 西部 | E58: 武蔵野 | F58: 45748 | G58: -
A59: 58 | B59: 311-543248X | C59: 武蔵野市吉祥寺南町3-10 | D59: 西部 | E59: 武蔵野 | F59: 45748 | G59: -
A60: 59 | B60: 311-543252X | C60: 武蔵野市境1-20 | D60: 西部 | E60: 武蔵野 | F60: 45748 | G60: -
A61: 60 | B61: 311-543253X | C61: 武蔵野市境1-16 | D61: 西部 | E61: 武蔵野 | F61: 45748 | G61: -
A62: 61 | B62: 311-543254X | C62: 武蔵野市関前4-2 | D62: 西部 | E62: 武蔵野 | F62: 45748 | G62: -
A63: 62 | B63: 311-543255X | C63: 武蔵野市西久保1-16 | D63: 西部 | E63: 武蔵野 | F63: 45748 | G63: -
A64: 63 | B64: 311-543257X | C64: 東久留米市小山5-1 | D64: 西部 | E64: 東久留 | F64: 45748 | G64: -
A65: 64 | B65: 311-543259X | C65: 東久留米市東本町4 | D65: 西部 | E65: 東久留 | F65: 45748 | G65: -
A66: 65 | B66: 311-543260X | C66: 東久留米市新川1-15 | D66: 西部 | E66: 東久留 | F66: 45748 | G66: -
A67: 66 | B67: 311-543261X | C67: 東久留米市本町1-6 | D67: 西部 | E67: 東久留 | F67: 45748 | G67: -
A68: 67 | B68: 311-543259X | C68: 東久留米市東本町4 | D68: 西部 | E68: 東久留 | F68: 中止
A69: 68 | B69: 113-412066X | C69: 大田区東六郷3-3 | D69: 南部 | E69: 大田区 | I69: 45756 | J69: 4 | L69: 事後 | N69: 40057688 | O69: みつば | P69: 12 | Q69: 7 | R69: 12 | S69: なし | W69: 46022 | X69: 12 | Y69: 28660 | Z69: 25.12 | AA69: 12 | AB69: 10 | AC69: 50228
A70: 69 | B70: 113-672201X | C70: 大田区東雪谷2-9-1 | D70: 南部 | E70: 大田区 | F70: 46328 | G70: -
A71: 70 | B71: 311-142143I | C71: 世田谷区経堂5-21 | D71: 西部 | E71: 世田谷 | I71: 45756 | J71: 4 | L71: 事後 | N71: 40058715 | O71: 共立 | Q71: 11
A72: 71 | B72: 311-242091M | C72: 世田谷区用賀4-36 | D72: 西部 | E72: 世田谷 | I72: 45756 | J72: 4 | L72: 事後 | N72: 40058720 | O72: みつば | P72: 7 | Q72: 11 | R72: 7 | S72: TG | W72: 45869 | X72: 7 | Y72: 273000 | Z72: 25.8 | AA72: 8 | AB72: 30 | AC72: 574732
A73: 72 | B73: 113-574201X | C73: 大田区蒲田5-39-3 | D73: 南部 | E73: 大田区 | F73: 45784 | G73: 45768
A74: 73 | B74: 512-412621 | C74: 和光市中央1-2 | D74: 北部 | E74: 和光市 | F74: 45687 | I74: 45756 | J74: 4 | L74: 事後 | M74: 保全 大久保 | N74: 40063661 | O74: 塩川 | Q74: 3
A75: 74 | B75: 311-242102F | C75: 世田谷区瀬田2-11 | D75: 西部 | E75: 世田谷 | I75: 45756 | J75: 4 | L75: 事後 | N75: 40062942 | O75: 共立 | Q75: 12
A76: 75 | B76: 311-342137M | C76: 武蔵野市緑町1-5 | D76: 西部 | E76: 武蔵野 | I76: 45756 | J76: 4 | L76: 事後 | M76: 赤羽 | N76: 40062576 | O76: 共立 | Q76: 12 | R76: 5 | S76: JP | W76: 45778 | X76: 5
A77: 76 | B77: 113-419005X | C77: 大田区下丸子2-22 | D77: 南部 | E77: 大田区 | I77: 45758 | J77: 4 | L77: 事後 | N77: 40064880 | O77: みつば | Q77: 1
A78: 77 | B78: 332-108603 | C78: 大田区山王4-9-26 | D78: 南部 | E78: 大田区 | I78: 45758 | J78: 4 | L78: 事後 | M78: 保全千葉 | O78: みつば | P78: 6 | Q78: 1 | R78: 6 | W78: 45838 | X78: 6 | Y78: 59510 | Z78: 25.6 | AA78: 6 | AB78: 101 | AC78: 149588
A79: 78 | B79: 332-403095 | C79: 大田区山王2-2-7 | D79: 南部 | E79: 大田区 | I79: 45758 | J79: 4 | L79: 事後 | M79: 保全千葉 | O79: みつば | P79: 2 | Q79: 1 | R79: 2 | W79: 46081 | X79: 2 | Y79: 36160 | Z79: 26.2 | AA79: 2 | AB79: 101 | AC79: 104810
A80: 79 | B80: 311-586300X | C80: 三鷹市下連雀6-2-6 | D80: 西部 | E80: 三鷹市 | F80: 45887 | G80: -
A81: 80 | B81: 113-415028X | C81: 大田区多摩川1-16 | D81: 南部 | E81: 大田区 | I81: 45764 | J81: 4 | L81: 事後 | N81: 40067635 | O81: みつば | Q81: 1
A82: 81 | B82: 311-342202X | C82: 武蔵野市境南町2-23 | D82: 西部 | E82: 武蔵野 | I82: 45764 | J82: 4 | L82: 事後 | M82: 赤羽 | N82: 40067880 | O82: 星 | Q82: 2 | R82: 3 | S82: JP | W82: 45717 | X82: 3
A83: 82 | B83: 113-312100X | C83: 大田区鵜木1-10 | D83: 南部 | E83: 大田区 | I83: 45764 | J83: 4 | L83: 事後 | N83: 40068294 | O83: みつば | Q83: 2
A84: 83 | B84: 113-471219X | C84: 大田区石川町2-16-10 | D84: 南部 | E84: 大田区 | F84: 45922 | G84: - | H84: 8/6
A85: 84 | B85: 113-471217Y | C85: 大田区鵜の木1-12-7 | D85: 南部 | E85: 大田区 | F85: 45870 | G85: -
A86: 85 | B86: 113-514039X | C86: 大田区田園調布5-55-5 | D86: 南部 | E86: 大田区 | F86: 45845 | G86: -
A87: 86 | B87: 113-581204X | C87: 大田区中央2-11-2 | D87: 南部 | E87: 大田区 | F87: 45901 | G87: - | H87: 8/18 | I87: 46035 | J87: 1 | L87: 事後 | M87: 岩重 | N87: 50053093 | O87: みつば | Q87: 1 | S87: 2/17JP
A88: 87 | B88: 311-843325K | C88: 世田谷区尾山台3-5 | D88: 西部 | E88: 世田谷 | F88: 45931 | G88: -
A89: 88 | B89: 311-142102M | C89: 世田谷区瀬田4-16 | D89: 西部 | E89: 世田谷 | F89: 44348 | G89: -
A90: 89 | B90: 332-401952 | C90: 大田区中央4-20-9 | D90: 南部 | E90: 大田区 | I90: 45777 | J90: 4 | L90: 事後 | M90: 8700 | O90: みつば | P90: 6 | Q90: 2 | R90: 6 | W90: 45838 | X90: 6 | Y90: 49090 | Z90: 25.6 | AA90: 6 | AB90: 101 | AC90: 123288.52
A91: 90 | B91: 113-412074X | C91: 大田区大森西2-22-20 | D91: 南部 | E91: 大田区 | I91: 45777 | J91: 4 | L91: 事後 | N91: 40070099 | O91: みつば | P91: 6 | Q91: 2 | R91: 6 | W91: 45838 | X91: 6 | Y91: 65160 | Z91: 25.6 | AA91: 6 | AB91: 10 | AC91: 114479
A92: 91 | B92: 311-342136M | C92: 武蔵野市緑町1-5 | D92: 西部 | E92: 武蔵野 | I92: 45777 | J92: 4 | L92: 事後 | N92: 40070727 | O92: 共立 | Q92: 2
A93: 92 | B93: 311-243083J | C93: 西東京市中町4-6 | D93: 西部 | E93: 西東京 | I93: 45777 | J93: 4 | L93: 事後 | N93: 40071209 | O93: みつば | Q93: 2
A94: 93 | B94: 311-242138J | C94: 西東京市富士町5-7 | D94: 西部 | E94: 西東京 | I94: 45778 | J94: 5 | L94: 事後 | N94: 40071266 | O94: みつば | Q94: 2
A95: 94 | B95: 113-519004X | C95: 大田区鵜の木2-29-7 | D95: 南部 | E95: 大田区 | F95: 45794 | G95: 45765 | I95: 45924 | J95: 9 | L95: 事後 | M95: 仲川 | N95: 50033691 | O95: みつば | Q95: 9
A96: 95 | B96: 411-519012A | C96: 新座市野火止8-1-24 | D96: 北部 | E96: 新座市 | F96: 45796 | G96: 45765
A97: 96 | B97: 113-411048X | C97: 大田区矢口3-17-13 | D97: 南部 | E97: 大田区 | I97: 45784 | J97: 5 | L97: 事後 | N97: 40071986 | O97: みつば | P97: 6 | Q97: 3 | R97: 6 | W97: 45838 | X97: 6 | Y97: 107010 | Z97: 25.6 | AA97: 6 | AB97: 10 | AC97: 187204
A98: 97 | B98: 113-419019X | C98: 大田区千鳥3-11-1 | D98: 南部 | E98: 大田区 | I98: 45789 | J98: 5 | L98: 事後 | N98: 40072036 | O98: みつば | P98: 6 | Q98: 3 | R98: 6 | W98: 45838 | X98: 6 | Y98: 77820 | Z98: 25.6 | AA98: 6 | AB98: 10 | AC98: 129098
A99: 98 | B99: 332-401848 | C99: 大田区上池台4-2-15 | D99: 南部 | E99: 大田区 | I99: 45789 | J99: 5 | L99: 事後 | M99: 8700 | O99: みつば | P99: 6 | Q99: 3 | R99: 6 | W99: 45838 | X99: 6 | Y99: 42180 | Z99: 25.6 | AA99: 6 | AB99: 101 | AC99: 106786.01
A100: 99 | B100: 332-407345 | C100: 大田区上池台1-53 | D100: 南部 | E100: 大田区 | I100: 45789 | J100: 5 | L100: 事後 | M100: 8700 | O100: みつば | P100: 2 | Q100: 3 | R100: 1 | W100: 46081 | X100: 2 | Y100: 40440 | Z100: 26.2 | AA100: 2 | AB100: 101 | AC100: 116011
...

Sheet 杭台帳(事後)(神)
A1: 整理番号 | B1: 工事番号 | C1: 住 所 | D1: NC区分 | E1: 住所（行政区） | F1: 受注日(後) | G1: 受注月(後) | H1: 受注番号(後) | I1: 区分(後) | J1: 発行番号(後) | K1: 外注先(後) | L1: 納品 月(後) | M1: 外注 発注月(後) | N1: 外注納品月(後) | O1: 杭購入金額 | P1: 外注支払月(後) | Q1: 外注支払月(後)(月のみ) | R1: 外注支払額(後) | S1: 入金月(後) | T1: 入金月(後)（月のみ） | U1: 精算 グループ(後) | V1: 入金額(後) | Y1: =SUM(U:U) -> 11060
A2: 1 | B2: 622-108485 | C2: 幸区中幸町4-29-3 | D2: 神奈川 | E2: 幸区中 | F2: 45113 | G2: 7 | I2: 事後 | J2: 30013944 | K2: 共立 | M2: 7 | Y2: =Y1+'杭台帳(神)'!Y1 -> 11060
A3: 2 | B3: 512-042227X | C3: 港北区篠原町81 | D3: 神奈川 | E3: 港北区 | F3: 45143 | G3: 8 | I3: 事後 | J3: 30018603 | K3: 共立 | M3: 8
A4: 3 | B4: 512-312060X | C4: 港北区富士塚1-9-3 | D4: 神奈川 | E4: 港北区
A5: 4 | B5: 512-311041X | C5: 鶴見区矢向4-7-4 | D5: 神奈川 | E5: 鶴見区
A6: 5 | B6: 511-219156X | C6: 横須賀市長沢3-7 | D6: 神奈川 | E6: 横須賀 | F6: 45194 | G6: 9 | I6: 事後 | J6: 30024979 | K6: みつば | L6: 7 | M6: 9 | N6: 7 | P6: 45867 | Q6: 7 | R6: 117310 | S6: 25.7 | T6: 7 | U6: 20 | V6: 297372
A7: 6 | B7: 513-214018X | C7: 宮前区平5-8-35 | D7: 神奈川 | E7: 宮前区 | F7: 45217 | G7: 10 | I7: 事後 | J7: 30027716 | K7: みつば | M7: 10
A8: 7 | B8: 622-301632 | C8: 麻生区王禅寺西3-27 | D8: 神奈川 | E8: 麻生区 | F8: 45225 | G8: 10 | I8: 事後 | J8: 30029509 | K8: みつば | M8: 10
A9: 8 | B9: 512-443101T | C9: 神奈川区白幡向町17-15 | D9: 神奈川 | E9: 神奈川
A10: 9 | B10: 513-214006X | C10: 中原区今井仲町8-30 | D10: 神奈川 | E10: 中原区 | F10: 45341 | G10: 2 | I10: 事後 | J10: 30043686 | K10: 占部 | M10: 2
A11: 10 | B11: 512-843145X | C11: 港北区篠原東3-17-4 | D11: 神奈川 | E11: 港北区 | F11: 45341 | G11: 2 | I11: 事後 | J11: 30043675 | K11: 共立 | M11: 2
A12: 11 | B12: 513-314146X | C12: 宮前区西野川1-38 | D12: 神奈川 | E12: 宮前区 | F12: 45341 | G12: 2 | I12: 事後 | J12: 30043720 | K12: 共立 | L12: 6 | M12: 2 | N12: 6 | S12: 25.9 | T12: 9 | U12: 21 | V12: 139623
A13: 12 | B13: 513-214132X | C13: 宮前区有馬8-7 | D13: 神奈川 | E13: 宮前区 | F13: 45341 | G13: 2 | I13: 事後 | J13: 30043688 | K13: みつば | L13: 5 | M13: 2 | N13: 5 | P13: 45432 | Q13: 5 | R13: 69950 | S13: 25.9 | T13: 9 | U13: 21 | V13: 138194
A14: 13 | B14: 513-219176X | C14: 宮前区潮見台9-2 | D14: 神奈川 | E14: 宮前区 | F14: 45341 | G14: 2 | I14: 事後 | J14: 30043691 | K14: みつば | L14: 5 | M14: 2 | N14: 5 | P14: 45797 | Q14: 5 | R14: 303000 | S14: 25.6 | T14: 6 | U14: 21 | V14: 463356
A15: 14 | B15: 513-311010X | C15: 高津区下野毛3-14-5 | D15: 神奈川 | E15: 高津区 | F15: 45341 | G15: 2 | I15: 事後 | J15: 30043713 | K15: みつば | M15: 2
A16: 15 | B16: 513-314005X | C16: 多摩区宿河原7-8-1 | D16: 神奈川 | E16: 多摩区 | F16: 45391 | G16: 4 | I16: 事後 | J16: 40001018 | K16: みつば | M16: 4
A17: 16 | B17: 513-219155X | C17: 宮前区菅生6-2-4 | D17: 神奈川 | E17: 宮前区 | F17: 45404 | G17: 4 | I17: 事後 | J17: 40010045 | K17: みつば | M17: 4
A18: 17 | B18: 513-212007X | C18: 宮前区馬絹4-11-37 | D18: 神奈川 | E18: 宮前区 | F18: 45404 | G18: 4 | I18: 事後 | J18: 40010209 | K18: 共立 | M18: 4 | N18: 8
A19: 18 | B19: 513-412016X | C19: 宮前区鷺沼1-18-10 | D19: 神奈川 | E19: 宮前区
A20: 19 | B20: 622-400802 | C20: 高津区溝口5-7-10 | D20: 神奈川 | E20: 高津区
A21: 20 | B21: 512-411028X | C21: 神奈川区入江1-11-3 | D21: 神奈川 | E21: 神奈川
A22: 21 | B22: 622-400946 | C22: 高津区下野毛3-5-10 | D22: 神奈川 | E22: 高津区
A23: 22 | B23: 513-214194X | C23: 宮前区西野川1-18 | D23: 神奈川 | E23: 宮前区 | F23: 45443 | G23: 5 | I23: 事後 | J23: 40038408 | K23: 共立 | L23: 6 | M23: 5 | N23: 6 | S23: 25.9 | T23: 9 | U23: 21 | V23: 89813
A24: 23 | B24: 512-403008M | C24: 港北区蓑輪町1-25-25 | D24: 神奈川 | E24: 港北区
A25: 24 | B25: 513-211063X | C25: 多摩区宿河原1-23-5 | D25: 神奈川 | E25: 多摩区 | F25: 45439 | G25: 5 | I25: 事後 | J25: 40037982 | K25: みつば | M25: 5
A26: 25 | B26: 622-211100 | C26: 中原区上平間594 | D26: 神奈川 | E26: 中原区 | F26: 45443 | G26: 5 | I26: 事後 | J26: 40015029 | K26: みつば | M26: 5
A27: 26 | B27: 622-210020 | C27: 中原区新城1-9 | D27: 神奈川 | E27: 中原区 | F27: 45443 | G27: 5 | I27: 事後 | J27: 40015054 | K27: みつば | M27: 5
A28: 27 | B28: 513-142161X | C28: 川崎区大島1-26-7 | D28: 神奈川 | E28: 川崎区 | F28: 45434 | G28: 5 | I28: 事後 | J28: 40035479 | K28: みつば | L28: 5 | M28: 5 | N28: 7 | P28: 45493 | Q28: 7 | R28: 327000 | S28: 25.9 | T28: 9 | U28: 21 | V28: 499648
A29: 28 | B29: 512-319282A | C29: 都筑区池辺町2352 | D29: 神奈川 | E29: 都筑区 | F29: 45460 | G29: 6 | I29: 事後 | J29: 40041466 | K29: みつば | M29: 6
A30: 29 | B30: 513-403014M | C30: 多摩区登戸918-6 | D30: 神奈川 | E30: 多摩区
A31: 30 | B31: 513-314111X | C31: 宮前区馬絹4-13-13 | D31: 神奈川 | E31: 宮前区 | F31: 45489 | G31: 7 | I31: 事後 | J31: 40046004 | K31: みつば | M31: 7
A32: 31 | B32: 513-319044X | C32: 宮前区梶ヶ谷1385 | D32: 神奈川 | E32: 宮前区 | F32: 45391 | G32: 4 | I32: 事後 | J32: 40045533 | K32: 共立
A33: 32 | B33: 513-142286X | C33: 高津区溝口5-10-9 | D33: 神奈川 | E33: 高津区 | F33: 44958 | G33: 2 | I33: 事後 | J33: 20041435 | K33: みつば | L33: 5 | M33: 2 | N33: 8 | P33: 45524 | Q33: 8 | R33: 124000 | S33: 25.9 | T33: 9 | U33: 21 | V33: 187820
A34: 33 | B34: 513-142122X | C34: 幸区鹿島田1-5-16 | D34: 神奈川 | E34: 幸区鹿 | F34: 44936 | G34: 1 | I34: 事後 | J34: 20037602 | K34: 共立 | L34: 12 | M34: 9 | N34: 12 | P34: 46053 | Q34: 1 | R34: 52850 | S34: 26.1 | T34: 1 | U34: 21 | V34: 94793
A35: 34 | B35: 511-243139S | C35: 横須賀市西逸見町2-79～2-75 | D35: 神奈川 | E35: 横須賀 | F35: 44866 | G35: 11 | I35: 事後 | J35: 20027686 | K35: みつば | L35: 12 | M35: 11 | N35: 12 | P35: 46022 | Q35: 12 | R35: 44770 | S35: 25.12 | T35: 12 | U35: 23 | V35: 107340
A36: 35 | B36: 512-219229X | C36: 都筑区牛久保町1893-7 | D36: 神奈川 | E36: 都筑区 | F36: 44915 | G36: 12 | I36: 事後 | J36: 20034940 | K36: みつば | L36: 1 | M36: 12 | N36: 1 | P36: 46053 | Q36: 1 | R36: 172380 | S36: 26.1 | T36: 1 | U36: 20 | V36: 339597
A37: 36 | B37: 513-014094A | C37: 多摩区菅北浦1-11 | D37: 神奈川 | E37: 多摩区 | F37: 45070 | G37: 5 | I37: 事後 | J37: 30006718 | K37: みつば | M37: 5
A38: 37 | B38: 511-342110J | C38: 横須賀市小川町3-4 | D38: 神奈川 | E38: 横須賀 | F38: 45453 | G38: 6 | I38: 事後 | J38: 40040445 | K38: みつば | L38: 7 | M38: 6 | N38: 7 | P38: 45867 | Q38: 7 | R38: 110130 | S38: 25.8 | T38: 8 | U38: 21 | V38: 255357
A39: 38 | B39: 513-342108P | C39: 麻生区百合丘1-24-38 | D39: 神奈川 | E39: 麻生区 | F39: 45485 | G39: 7 | I39: 事後 | J39: 40045417 | K39: みつば | L39: 7 | M39: 7 | N39: 6 | P39: 45834 | Q39: 6 | R39: 64570 | S39: 25.7 | T39: 7 | U39: 21 | V39: 125683
A40: 39 | B40: 513-214129A | C40: 宮前区西野川1-12 | D40: 神奈川 | E40: 宮前区 | F40: 45453 | G40: 6 | I40: 事後 | J40: 40040406 | K40: 共立 | M40: 6
A41: 40 | B41: 513-111032X | C41: 多摩区堰2-1-9 | D41: 神奈川 | E41: 多摩区 | F41: 45453 | G41: 6 | I41: 事後 | J41: 40040414 | K41: 共立 | M41: 6
A42: 41 | B42: 512-400962N | C42: 港北区箕輪町1-12-3 | D42: 神奈川 | E42: 港北区 | F42: 45519 | G42: 8 | I42: 事後 | J42: 40048299 | K42: みつば | L42: 7 | M42: 8 | N42: 6 | P42: 45834 | Q42: 6 | R42: 112050 | S42: 25.7 | T42: 7 | U42: 23 | V42: 213694
A43: 42 | B43: 513-419071X | C43: 多摩区菅5-12-23 | D43: 神奈川 | E43: 多摩区
A44: 43 | B44: 511-242179X | C44: 戸塚区上倉田町350-1 | D44: 神奈川 | E44: 戸塚区 | F44: 45517 | G44: 8 | I44: 事後 | J44: 40048784 | K44: みつば | L44: 7 | M44: 8 | N44: 6 | P44: 45834 | Q44: 6 | R44: 154720 | S44: 25.7 | T44: 7 | U44: 21 | V44: 383941
A45: 44 | B45: 513-342141F | C45: 中原区中丸子258-13 | D45: 神奈川 | E45: 中原区 | F45: 45517 | G45: 8 | I45: 事後 | J45: 40049025 | K45: みつば | M45: 8
A46: 45 | B46: 513-242210W | C46: 麻生区王禅寺西2-1-3 | D46: 神奈川 | E46: 麻生区 | F46: 45544 | G46: 9 | I46: 事後 | J46: 40051755 | K46: みつば | L46: 5 | M46: 9 | N46: 5 | P46: 45797 | Q46: 5 | R46: 319000 | S46: 25.6 | T46: 6 | U46: 21 | V46: 502834
A47: 46 | B47: 513-114136X | C47: 多摩区生田1-1-1 | D47: 神奈川 | E47: 多摩区 | F47: 45544 | G47: 9 | I47: 事後 | J47: 40051776 | K47: みつば | L47: 5 | M47: 9 | N47: 5 | P47: 45797 | Q47: 5 | R47: 262000 | S47: 25.6 | T47: 6 | U47: 21 | V47: 414647
A48: 47 | B48: 513-319038X | C48: 宮前区平3-17 | D48: 神奈川 | E48: 宮前区 | F48: 45544 | G48: 9 | I48: 事後 | J48: 40051785 | K48: みつば | L48: 5 | M48: 9 | N48: 5 | P48: 45797 | Q48: 5 | R48: 164000 | S48: 25.6 | T48: 6 | U48: 21 | V48: 260360
A49: 48 | B49: 512-342200T | C49: 神奈川区三ツ沢南町1 | D49: 神奈川 | E49: 神奈川 | F49: 45544 | G49: 9 | I49: 事後 | J49: 40051649 | K49: 共立 | M49: 9
A50: 49 | B50: 513-119095X | C50: 川崎区浜町4-15-5 | D50: 神奈川 | E50: 川崎区 | F50: 45544 | G50: 9 | I50: 事後 | J50: 40051759 | K50: 共立 | L50: 6 | M50: 9 | N50: 6 | P50: 45833 | Q50: 6 | R50: 167070 | S50: 25.6 | T50: 6 | U50: 21 | V50: 299583
A51: 50 | B51: 513-342153P | C51: 川崎区大島5-21-10 | D51: 神奈川 | E51: 川崎区 | F51: 45575 | G51: 10 | I51: 事後 | J51: 40055110 | K51: みつば | L51: 5 | M51: 10 | N51: 5 | P51: 45797 | Q51: 5 | R51: 139000 | S51: 25.6 | T51: 6 | U51: 21 | V51: 221429
A52: 51 | B52: 512-414357X | C52: 神奈川区入江1-11-31 | D52: 神奈川 | E52: 神奈川
A53: 52 | B53: 513-014072X | C53: 多摩区登戸2851-15 | D53: 神奈川 | E53: 多摩区 | F53: 45609 | G53: 11 | I53: 事後 | J53: 40058910 | K53: 共立 | M53: 11
A54: 53 | B54: 513-411005X | C54: 川崎区殿町3-18-5 | D54: 神奈川 | E54: 川崎区 | F54: 45609 | G54: 11 | I54: 事後 | J54: 40058915 | K54: 共立 | L54: 2 | M54: 11 | N54: 2 | P54: 46081 | Q54: 2 | R54: 48740 | S54: 26.2 | T54: 2 | U54: 21 | V54: 94394
A55: 54 | B55: 513-414029X | C55: 多摩区中野島4-8 | D55: 神奈川 | E55: 多摩区 | F55: 45609 | G55: 11 | I55: 事後 | J55: 40058913 | K55: 共立 | L55: 2 | M55: 11 | N55: 2 | P55: 46081 | Q55: 2 | R55: 36980
A56: 55 | B56: 513-414007X | C56: 麻生区百合丘2-12 | D56: 神奈川 | E56: 麻生区 | F56: 45609 | G56: 11 | I56: 事後 | J56: 40058909 | K56: 共立 | L56: 2 | M56: 11 | N56: 2 | P56: 46081 | Q56: 2 | R56: 40380 | S56: 26.2 | T56: 2 | U56: 21 | V56: 78205
A57: 56 | B57: 512-314349X | C57: 鶴見区獅子ヶ谷3-19 | D57: 神奈川 | E57: 鶴見区 | F57: 45609 | G57: 11 | I57: 事後 | J57: 40058819 | K57: 共立 | M57: 11
A58: 57 | B58: 513-214105X | C58: 宮前区野川本町1-34 | D58: 神奈川 | E58: 宮前区 | F58: 45609 | G58: 11 | I58: 事後 | J58: 40058903 | K58: 共立 | L58: 2 | M58: 11 | N58: 2 | P58: 46081 | Q58: 2 | R58: 185100 | S58: 26.2 | T58: 2 | U58: 21 | V58: 358555
A59: 58 | B59: 513-312220X | C59: 川崎区浅田2-12-22 | D59: 神奈川 | E59: 川崎区 | F59: 45609 | G59: 11 | I59: 事後 | J59: 40058917 | K59: 共立 | L59: 2 | M59: 11 | N59: 2 | P59: 46081 | Q59: 2 | R59: 28620 | S59: 26.2 | T59: 2 | U59: 21 | V59: 55411
A60: 59 | B60: 513-319096X | C60: 宮前区神木本町4-20 | D60: 神奈川 | E60: 宮前区 | F60: 45609 | G60: 11 | I60: 事後 | J60: 40058918 | K60: 共立 | M60: 11
A61: 60 | B61: 513-219128X | C61: 多摩区宿河原2-48 | D61: 神奈川 | E61: 多摩区 | F61: 45609 | G61: 11 | I61: 事後 | J61: 40058922 | K61: 共立 | M61: 11
A62: 61 | B62: 512-043220S | C62: 鶴見区寺谷1-17-25 | D62: 神奈川 | E62: 鶴見区 | F62: 45609 | G62: 11 | I62: 事後 | J62: 40058923 | K62: 共立 | M62: 11 | N62: 3
A63: 62 | B63: 622-110731 | C63: 宮前区犬蔵3-14 | D63: 神奈川 | E63: 宮前区 | F63: 45618 | G63: 11 | I63: 事後 | J63: 40060277 | K63: 共立 | L63: 2 | M63: 11 | N63: 2 | P63: 46081 | Q63: 2 | R63: 34660 | S63: 26.2 | T63: 2 | U63: 101 | V63: 90760
A64: 63 | B64: 512-314328X | C64: 神奈川区片倉5-36-6 | D64: 神奈川 | E64: 神奈川 | F64: 45638 | G64: 12 | I64: 事後 | J64: 40062104 | K64: 共立 | M64: 12
A65: 64 | B65: 512-311021X | C65: 神奈川区松本町2-13-8 | D65: 神奈川 | E65: 神奈川 | F65: 45679 | G65: 1 | I65: 事後 | J65: 40066781 | K65: みつば | L65: 5 | M65: 2 | N65: 5 | P65: 45797 | Q65: 5 | R65: 74180 | S65: 25.6 | T65: 6 | U65: 21 | V65: 143669
A66: 65 | B66: 512-342170F | C66: 神奈川区青葉町6-26 | D66: 神奈川 | E66: 神奈川 | F66: 45679 | G66: 1 | I66: 事後 | J66: 40066831 | K66: みつば | L66: 5 | M66: 2 | N66: 5 | P66: 45797 | Q66: 5 | R66: 83500 | S66: 25.6 | T66: 6 | U66: 21 | V66: 161703
A67: 66 | B67: 513-342155P | C67: 川崎区南町18-18 | D67: 神奈川 | E67: 川崎区 | F67: 45707 | G67: 2 | I67: 事後 | J67: 40070246 | K67: みつば | L67: 5 | M67: 2 | N67: 5 | P67: 45797 | Q67: 5 | R67: 112820 | S67: 25.6 | T67: 6 | U67: 21 | V67: 218565
A68: 67 | B68: 512-342236J | C68: 青葉区荏田町448-26 | D68: 神奈川 | E68: 青葉区 | F68: 45707 | G68: 2 | I68: 事後 | J68: 40070241 | K68: みつば | L68: 6 | M68: 2 | N68: 6 | P68: 45834 | Q68: 6 | R68: 344000 | S68: 25.6 | T68: 6 | U68: 21 | V68: 543250
A69: 68 | B69: 512-442208T | C69: 青葉区桜台1-123 | D69: 神奈川 | E69: 青葉区 | F69: 45707 | G69: 2 | I69: 事後 | J69: 40070188 | K69: みつば | L69: 5 | M69: 2 | N69: 5 | P69: 45797 | Q69: 5 | R69: 116660 | S69: 25.6 | T69: 6 | U69: 21 | V69: 225938
A70: 69 | B70: 512-342172P | C70: 鶴見区岸谷2-14-4 | D70: 神奈川 | E70: 鶴見区 | F70: 45707 | G70: 2 | I70: 事後 | J70: 40070433 | K70: みつば | L70: 5 | M70: 2 | N70: 5 | P70: 45797 | Q70: 5 | R70: 134530 | S70: 25.6 | T70: 6 | U70: 21 | V70: 250216
A71: 70 | B71: 512-342136J | C71: 鶴見区鶴見1-1-2 | D71: 神奈川 | E71: 鶴見区 | F71: 45707 | G71: 2 | I71: 事後 | J71: 40070424 | K71: みつば | L71: 5 | M71: 2 | N71: 5 | P71: 45797 | Q71: 5 | R71: 114720 | S71: 25.6 | T71: 6 | U71: 21 | V71: 222206
A72: 71 | B72: 512-342110T | C72: 神奈川区神奈川2-12-3 | D72: 神奈川 | E72: 神奈川 | F72: 45707 | G72: 2 | I72: 事後 | J72: 40070403 | K72: みつば | L72: 6 | M72: 2 | N72: 6 | P72: 45834 | Q72: 6 | R72: 279000 | S72: 25.6 | T72: 6 | U72: 21 | V72: 440201
A73: 72 | B73: 513-242108J | C73: 川崎区藤崎1-11-9 | D73: 神奈川 | E73: 川崎区 | F73: 45707 | G73: 2 | I73: 事後 | J73: 40070391 | K73: みつば | L73: 5 | M73: 2 | N73: 5 | P73: 45797 | Q73: 5 | R73: 118820 | S73: 25.6 | T73: 6 | U73: 21 | V73: 230177
A74: 73 | B74: 511-132401X | C74: 戸塚区秋葉町353-4 | D74: 神奈川 | E74: 戸塚区 | F74: 45707 | G74: 2 | I74: 事後 | J74: 40070390 | K74: みつば | L74: 5 | M74: 2 | N74: 5 | P74: 45797 | Q74: 5 | R74: 85660 | S74: 25.6 | T74: 6 | U74: 21 | V74: 216070
A75: 74 | B75: 513-342117W | C75: 川崎区観音2-20-16 | D75: 神奈川 | E75: 川崎区 | F75: 45707 | G75: 2 | I75: 事後 | J75: 40070258 | K75: 共立 | L75: 6 | M75: 2 | N75: 5 | P75: 45833 | Q75: 6 | R75: 183210 | S75: 25.6 | T75: 6 | U75: 21 | V75: 290378
A76: 75 | B76: 512-342223W | C76: 神奈川区六角橋4-14-6 | D76: 神奈川 | E76: 神奈川 | F76: 45707 | G76: 2 | I76: 事後 | J76: 40070238 | K76: 共立 | L76: 6 | M76: 2 | N76: 5 | P76: 45833 | Q76: 6 | R76: 43720 | S76: 25.6 | T76: 6 | U76: 21 | V76: 84672
... A81: 80 | B81: 512-414344X | C81: 鶴見区上の宮2-10 | D81: 神奈川 | E81: 鶴見区 | F81: 45707 | G81: 2 | I81: 事後 | J81: 40070392 | K81: 共立 | L81: 5 | M81: 2 | N81: 5 | P81: 45797 | Q81: 5 | R81: 54060 | S81: 25.6 | T81: 6 | U81: 21 | V81: 104685
A82: 81 | B82: 513-514106X | C82: 宮前区平5-4 | D82: 神奈川 | E82: 宮前区
A83: 82 | B83: 512-419087X | C83: 鶴見区東寺尾1-29-27 | D83: 神奈川 | E83: 鶴見区 | F83: 45729 | G83: 3 | I83: 事後 | J83: 40073291 | K83: 共立 | L83: 5 | M83: 3 | N83: 5 | P83: 45797 | Q83: 5 | R83: 76790 | S83: 25.6 | T83: 6 | U83: 21 | V83: 148011
A84: 83 | B84: 513-410001X | C84: 幸区新小倉545-50 | D84: 神奈川 | E84: 幸区新 | F84: 45729 | G84: 3 | I84: 事後 | J84: 40073286 | K84: 共立 | L84: 7 | M84: 3 | N84: 7 | P84: 45867 | Q84: 7 | R84: 77100 | S84: 25.7 | T84: 7 | U84: 21 | V84: 124314
A85: 84 | B85: 512-419118X | C85: 港北区新吉田東1-60-7 | D85: 神奈川 | E85: 港北区 | F85: 45729 | G85: 3 | I85: 事後 | J85: 40073277 | K85: 共立 | L85: 7 | M85: 3 | N85: 6 | P85: 45833 | Q85: 6 | R85: 40020 | S85: 25.7 | T85: 7 | U85: 21 | V85: 77498
A86: 85 | B86: 513-414221X | C86: 高津区明津102 | D86: 神奈川 | E86: 高津区 | F86: 45729 | G86: 3 | I86: 事後 | J86: 40073243 | K86: 共立 | L86: 7 | M86: 3 | N86: 6 | P86: 45867 | Q86: 7 | R86: 79915 | S86: 25.7 | T86: 7 | U86: 21 | V86: 128747
A87: 86 | B87: 513-419074X | C87: 高津区下野毛3-15 | D87: 神奈川 | E87: 高津区 | F87: 45729 | G87: 3 | I87: 事後 | J87: 40073238 | K87: 共立 | L87: 6 | M87: 3 | N87: 6 | P87: 45833 | Q87: 6 | R87: 41660 | S87: 25.6 | T87: 6 | U87: 21 | V87: 80663
A88: 87 | B88: 512-403012X | C88: 神奈川区菅田町467-6 | D88: 神奈川 | E88: 神奈川 | F88: 45729 | G88: 3 | I88: 事後 | J88: 40073127 | K88: 共立 | L88: 5 | M88: 3 | N88: 5 | P88: 45797 | Q88: 5 | R88: 28660 | S88: 25.6 | T88: 6 | U88: 21 | V88: 55503
A89: 88 | B89: 512-414288X | C89: 都筑区牛久保町1918 | D89: 神奈川 | E89: 都筑区 | F89: 45729 | G89: 3 | I89: 事後 | J89: 40073035 | K89: 共立 | L89: 7 | M89: 3 | N89: 6 | P89: 45833 | Q89: 6 | R89: 37340 | S89: 25.7 | T89: 7 | U89: 21 | V89: 72307
A90: 89 | B90: 513-314140X | C90: 高津区明津106 | D90: 神奈川 | E90: 高津区 | F90: 45729 | G90: 3 | I90: 事後 | J90: 40073294 | K90: 共立 | L90: 6 | M90: 3 | N90: 6 | P90: 45833 | Q90: 6 | R90: 43720 | S90: 25.6 | T90: 6 | U90: 21 | V90: 84671
A91: 90 | B91: 513-212059X | C91: 高津区下作延7-7-34 | D91: 神奈川 | E91: 高津区 | F91: 45729 | G91: 3 | I91: 事後 | J91: 40073280 | K91: 共立 | L91: 5 | M91: 3 | N91: 5 | P91: 45797 | Q91: 5 | R91: 44700 | S91: 25.6 | T91: 6 | U91: 21 | V91: 86561
A92: 91 | B92: 512-312026X | C92: 港北区日吉3-11-13 | D92: 神奈川 | E92: 港北区 | F92: 45729 | G92: 3 | I92: 事後 | J92: 40073276 | K92: 共立 | L92: 7 | M92: 3 | N92: 6 | P92: 45833 | Q92: 6 | R92: 34300 | S92: 25.7 | T92: 7 | U92: 21 | V92: 66409
A93: 92 | B93: 512-919091X | C93: 鶴見区下末吉6-6-33 | D93: 神奈川 | E93: 鶴見区 | F93: 45729 | G93: 3 | I93: 事後 | J93: 40073274 | K93: 共立 | L93: 5 | M93: 3 | N93: 5 | P93: 45797 | Q93: 5 | R93: 30980 | S93: 25.6 | T93: 6 | U93: 21 | V93: 59988
A94: 93 | B94: 512-042140X | C94: 神奈川区鶴屋町2-25-1 | D94: 神奈川 | E94: 神奈川 | F94: 45729 | G94: 3 | I94: 事後 | J94: 40073269 | K94: 共立 | L94: 5 | M94: 3 | N94: 5 | P94: 45797 | Q94: 5 | R94: 130440 | S94: 25.6 | T94: 6 | U94: 21 | V94: 252649
... A104: 103 | B104: 513-319143X | C104: 高津区子母口751 | D104: 神奈川 | E104: 高津区 | F104: 45729 | G104: 3 | I104: 事後 | J104: 40073215 | K104: みつば | L104: 5 | M104: 3 | N104: 5 | P104: 45797 | Q104: 5 | R104: 56440 | S104: 25.6 | T104: 6 | U104: 21 | V104: 109310
A105: 104 | B105: 513-505005X | C105: 川崎区夜光1-2-1 | D105: 神奈川 | E105: 川崎区
A106: 105 | B106: 513-511012X | C106: 幸区下平間115-19 | D106: 神奈川 | E106: 幸区下
A107: 106 | B107: 513-511003X | C107: 高津区久末1861 | D107: 神奈川 | E107: 高津区
A108: 107 | B108: 512-514232X | C108: 神奈川区神大寺2-11 | D108: 神奈川 | E108: 神奈川
A109: 108 | B109: 513-511015X | C109: 多摩区東三田1-2-4 | D109: 神奈川 | E109: 多摩区 | F109: 45971 | G109: 11 | I109: 事後 | J109: 50042520 | K109: みつば
A110: 109 | B110: 512-519049X | C110: 青葉区すみよし台19-22 | D110: 神奈川 | E110: 青葉区 | F110: 45944 | G110: 10 | I110: 事後 | J110: 50037005 | K110: みつば | L110: 12 | N110: 12 | P110: 46022 | Q110: 12 | R110: 36230 | S110: 25.12 | T110: 12 | U110: 21 | V110: 93280
A111: 110 | B111: 512-511021X | C111: 青葉区市ヶ尾町1178-12 | D111: 神奈川 | E111: 青葉区
A112: 111 | B112: 513-553135F | C112: 宮前区宮崎6-9-1 | D112: 神奈川 | E112: 宮前区
A113: 112 | B113: 513-553136F | C113: 宮前区土橋7-1-5 | D113: 神奈川 | E113: 宮前区
...

Sheet 速報sheet
B1: =#REF! -> #REF! | C1: 月売上速報（導管本部） | W1: 西部 | Y1: 西部NC設計 | AA1: （道路復旧・その他作業含む） | AD1: 杭測
B2: 西部（事） | C2: 売上速報 | D2: =+J2+Q2 -> 0 | H2: 杭以外売上 | J2: =+AA5 -> 0 | O2: 杭測売上 | Q2: =+AE6 -> 0 | W2: 先月目標累計 | X2: =IF($B$1=6,"0",SUM(目標比較!$D$7:INDEX(目標比較!$D$7:$O$7,MATCH(速報sheet!$B$1,目標比較!$D$5:$O$5, 0)-1))) -> #REF! | Z2: NC受注 | AA2: =COUNTIFS(台帳表ｋ[ＮＣ区分],"西部",#REF!,$B$1) -> #REF! | AB2: 件 | AD2: TG受注 | AE2: =COUNTIFS(測量台帳1ｋ[NC区分],"西部",測量台帳1ｋ[受注月],$B$1)+COUNTIFS(測量台帳1__2ｋ[NC区分],"西部",測量台帳1__2ｋ[受注月(後)],$B$1) -> 0 | AF2: 件 | AG2: 未発注 | AH2: =COUNTIFS(測量台帳1ｋ[NC区分],"西部",測量台帳1ｋ[外注 発注月],"<>")+COUNTIFS(測量台帳1__2ｋ[NC区分],"西部",測量台帳1__2ｋ[外注 発注月(後)],"<>") -> 0
C3: 売上目標 | D3: =X3 -> #REF! | E3: 差額 | F3: =D2-D3 -> #REF! | H3: 杭以外予想 | J3: =+X7 -> #REF! | L3: 差額 | M3: =J2-J3 -> #REF! | O3: 杭測予想 | Q3: =+X8 -> #REF! | S3: 差額 | T3: =Q2-Q3 -> #REF! | W3: 今月目標 | X3: =INDEX(目標比較!$D$7:$O$7, MATCH(速報sheet!$B$1,目標比較!$D$5:$O$5, 0)) -> #REF! | Z3: NC納品 | AA3: =COUNTIFS(台帳表ｋ[ＮＣ区分],"西部",台帳表ｋ[納品月],$B$1) -> 0 | AB3: 件 | AD3: 外注発注 | AE3: =COUNTIFS(測量台帳1ｋ[NC区分],"西部",測量台帳1ｋ[外注 発注月],$B$1)+COUNTIFS(測量台帳1__2ｋ[NC区分],"西部",測量台帳1__2ｋ[外注 発注月(後)],$B$1) -> 0 | AF3: 件
C4: 売上累計 | D4: =+D2+X5 -> #REF! | E4: 差額 | F4: =D4-X4 -> #REF! | H4: 全体予想 | J4: =+X6 -> #REF! | L4: 差額 | M4: =D2-J4 -> #REF! | O4: 来月売上目標 | Q4: =X9 -> #REF! | W4: 今月目標累計 | X4: =IF($B$1=6,"0",SUM(目標比較!$D$7:INDEX(目標比較!$D$7:$O$7,MATCH(速報sheet!B1,目標比較!$D$5:$O$5, 0)))) -> #REF! | Z4: NC清算 | AA4: =COUNTIFS(台帳表ｋ[ＮＣ区分],"西部",台帳表ｋ[入金月（月のみ）],$B$1) -> 0 | AB4: 件 | AD4: 外注納品 | AE4: =COUNTIFS(測量台帳1ｋ[NC区分],"西部",測量台帳1ｋ[外注納品月],$B$1)+COUNTIFS(測量台帳1__2ｋ[NC区分],"西部",測量台帳1__2ｋ[外注納品月(後)],$B$1) -> 0 | AF4: 件
C5: 西部NC要因 | P5: 全エリア精算内訳 | W5: 先月売上累計 | X5: =IF($B$1=6,"0",SUM(速報sheet!$X$16:INDEX($X$16:$AI$16,MATCH(速報sheet!$B$1,$X$11:$AI$11, 0)-1))) -> #REF! | Z5: NC清算 | AA5: =SUMIFS(台帳表ｋ[金額],台帳表ｋ[入金月（月のみ）],$B$1,台帳表ｋ[ＮＣ区分],"西部") -> 0 | AB5: 千円 | AD5: TG納品 | AE5: =COUNTIFS(測量台帳1ｋ[NC区分],"西部",測量台帳1ｋ[納品月],$B$1)+COUNTIFS(測量台帳1__2ｋ[NC区分],"西部",測量台帳1__2ｋ[納品 月(後)],$B$1) -> 0 | AF5: 件
C6: 設計 | P6: 修正変更 | S6: 件 | U6: 千円 | W6: 今月予想売上 | X6: =INDEX(目標比較!$D$11:$O$11, MATCH(速報sheet!$B$1,目標比較!$D$5:$O$5, 0)) -> #REF! | Z6: 手持ち | AA6: =COUNTIFS(台帳表ｋ[ＮＣ区分],"西部",台帳表ｋ[顧客引渡 実施日],"") -> 0 | AB6: 件 | AD6: TG清算 | AE6: =SUMIFS(測量台帳1ｋ[入金額],測量台帳1ｋ[入金月（月のみ）],$B$1,測量台帳1ｋ[NC区分],"西部")+SUMIFS(測量台帳1__2ｋ[入金額(後)],測量台帳1__2ｋ[入金月(後)（月のみ）],$B$1,測量台帳1__2ｋ[NC区分],"西部") -> 0 | AF6: 千円
K7: 精算本体 | P7: 本体 | S7: 件 | U7: 千円 | W7: 今月杭以外予想 | X7: =INDEX(目標比較!$D$13:$O$13, MATCH(速報sheet!$B$1,目標比較!$D$5:$O$5, 0)) -> #REF! | Z7: 保留 | AA7: =COUNTIFS(台帳表ｋ[ＮＣ区分],"西部",台帳表ｋ[顧客引渡 実施日],"保留") -> 0 | AB7: 件
L8: 件 | N8: ｍ | P8: 申請・竣工 | S8: 件 | U8: 千円 | W8: 今月杭予想売上 | X8: =INDEX(目標比較!$D$10:$O$10, MATCH(速報sheet!$B$1,目標比較!$D$5:$O$5, 0)) -> #REF! | Z8: 計
P9: その他 | S9: 件 | U9: 千円 | W9: 来月売上目標 | X9: =INDEX(目標比較!$D$7:$O$7, MATCH(速報sheet!$B$1+1,目標比較!$D$5:$O$5, 0)) -> #REF!
C10: 杭 | P10: 測量調整 | S10: 件 | U10: 千円
R11: =SUM(R6:R10) -> 0 | S11: 件 | T11: =SUM(T6:T10) -> 0 | U11: 千円 | X11: 6 | Y11: 7 | Z11: 8 | AA11: 9 | AB11: 10 | AC11: 11 | AD11: 12 | AE11: 1 | AF11: 2 | AG11: 3 | AH11: 4 | AI11: 5 | AJ11: 累計
C12: 西部NC傾向 | R12: 精算全本体 | W12: 売上目標 | X12: =目標比較!D7 -> 30600000 | Y12: =目標比較!E7 -> 31800000 | Z12: =目標比較!F7 -> 31900000 | AA12: =目標比較!G7 -> 29500000 | AB12: =目標比較!H7 -> 29700000 | AC12: =目標比較!I7 -> 31700000 | AD12: =目標比較!J7 -> 30900000 | AE12: =目標比較!K7 -> 35200000 | ... AJ12: =目標比較!P7 -> 380000000
S13: 件 | U13: ｍ | W13: 売上予想 | X13: =目標比較!D11 -> 16449886 | Y13: =目標比較!E11 -> 17851387 | Z13: =目標比較!F11 -> 15063890 | AA13: =目標比較!G11 -> 11863133 | AB13: =目標比較!H11 -> 17715509 | AC13: =目標比較!I11 -> 17713237 | AD13: =目標比較!J11 -> 12172500 | AE13: =目標比較!K11 -> 14069228 | ... AJ13: =目標比較!P11 -> 1.4102331e+08
W14: 杭予想 | X14: =目標比較!D10 -> 21673162 | Y14: =目標比較!E10 -> 23386332 | Z14: =目標比較!F10 -> 18801467 | AA14: =目標比較!G10 -> 19935806 | AB14: =目標比較!H10 -> 25832634 | AC14: =目標比較!I10 -> 30180043 | AD14: =目標比較!J10 -> 16559904 | AE14: =目標比較!K10 -> 21308517 | ... AJ14: =目標比較!P10 -> 2.0301613e+08
W15: 杭以外予想 | X15: =目標比較!D13 -> 0.70827326 | Y15: =目標比較!E13 -> 0.73541925 | Z15: =目標比較!F13 -> 0.58938768 | AA15: =目標比較!G13 -> 0.67579003 | AB15: =目標比較!H13 -> 0.86978566 | AC15: =目標比較!I13 -> 0.95205182 | AD15: =目標比較!J13 -> 0.53591922 | AE15: =目標比較!K13 -> 0.6053556 | ... AJ15: =目標比較!P13 -> 0.53425297
W16: 実売上 | X16: =SUMIFS(台帳表ｋ[金額],台帳表ｋ[入金月（月のみ）],X$11,台帳表ｋ[ＮＣ区分],"西部")+SUMIFS(測量台帳1ｋ[入金額],測量台帳1ｋ[入金月（月のみ）],X$11,測量台帳1ｋ[NC区分],"西部")+SUMIFS(測量台帳1__2ｋ[入金額(後)],測量台帳1__2ｋ[入金月(後)（月のみ）],X$11,測量台帳1__2ｋ[NC区分],"西部") -> 0 | Y16: =SUMIFS(台帳表ｋ[金額],台帳表ｋ[入金月（月のみ）],Y$11,台帳表ｋ[ＮＣ区分],"西部")+SUMIFS(測量台帳1ｋ[入金額],測量台帳1ｋ[入金月（月のみ）],Y$11,測量台帳1ｋ[NC区分],"西部")+SUMIFS(測量台帳1__2ｋ[入金額(後)],測量台帳1__2ｋ[入金月(後)（月のみ）],Y$11,測量台帳1__2ｋ[NC区分],"西部") -> 0 | Z16: =SUMIFS(台帳表ｋ[金額],台帳表ｋ[入金月（月のみ）],Z$11,台帳表ｋ[ＮＣ区分],"西部")+SUMIFS(測量台帳1ｋ[入金額],測量台帳1ｋ[入金月（月のみ）],Z$11,測量台帳1ｋ[NC区分],"西部")+SUMIFS(測量台帳1__2ｋ[入金額(後)],測量台帳1__2ｋ[入金月(後)（月のみ）],Z$11,測量台帳1__2ｋ[NC区分],"西部") -> 0 | AA16: =SUMIFS(台帳表ｋ[金額],台帳表ｋ[入金月（月のみ）],AA$11,台帳表ｋ[ＮＣ区分],"西部")+SUMIFS(測量台帳1ｋ[入金額],測量台帳1ｋ[入金月（月のみ）],AA$11,測量台帳1ｋ[NC区分],"西部")+SUMIFS(測量台帳1__2ｋ[入金額(後)],測量台帳1__2ｋ[入金月(後)（月のみ）],AA$11,測量台帳1__2ｋ[NC区分],"西部") -> 0 | AB16: =SUMIFS(台帳表ｋ[金額],台帳表ｋ[入金月（月のみ）],AB$11,台帳表ｋ[ＮＣ区分],"西部")+SUMIFS(測量台帳1ｋ[入金額],測量台帳1ｋ[入金月（月のみ）],AB$11,測量台帳1ｋ[NC区分],"西部")+SUMIFS(測量台帳1__2ｋ[入金額(後)],測量台帳1__2ｋ[入金月(後)（月のみ）],AB$11,測量台帳1__2ｋ[NC区分],"西部") -> 0 | AC16: =SUMIFS(台帳表ｋ[金額],台帳表ｋ[入金月（月のみ）],AC$11,台帳表ｋ[ＮＣ区分],"西部")+SUMIFS(測量台帳1ｋ[入金額],測量台帳1ｋ[入金月（月のみ）],AC$11,測量台帳1ｋ[NC区分],"西部")+SUMIFS(測量台帳1__2ｋ[入金額(後)],測量台帳1__2ｋ[入金月(後)（月のみ）],AC$11,測量台帳1__2ｋ[NC区分],"西部") -> 0 | AD16: =SUMIFS(台帳表ｋ[金額],台帳表ｋ[入金月（月のみ）],AD$11,台帳表ｋ[ＮＣ区分],"西部")+SUMIFS(測量台帳1ｋ[入金額],測量台帳1ｋ[入金月（月のみ）],AD$11,測量台帳1ｋ[NC区分],"西部")+SUMIFS(測量台帳1__2ｋ[入金額(後)],測量台帳1__2ｋ[入金月(後)（月のみ）],AD$11,測量台帳1__2ｋ[NC区分],"西部") -> 0 | AE16: =SUMIFS(台帳表ｋ[金額],台帳表ｋ[入金月（月のみ）],AE$11,台帳表ｋ[ＮＣ区分],"西部")+SUMIFS(測量台帳1ｋ[入金額],測量台帳1ｋ[入金月（月のみ）],AE$11,測量台帳1ｋ[NC区分],"西部")+SUMIFS(測量台帳1__2ｋ[入金額(後)],測量台帳1__2ｋ[入金月(後)（月のみ）],AE$11,測量台帳1__2ｋ[NC区分],"西部") -> 0 | ... AI16: =SUMIFS(台帳表ｋ[金額],台帳表ｋ[入金月（月のみ）],AI$11,台帳表ｋ[ＮＣ区分],"西部")+SUMIFS(測量台帳1ｋ[入金額],測量台帳1ｋ[入金月（月のみ）],AI$11,測量台帳1ｋ[NC区分],"西部")+SUMIFS(測量台帳1__2ｋ[入金額(後)],測量台帳1__2ｋ[入金月(後)（月のみ）],AI$11,測量台帳1__2ｋ[NC区分],"西部") -> 0 | AJ16: =SUM(X16:AI16) -> 0
C18: 西部NC今月の戦略 | W18: 西部NC売上 | X18: =+AB18+AB19 -> 0 | Y18: 千円 | Z18: ☚ | AA18: 設計 | AB18: =AA5 -> 0 | AC18: 千円
C19: 設計 | AA19: 杭測 | AB19: =AE6 -> 0 | AC19: 千円
Y22: （道路復旧・その他作業含む）
C23: 北部NC要因 | X23: 埼玉NC設計 | AA23: 北部NC設計 | AD23: 埼玉NC設計 | AF23: 杭測 | AG23: 北部NC設計
C24: 設計 | X24: =COUNTIFS(台帳表ｋ[ＮＣ区分],"埼玉",#REF!,$B$1) -> #REF! | Y24: 件 | Z24: NC受注 | AA24: =COUNTIFS(台帳表ｋ[ＮＣ区分],"北部",#REF!,$B$1) -> #REF! | AB24: 件 | AD24: =COUNTIFS(測量台帳1ｋ[NC区分],"埼玉",測量台帳1ｋ[受注月],$B$1)+COUNTIFS(測量台帳1__2ｋ[NC区分],"埼玉",測量台帳1__2ｋ[受注月(後)],$B$1) -> 0 | AE24: 件 | AF24: TG受注 | AG24: =COUNTIFS(測量台帳1ｋ[NC区分],"北部",測量台帳1ｋ[受注月],$B$1)+COUNTIFS(測量台帳1__2ｋ[NC区分],"北部",測量台帳1__2ｋ[受注月(後)],$B$1) -> 0 | AH24: 件
X25: =COUNTIFS(台帳表ｋ[ＮＣ区分],"埼玉",台帳表ｋ[納品月],$B$1) -> 0 | Y25: 件 | Z25: NC納品 | AA25: =COUNTIFS(台帳表ｋ[ＮＣ区分],"北部",台帳表ｋ[納品月],$B$1) -> 0 | AB25: 件 | AD25: =COUNTIFS(測量台帳1ｋ[NC区分],"埼玉",測量台帳1ｋ[外注 発注月],$B$1)+COUNTIFS(測量台帳1__2ｋ[NC区分],"埼玉",測量台帳1__2ｋ[外注 発注月(後)],$B$1) -> 0 | AE25: 件 | AF25: 外注発注 | AG25: =COUNTIFS(測量台帳1ｋ[NC区分],"北部",測量台帳1ｋ[外注 発注月],$B$1)+COUNTIFS(測量台帳1__2ｋ[NC区分],"北部",測量台帳1__2ｋ[外注 発注月(後)],$B$1) -> 0 | AH25: 件
X26: =COUNTIFS(台帳表ｋ[ＮＣ区分],"埼玉",台帳表ｋ[入金月（月のみ）],$B$1) -> 0 | Y26: 件 | Z26: NC清算 | AA26: =COUNTIFS(台帳表ｋ[ＮＣ区分],"北部",台帳表ｋ[入金月（月のみ）],$B$1) -> 0 | AB26: 件 | AD26: =COUNTIFS(測量台帳1ｋ[NC区分],"埼玉",測量台帳1ｋ[外注納品月],$B$1)+COUNTIFS(測量台帳1__2ｋ[NC区分],"埼玉",測量台帳1__2ｋ[外注納品月(後)],$B$1) -> 0 | AE26: 件 | AF26: 外注納品 | AG26: =COUNTIFS(測量台帳1ｋ[NC区分],"北部",測量台帳1ｋ[外注納品月],$B$1)+COUNTIFS(測量台帳1__2ｋ[NC区分],"北部",測量台帳1__2ｋ[外注納品月(後)],$B$1) -> 0 | AH26: 件
C27: 杭 | R27: 精算本体 | X27: =SUMIFS(台帳表ｋ[金額],台帳表ｋ[入金月（月のみ）],$B$1,台帳表ｋ[ＮＣ区分],"埼玉") -> 0 | Y27: 千円 | Z27: NC清算 | AA27: =SUMIFS(台帳表ｋ[金額],台帳表ｋ[入金月（月のみ）],$B$1,台帳表ｋ[ＮＣ区分],"北部") -> 0 | AB27: 千円 | AD27: =COUNTIFS(測量台帳1ｋ[NC区分],"埼玉",測量台帳1ｋ[納品月],$B$1)+COUNTIFS(測量台帳1__2ｋ[NC区分],"埼玉",測量台帳1__2ｋ[納品 月(後)],$B$1) -> 0 | AE27: 件 | AF27: TG納品 | AG27: =COUNTIFS(測量台帳1ｋ[NC区分],"北部",測量台帳1ｋ[納品月],$B$1)+COUNTIFS(測量台帳1__2ｋ[NC区分],"北部",測量台帳1__2ｋ[納品 月(後)],$B$1) -> 0 | AH27: 件
S28: 件 | U28: ｍ | X28: =COUNTIFS(台帳表ｋ[ＮＣ区分],"埼玉",台帳表ｋ[顧客引渡 実施日],"") -> 0 | Y28: 件 | Z28: 手持ち | AA28: =COUNTIFS(台帳表ｋ[ＮＣ区分],"北部",台帳表ｋ[顧客引渡 実施日],"") -> 0 | AB28: 件 | AD28: =SUMIFS(測量台帳1ｋ[入金額],測量台帳1ｋ[入金月（月のみ）],$B$1,測量台帳1ｋ[NC区分],"埼玉")+SUMIFS(測量台帳1__2ｋ[入金額(後)],測量台帳1__2ｋ[入金月(後)（月のみ）],$B$1,測量台帳1__2ｋ[NC区分],"埼玉") -> 0 | AE28: 千円 | AF28: TG清算 | AG28: =SUMIFS(測量台帳1ｋ[入金額],測量台帳1ｋ[入金月（月のみ）],$B$1,測量台帳1ｋ[NC区分],"北部")+SUMIFS(測量台帳1__2ｋ[入金額(後)],測量台帳1__2ｋ[入金月(後)（月のみ）],$B$1,測量台帳1__2ｋ[NC区分],"北部") -> 0 | AH28: 千円
X29: =COUNTIFS(台帳表ｋ[ＮＣ区分],"埼玉",台帳表ｋ[顧客引渡 実施日],"保留") -> 0 | Y29: 件 | Z29: 保留 | AA29: =COUNTIFS(台帳表ｋ[ＮＣ区分],"北部",台帳表ｋ[顧客引渡 実施日],"保留") -> 0 | AB29: 件
C30: 北部NC傾向 | AD30: =COUNTIFS(測量台帳1ｋ[NC区分],"埼玉",測量台帳1ｋ[外注 発注月],"<>")+COUNTIFS(測量台帳1__2ｋ[NC区分],"埼玉",測量台帳1__2ｋ[外注 発注月(後)],"<>") -> 0 | AF30: 未発注 | AG30: =COUNTIFS(測量台帳1ｋ[NC区分],"北部",測量台帳1ｋ[外注 発注月],"<>")+COUNTIFS(測量台帳1__2ｋ[NC区分],"北部",測量台帳1__2ｋ[外注 発注月(後)],"<>") -> 0
Y31: 埼玉+ | Z31: 北部 計
C35: 北部NC今月の戦略 | W35: 北部NC売上 | X35: =+AB35+AB36 -> 0 | Y35: 千円 | Z35: ☚ | AA35: 設計 | AB35: =SUM(X27,AA27) -> 0 | AC35: 千円
AA36: 杭測 | AB36: =SUM(AD28,AG28) -> 0 | AC36: 千円
C37: 設計
C39: 杭
C41: 南部NC要因 | Y41: 南部設計 | AA41: （道路復旧・その他作業含む） | AD41: 杭測
C42: 設計 | Z42: NC受注 | AA42: =COUNTIFS(台帳表ｋ[ＮＣ区分],"南部",#REF!,$B$1) -> #REF! | AB42: 件 | AD42: TG受注 | AE42: =COUNTIFS(測量台帳1ｋ[NC区分],"南部",測量台帳1ｋ[受注月],$B$1)+COUNTIFS(測量台帳1__2ｋ[NC区分],"南部",測量台帳1__2ｋ[受注月(後)],$B$1) -> 0 | AF42: 件 | AG42: 未発注 | AH42: =COUNTIFS(測量台帳1ｋ[NC区分],"南部",測量台帳1ｋ[外注 発注月],"<>")+COUNTIFS(測量台帳1__2ｋ[NC区分],"南部",測量台帳1__2ｋ[外注 発注月(後)],"<>") -> 0
Z43: NC納品 | AA43: =COUNTIFS(台帳表ｋ[ＮＣ区分],"南部",台帳表ｋ[納品月],$B$1) -> 0 | AB43: 件 | AD43: 外注発注 | AE43: =COUNTIFS(測量台帳1ｋ[NC区分],"南部",測量台帳1ｋ[外注 発注月],$B$1)+COUNTIFS(測量台帳1__2ｋ[NC区分],"南部",測量台帳1__2ｋ[外注 発注月(後)],$B$1) -> 0 | AF43: 件
R44: 精算本体 | Z44: NC清算 | AA44: =COUNTIFS(台帳表ｋ[ＮＣ区分],"南部",台帳表ｋ[入金月（月のみ）],$B$1) -> 0 | AB44: 件 | AD44: 外注納品 | AE44: =COUNTIFS(測量台帳1ｋ[NC区分],"南部",測量台帳1ｋ[外注納品月],$B$1)+COUNTIFS(測量台帳1__2ｋ[NC区分],"南部",測量台帳1__2ｋ[外注納品月(後)],$B$1) -> 0 | AF44: 件
C45: 杭 | S45: 件 | U45: ｍ | Z45: NC清算 | AA45: =SUMIFS(台帳表ｋ[金額],台帳表ｋ[入金月（月のみ）],$B$1,台帳表ｋ[ＮＣ区分],"南部") -> 0 | AB45: 千円 | AD45: TG納品 | AE45: =COUNTIFS(測量台帳1ｋ[NC区分],"南部",測量台帳1ｋ[納品月],$B$1)+COUNTIFS(測量台帳1__2ｋ[NC区分],"南部",測量台帳1__2ｋ[納品 月(後)],$B$1) -> 0 | AF45: 件
Z46: 手持ち | AA46: =COUNTIFS(台帳表ｋ[ＮＣ区分],"南部",台帳表ｋ[顧客引渡 実施日],"") -> 0 | AB46: 件 | AD46: TG清算 | AE46: =SUMIFS(測量台帳1ｋ[入金額],測量台帳1ｋ[入金月（月のみ）],$B$1,測量台帳1ｋ[NC区分],"南部")+SUMIFS(測量台帳1__2ｋ[入金額(後)],測量台帳1__2ｋ[入金月(後)（月のみ）],$B$1,測量台帳1__2ｋ[NC区分],"南部") -> 0 | AF46: 千円
C47: 南部NC傾向 | Z47: 保留 | AA47: =COUNTIFS(台帳表ｋ[ＮＣ区分],"南部",台帳表ｋ[顧客引渡 実施日],"保留") -> 0 | AB47: 件
AF49: 設計 | AG49: 手持ち | AH49: 保留
AF50: 西部 | AG50: =+AA6 -> 0 | AH50: =+AA7 -> 0
AF51: 北部 | AG51: =+AA28 -> 0 | AH51: =+AA29 -> 0
AF52: 南部 | AG52: =+AA46 -> 0 | AH52: =+AA47 -> 0 | AI52: 計
C53: 南部NC今月の戦略 | W53: 南部NC売上 | X53: =+AB53+AB54 -> 0 | Y53: 千円 | Z53: ☚ | AA53: 設計 | AB53: =AA45 -> 0 | AC53: 千円 | AG53: =SUM(AG50:AG52) -> 0 | AH53: =SUM(AH50:AH52) -> 0 | AI53: =SUM(AG53:AH53) -> 0
AA54: 杭測 | AB54: =AE46 -> 0 | AC54: 千円
C56: 全エリア共通
C57: 設計
C58: 杭
B60: =+B1 -> #REF! | C60: =+C1 -> 月売上速報（導管本部） | W60: 多摩 | Y60: 設計 | AD60: 杭測
B61: 多摩（事） | C61: 売上速報 | D61: =+J61+Q61 -> 0 | H61: 杭以外売上 | J61: =+AA64 -> 0 | O61: 杭測売上 | Q61: =+AE65 -> 0 | W61: 先月目標累計 | X61: =IF($B$1=6,"0",SUM(目標比較!$D$14:INDEX(目標比較!$D$14:$O$14,MATCH(速報sheet!$B$1,目標比較!$D$5:$O$5, 0)-1))) -> #REF! | Z61: NC受注 | AA61: =COUNTIFS(台帳表ｋ[ＮＣ区分],"多摩",#REF!,$B$1) -> #REF! | AB61: 件 | AD61: TG受注 | AE61: =COUNTIFS(測量台帳1ｋ[NC区分],"多摩",測量台帳1ｋ[受注月],$B$1)+COUNTIFS(測量台帳1__2ｋ[NC区分],"多摩",測量台帳1__2ｋ[受注月(後)],$B$1) -> 0 | AF61: 件 | AG61: 未発注 | AH61: =COUNTIFS(測量台帳1ｋ[NC区分],"多摩",測量台帳1ｋ[外注 発注月],"<>")+COUNTIFS(測量台帳1__2ｋ[NC区分],"多摩",測量台帳1__2ｋ[外注 発注月(後)],"<>") -> 0
C62: 売上目標 | D62: =X62 -> #REF! | E62: 差額 | F62: =D61-D62 -> #REF! | H62: 杭以外予想 | J62: =+X66 -> #REF! | L62: 差額 | M62: =J61-J62 -> #REF! | O62: 杭測予想 | Q62: =+X67 -> #REF! | S62: 差額 | T62: =Q61-Q62 -> #REF! | W62: 今月目標 | X62: =INDEX(目標比較!$D$14:$O$14, MATCH(速報sheet!$B$1,目標比較!$D$5:$O$5, 0)) -> #REF! | Z62: NC納品 | AA62: =COUNTIFS(台帳表ｋ[ＮＣ区分],"多摩",台帳表ｋ[納品月],$B$1) -> 0 | AB62: 件 | AD62: 外注発注 | AE62: =COUNTIFS(測量台帳1ｋ[NC区分],"多摩",測量台帳1ｋ[外注 発注月],$B$1)+COUNTIFS(測量台帳1__2ｋ[NC区分],"多摩",測量台帳1__2ｋ[外注 発注月(後)],$B$1) -> 0 | AF62: 件
C63: 売上累計 | D63: =+D61+X64 -> #REF! | E63: 差額 | F63: =D63-X63 -> #REF! | H63: 全体予想 | J63: =+X65 -> #REF! | L63: 差額 | M63: =D61-J63 -> #REF! | O63: 来月売上目標 | Q63: =X68 -> #REF! | W63: 今月目標累計 | X63: =IF($B$1=6,"0",SUM(目標比較!$D$14:INDEX(目標比較!$D$14:$O$14,MATCH(速報sheet!$B$1,目標比較!$D$5:$O$5, 0)))) -> #REF! | Z63: NC清算 | AA63: =COUNTIFS(台帳表ｋ[ＮＣ区分],"多摩",台帳表ｋ[入金月（月のみ）],$B$1) -> 0 | AB63: 件 | AD63: 外注納品 | AE63: =COUNTIFS(測量台帳1ｋ[NC区分],"多摩",測量台帳1ｋ[外注納品月],$B$1)+COUNTIFS(測量台帳1__2ｋ[NC区分],"多摩",測量台帳1__2ｋ[外注納品月(後)],$B$1) -> 0 | AF63: 件
C64: 要因 | W64: 先月売上累計 | X64: =IF($B$1=6,"0",SUM(速報sheet!$X$75:INDEX($X$75:$AI$75,MATCH(速報sheet!$B$1,$X$70:$AI$70, 0)-1))) -> #REF! | Z64: NC清算 | AA64: =SUMIFS(台帳表ｋ[金額],台帳表ｋ[入金月（月のみ）],$B$1,台帳表ｋ[ＮＣ区分],"多摩") -> 0 | AB64: 千円 | AD64: TG納品 | AE64: =COUNTIFS(測量台帳1ｋ[NC区分],"多摩",測量台帳1ｋ[納品月],$B$1)+COUNTIFS(測量台帳1__2ｋ[NC区分],"多摩",測量台帳1__2ｋ[納品 月(後)],$B$1) -> 0 | AF64: 件
W65: 今月予想売上 | X65: =INDEX(目標比較!$D$18:$O$18, MATCH(速報sheet!$B$1,目標比較!$D$5:$O$5, 0)) -> #REF! | Z65: 手持ち | AA65: =COUNTIFS(台帳表ｋ[ＮＣ区分],"多摩",台帳表ｋ[顧客引渡 実施日],"") -> 0 | AB65: 件 | AD65: TG清算 | AE65: =SUMIFS(測量台帳1ｋ[入金額],測量台帳1ｋ[入金月（月のみ）],$B$1,測量台帳1ｋ[NC区分],"多摩")+SUMIFS(測量台帳1__2ｋ[入金額(後)],測量台帳1__2ｋ[入金月(後)（月のみ）],$B$1,測量台帳1__2ｋ[NC区分],"多摩") -> 0 | AF65: 千円
W66: 今月杭以外予想 | X66: =INDEX(目標比較!$D$16:$O$16, MATCH(速報sheet!$B$1,目標比較!$D$5:$O$5, 0)) -> #REF! | Z66: 保留 | AA66: =COUNTIFS(台帳表ｋ[ＮＣ区分],"多摩",台帳表ｋ[顧客引渡 実施日],"保留") -> 0 | AB66: 件
W67: 今月杭予想売上 | X67: =INDEX(目標比較!$D$15:$O$15, MATCH(速報sheet!$B$1,目標比較!$D$5:$O$5, 0)) -> #REF!
W68: 来月売上目標 | X68: =INDEX(目標比較!$D$14:$O$14, MATCH(速報sheet!$B$1+1,目標比較!$D$5:$O$5, 0)) -> #REF!
X70: 6 | Y70: 7 | Z70: 8 | AA70: 9 | AB70: 10 | AC70: 11 | AD70: 12 | AE70: 1 | AF70: 2 | AG70: 3 | AH70: 4 | AI70: 5 | AJ70: 累計
C71: 傾向 | W71: 売上目標 | X71: =目標比較!D14 -> 56100000 | Y71: =目標比較!E14 -> 53900000 | Z71: =目標比較!F14 -> 50600000 | AA71: =目標比較!G14 -> 49300000 | AB71: =目標比較!H14 -> 48700000 | AC71: =目標比較!I14 -> 50800000 | AD71: =目標比較!J14 -> 52300000 | AE71: =目標比較!K14 -> 42200000 | ... AJ71: =目標比較!P14 -> 591000000
W72: 売上予想 | X72: =目標比較!D18 -> 25222233 | Y72: =目標比較!E18 -> 22760035 | Z72: =目標比較!F18 -> 23557703 | AA72: =目標比較!G18 -> 24706070 | AB72: =目標比較!H18 -> 18363916 | AC72: =目標比較!I18 -> 20574346 | AD72: =目標比較!J18 -> 20820082 | AE72: =目標比較!K18 -> 20522017 | ... AJ72: =目標比較!P18 -> 1.9569673e+08
W73: 杭予想 | X73: =目標比較!D15 -> 28100000 | Y73: =目標比較!E15 -> 27900000 | Z73: =目標比較!F15 -> 25600000 | AA73: =目標比較!G15 -> 24300000 | AB73: =目標比較!H15 -> 24700000 | AC73: =目標比較!I15 -> 25800000 | AD73: =目標比較!J15 -> 26300000 | AE73: =目標比較!K15 -> 20200000 | ... AJ73: =目標比較!P15 -> 296000000
W74: 杭以外予想 | X74: =目標比較!D16 -> 28000000 | Y74: =目標比較!E16 -> 26000000 | Z74: =目標比較!F16 -> 25000000 | AA74: =目標比較!G16 -> 25000000 | AB74: =目標比較!H16 -> 24000000 | AC74: =目標比較!I16 -> 25000000 | AD74: =目標比較!J16 -> 26000000 | AE74: =目標比較!K16 -> 22000000 | ... AJ74: =目標比較!P16 -> 295000000
W75: 実売上 | X75: =SUMIFS(台帳表ｋ[金額],台帳表ｋ[入金月（月のみ）],X$70,台帳表ｋ[ＮＣ区分],"多摩")+SUMIFS(測量台帳1ｋ[入金額],測量台帳1ｋ[入金月（月のみ）],X$70,測量台帳1ｋ[NC区分],"多摩")+SUMIFS(測量台帳1__2ｋ[入金額(後)],測量台帳1__2ｋ[入金月(後)（月のみ）],X$70,測量台帳1__2ｋ[NC区分],"多摩") -> 0 | Y75: =SUMIFS(台帳表ｋ[金額],台帳表ｋ[入金月（月のみ）],Y$70,台帳表ｋ[ＮＣ区分],"多摩")+SUMIFS(測量台帳1ｋ[入金額],測量台帳1ｋ[入金月（月のみ）],Y$70,測量台帳1ｋ[NC区分],"多摩")+SUMIFS(測量台帳1__2ｋ[入金額(後)],測量台帳1__2ｋ[入金月(後)（月のみ）],Y$70,測量台帳1__2ｋ[NC区分],"多摩") -> 0 | Z75: =SUMIFS(台帳表ｋ[金額],台帳表ｋ[入金月（月のみ）],Z$70,台帳表ｋ[ＮＣ区分],"多摩")+SUMIFS(測量台帳1ｋ[入金額],測量台帳1ｋ[入金月（月のみ）],Z$70,測量台帳1ｋ[NC区分],"多摩")+SUMIFS(測量台帳1__2ｋ[入金額(後)],測量台帳1__2ｋ[入金月(後)（月のみ）],Z$70,測量台帳1__2ｋ[NC区分],"多摩") -> 0 | AA75: =SUMIFS(台帳表ｋ[金額],台帳表ｋ[入金月（月のみ）],AA$70,台帳表ｋ[ＮＣ区分],"多摩")+SUMIFS(測量台帳1ｋ[入金額],測量台帳1ｋ[入金月（月のみ）],AA$70,測量台帳1ｋ[NC区分],"多摩")+SUMIFS(測量台帳1__2ｋ[入金額(後)],測量台帳1__2ｋ[入金月(後)（月のみ）],AA$70,測量台帳1__2ｋ[NC区分],"多摩") -> 0 | AB75: =SUMIFS(台帳表ｋ[金額],台帳表ｋ[入金月（月のみ）],AB$70,台帳表ｋ[ＮＣ区分],"多摩")+SUMIFS(測量台帳1ｋ[入金額],測量台帳1ｋ[入金月（月のみ）],AB$70,測量台帳1ｋ[NC区分],"多摩")+SUMIFS(測量台帳1__2ｋ[入金額(後)],測量台帳1__2ｋ[入金月(後)（月のみ）],AB$70,測量台帳1__2ｋ[NC区分],"多摩") -> 0 | AC75: =SUMIFS(台帳表ｋ[金額],台帳表ｋ[入金月（月のみ）],AC$70,台帳表ｋ[ＮＣ区分],"多摩")+SUMIFS(測量台帳1ｋ[入金額],測量台帳1ｋ[入金月（月のみ）],AC$70,測量台帳1ｋ[NC区分],"多摩")+SUMIFS(測量台帳1__2ｋ[入金額(後)],測量台帳1__2ｋ[入金月(後)（月のみ）],AC$70,測量台帳1__2ｋ[NC区分],"多摩") -> 0 | AD75: =SUMIFS(台帳表ｋ[金額],台帳表ｋ[入金月（月のみ）],AD$70,台帳表ｋ[ＮＣ区分],"多摩")+SUMIFS(測量台帳1ｋ[入金額],測量台帳1ｋ[入金月（月のみ）],AD$70,測量台帳1ｋ[NC区分],"多摩")+SUMIFS(測量台帳1__2ｋ[入金額(後)],測量台帳1__2ｋ[入金月(後)（月のみ）],AD$70,測量台帳1__2ｋ[NC区分],"多摩") -> 0 | AE75: =SUMIFS(台帳表ｋ[金額],台帳表ｋ[入金月（月のみ）],AE$70,台帳表ｋ[ＮＣ区分],"多摩")+SUMIFS(測量台帳1ｋ[入金額],測量台帳1ｋ[入金月（月のみ）],AE$70,測量台帳1ｋ[NC区分],"多摩")+SUMIFS(測量台帳1__2ｋ[入金額(後)],測量台帳1__2ｋ[入金月(後)（月のみ）],AE$70,測量台帳1__2ｋ[NC区分],"多摩") -> 0 | ... AI75: =SUMIFS(台帳表ｋ[金額],台帳表ｋ[入金月（月のみ）],AI$70,台帳表ｋ[ＮＣ区分],"多摩")+SUMIFS(測量台帳1ｋ[入金額],測量台帳1ｋ[入金月（月のみ）],AI$70,測量台帳1ｋ[NC区分],"多摩")+SUMIFS(測量台帳1__2ｋ[入金額(後)],測量台帳1__2ｋ[入金月(後)（月のみ）],AI$70,測量台帳1__2ｋ[NC区分],"多摩") -> 0 | AJ75: =SUM(X75:AI75) -> 0
C76: 今月の戦略 | W76: 繁閑調整 | X76: エリア
W77: 西部NC管内 | X77: 311 | Y77: ➡ | AA77: 千円 | AB77: ⇐ | AC77: 多摩事業所で西部NC設計分を処理した金額
B82: =+B1 -> #REF! | C82: =+C60 -> 月売上速報（導管本部） | W82: 神奈川 | Y82: 設計 | AD82: 杭測
B83: 神奈川（事） | C83: 売上速報 | D83: =+J83+Q83 -> 0 | H83: 杭以外売上 | J83: =+AA86 -> 0 | O83: 杭測売上 | Q83: =+AE87 -> 0 | W83: 先月目標累計 | X83: =IF($B$1=6,"0",SUM(目標比較!$D$21:INDEX(目標比較!$D$21:$O$21,MATCH(速報sheet!$B$1,目標比較!$D$5:$O$5, 0)-1))) -> #REF! | Z83: NC受注 | AA83: =COUNTIFS(台帳表ｋ[ＮＣ区分],"神奈川",#REF!,$B$1) -> #REF! | AB83: 件 | AD83: TG受注 | AE83: =COUNTIFS(測量台帳1ｋ[NC区分],"神奈川",測量台帳1ｋ[受注月],$B$1)+COUNTIFS(測量台帳1__2ｋ[NC区分],"神奈川",測量台帳1__2ｋ[受注月(後)],$B$1) -> 0 | AF83: 件 | AG83: 未発注 | AH83: =COUNTIFS(測量台帳1ｋ[NC区分],"神奈川",測量台帳1ｋ[外注 発注月],"<>")+COUNTIFS(測量台帳1__2ｋ[NC区分],"神奈川",測量台帳1__2ｋ[外注 発注月(後)],"<>") -> 3022
C84: 売上目標 | D84: =X84 -> #REF! | E84: 差額 | F84: =D83-D84 -> #REF! | H84: 杭以外予想 | J84: =+X88 -> #REF! | L84: 差額 | M84: =J83-J84 -> #REF! | O84: 杭測予想 | Q84: =+X89 -> #REF! | S84: 差額 | T84: =Q83-Q84 -> #REF! | W84: 今月目標 | X84: =INDEX(目標比較!$D$21:$O$21, MATCH(速報sheet!$B$1,目標比較!$D$5:$O$5, 0)) -> #REF! | Z84: NC納品 | AA84: =COUNTIFS(台帳表ｋ[ＮＣ区分],"神奈川",台帳表ｋ[納品月],$B$1) -> 0 | AB84: 件 | AD84: 外注発注 | AE84: =COUNTIFS(測量台帳1ｋ[NC区分],"神奈川",測量台帳1ｋ[外注 発注月],$B$1)+COUNTIFS(測量台帳1__2ｋ[NC区分],"神奈川",測量台帳1__2ｋ[外注 発注月(後)],$B$1) -> 0 | AF84: 件
C85: 売上累計 | D85: =+D83+X86 -> #REF! | E85: 差額 | F85: =D85-X85 -> #REF! | H85: 全体予想 | J85: =+X87 -> #REF! | L85: 差額 | M85: =D83-J85 -> #REF! | O85: 来月売上目標 | Q85: =X90 -> #REF! | W85: 今月目標累計 | X85: =IF($B$1=6,"0",SUM(目標比較!$D$21:INDEX(目標比較!$D$21:$O$21,MATCH(速報sheet!$B$1,目標比較!$D$5:$O$5, 0)))) -> #REF! | Z85: NC清算 | AA85: =COUNTIFS(台帳表ｋ[ＮＣ区分],"神奈川",台帳表ｋ[入金月（月のみ）],$B$1) -> 0 | AB85: 件 | AD85: 外注納品 | AE85: =COUNTIFS(測量台帳1ｋ[NC区分],"神奈川",測量台帳1ｋ[外注納品月],$B$1)+COUNTIFS(測量台帳1__2ｋ[NC区分],"神奈川",測量台帳1__2ｋ[外注納品月(後)],$B$1) -> 0 | AF85: 件
C86: 要因 | W86: 先月売上累計 | X86: =IF($B$1=6,"0",SUM(速報sheet!$X$98:INDEX($X$98:$AI$98,MATCH(速報sheet!$B$1,$X$93:$AI$93, 0)-1))) -> #REF! | Z86: NC清算 | AA86: =SUMIFS(台帳表ｋ[金額],台帳表ｋ[入金月（月のみ）],$B$1,台帳表ｋ[ＮＣ区分],"神奈川") -> 0 | AB86: 千円 | AD86: TG納品 | AE86: =COUNTIFS(測量台帳1ｋ[NC区分],"神奈川",測量台帳1ｋ[納品月],$B$1)+COUNTIFS(測量台帳1__2ｋ[NC区分],"神奈川",測量台帳1__2ｋ[納品 月(後)],$B$1) -> 0 | AF86: 件
W87: 今月予想売上 | X87: =INDEX(目標比較!$D$25:$O$25, MATCH(速報sheet!$B$1,目標比較!$D$5:$O$5, 0)) -> #REF! | Z87: 手持ち | AA87: =COUNTIFS(台帳表ｋ[ＮＣ区分],"神奈川",台帳表ｋ[顧客引渡 実施日],"") -> 0 | AB87: 件 | AD87: TG清算 | AE87: =SUMIFS(測量台帳1ｋ[入金額],測量台帳1ｋ[入金月（月のみ）],$B$1,測量台帳1ｋ[NC区分],"神奈川")+SUMIFS(測量台帳1__2ｋ[入金額(後)],測量台帳1__2ｋ[入金月(後)（月のみ）],$B$1,測量台帳1__2ｋ[NC区分],"神奈川") -> 0 | AF87: 千円
W88: 今月杭以外予想 | X88: =INDEX(目標比較!$D$23:$O$23, MATCH(速報sheet!$B$1,目標比較!$D$5:$O$5, 0)) -> #REF! | Z88: 保留 | AA88: =COUNTIFS(台帳表ｋ[ＮＣ区分],"神奈川",台帳表ｋ[顧客引渡 実施日],"保留") -> 0 | AB88: 件
W89: 今月杭予想売上 | X89: =INDEX(目標比較!$D$22:$O$22, MATCH(速報sheet!$B$1,目標比較!$D$5:$O$5, 0)) -> #REF!
W90: 来月売上目標 | X90: =INDEX(目標比較!$D$21:$O$21, MATCH(速報sheet!$B$1+1,目標比較!$D$5:$O$5, 0)) -> #REF!
N91: 神奈川事業所売上 | Q91: ： | R91: =SUMIFS(台帳表ｋ[金額],台帳表ｋ[入金月（月のみ）],$B$1,台帳表ｋ[事務所/分室],"神")+SUMIFS(測量台帳1ｋ[入金額],測量台帳1ｋ[入金月（月のみ）],$B$1,測量台帳1ｋ[NC区分],"神奈川")+SUMIFS(測量台帳1__2ｋ[入金額(後)],測量台帳1__2ｋ[入金月(後)（月のみ）],$B$1,測量台帳1__2ｋ[NC区分],"神奈川") -> 0 | T91: 千円
N92: 湘南分室売上 | Q92: ： | R92: =SUMIFS(台帳表ｋ[金額],台帳表ｋ[入金月（月のみ）],$B$1,台帳表ｋ[事務所/分室],"湘")+SUMIFS(測量台帳1ｋ[入金額],測量台帳1ｋ[入金月（月のみ）],$B$1,測量台帳1ｋ[NC区分],"湘南")+SUMIFS(測量台帳1__2ｋ[入金額(後)],測量台帳1__2ｋ[入金月(後)（月のみ）],$B$1,測量台帳1__2ｋ[NC区分],"湘南") -> 0 | T92: 千円
C93: 傾向 | X93: 6 | Y93: 7 | Z93: 8 | AA93: 9 | AB93: 10 | AC93: 11 | AD93: 12 | AE93: 1 | AF93: 2 | AG93: 3 | AH93: 4 | AI93: 5 | AJ93: 累計
W94: 総売上目標 | X94: =目標比較!D21 -> 32500000 | Y94: =目標比較!E21 -> 31600000 | Z94: =目標比較!F21 -> 30400000 | AA94: =目標比較!G21 -> 30400000 | AB94: =目標比較!H21 -> 32900000 | AC94: =目標比較!I21 -> 29600000 | AD94: =目標比較!J21 -> 27500000 | AE94: =目標比較!K21 -> 29800000 | ... AJ94: =目標比較!P21 -> 396000000
W95: 売上予想 | X95: =目標比較!D25 -> 21067120 | Y95: =目標比較!E25 -> 19938347 | Z95: =目標比較!F25 -> 19929693 | AA95: =目標比較!G25 -> 19016747 | AB95: =目標比較!H25 -> 26028214 | AC95: =目標比較!I25 -> 17391596 | AD95: =目標比較!J25 -> 16804410 | AE95: =目標比較!K25 -> 16698851 | ... AJ95: =目標比較!P25 -> 177063726
W96: 杭予想 | X96: =目標比較!D22 -> 19300000 | Y96: =目標比較!E22 -> 18900000 | Z96: =目標比較!F22 -> 17800000 | AA96: =目標比較!G22 -> 17800000 | AB96: =目標比較!H22 -> 19600000 | AC96: =目標比較!I22 -> 17700000 | AD96: =目標比較!J22 -> 15200000 | AE96: =目標比較!K22 -> 18000000 | ... AJ96: =目標比較!P22 -> 234000000
W97: 総杭以外予想 | X97: =目標比較!D23 -> 13200000 | Y97: =目標比較!E23 -> 12700000 | Z97: =目標比較!F23 -> 12600000 | AA97: =目標比較!G23 -> 12600000 | AB97: =目標比較!H23 -> 13300000 | AC97: =目標比較!I23 -> 11900000 | AD97: =目標比較!J23 -> 12300000 | AE97: =目標比較!K23 -> 11800000 | ... AJ97: =目標比較!P23 -> 162000000
C98: 今月の戦略 | W98: 実売上 | X98: =SUMIFS(台帳表ｋ[金額],台帳表ｋ[入金月（月のみ）],X$93,台帳表ｋ[ＮＣ区分],"神奈川")+SUMIFS(測量台帳1ｋ[入金額],測量台帳1ｋ[入金月（月のみ）],X$93,測量台帳1ｋ[NC区分],"神奈川")+SUMIFS(測量台帳1__2ｋ[入金額(後)],測量台帳1__2ｋ[入金月(後)（月のみ）],X$93,測量台帳1__2ｋ[NC区分],"神奈川") -> 40427773 | Y98: =SUMIFS(台帳表ｋ[金額],台帳表ｋ[入金月（月のみ）],Y$93,台帳表ｋ[ＮＣ区分],"神奈川")+SUMIFS(測量台帳1ｋ[入金額],測量台帳1ｋ[入金月（月のみ）],Y$93,測量台帳1ｋ[NC区分],"神奈川")+SUMIFS(測量台帳1__2ｋ[入金額(後)],測量台帳1__2ｋ[入金月(後)（月のみ）],Y$93,測量台帳1__2ｋ[NC区分],"神奈川") -> 38152494 | Z98: =SUMIFS(台帳表ｋ[金額],台帳表ｋ[入金月（月のみ）],Z$93,台帳表ｋ[ＮＣ区分],"神奈川")+SUMIFS(測量台帳1ｋ[入金額],測量台帳1ｋ[入金月（月のみ）],Z$93,測量台帳1ｋ[NC区分],"神奈川")+SUMIFS(測量台帳1__2ｋ[入金額(後)],測量台帳1__2ｋ[入金月(後)（月のみ）],Z$93,測量台帳1__2ｋ[NC区分],"神奈川") -> 37918360 | AA98: =SUMIFS(台帳表ｋ[金額],台帳表ｋ[入金月（月のみ）],AA$93,台帳表ｋ[ＮＣ区分],"神奈川")+SUMIFS(測量台帳1ｋ[入金額],測量台帳1ｋ[入金月（月のみ）],AA$93,測量台帳1ｋ[NC区分],"神奈川")+SUMIFS(測量台帳1__2ｋ[入金額(後)],測量台帳1__2ｋ[入金月(後)（月のみ）],AA$93,測量台帳1__2ｋ[NC区分],"神奈川") -> 39238342 | AB98: =SUMIFS(台帳表ｋ[金額],台帳表ｋ[入金月（月のみ）],AB$93,台帳表ｋ[ＮＣ区分],"神奈川")+SUMIFS(測量台帳1ｋ[入金額],測量台帳1ｋ[入金月（月のみ）],AB$93,測量台帳1ｋ[NC区分],"神奈川")+SUMIFS(測量台帳1__2ｋ[入金額(後)],測量台帳1__2ｋ[入金月(後)（月のみ）],AB$93,測量台帳1__2ｋ[NC区分],"神奈川") -> 41198830 | AC98: =SUMIFS(台帳表ｋ[金額],台帳表ｋ[入金月（月のみ）],AC$93,台帳表ｋ[ＮＣ区分],"神奈川")+SUMIFS(測量台帳1ｋ[入金額],測量台帳1ｋ[入金月（月のみ）],AC$93,測量台帳1ｋ[NC区分],"神奈川")+SUMIFS(測量台帳1__2ｋ[入金額(後)],測量台帳1__2ｋ[入金月(後)（月のみ）],AC$93,測量台帳1__2ｋ[NC区分],"神奈川") -> 32158315 | AD98: =SUMIFS(台帳表ｋ[金額],台帳表ｋ[入金月（月のみ）],AD$93,台帳表ｋ[ＮＣ区分],"神奈川")+SUMIFS(測量台帳1ｋ[入金額],測量台帳1ｋ[入金月（月のみ）],AD$93,測量台帳1ｋ[NC区分],"神奈川")+SUMIFS(測量台帳1__2ｋ[入金額(後)],測量台帳1__2ｋ[入金月(後)（月のみ）],AD$93,測量台帳1__2ｋ[NC区分],"神奈川") -> 31182309 | AE98: =SUMIFS(台帳表ｋ[金額],台帳表ｋ[入金月（月のみ）],AE$93,台帳表ｋ[ＮＣ区分],"神奈川")+SUMIFS(測量台帳1ｋ[入金額],測量台帳1ｋ[入金月（月のみ）],AE$93,測量台帳1ｋ[NC区分],"神奈川")+SUMIFS(測量台帳1__2ｋ[入金額(後)],測量台帳1__2ｋ[入金月(後)（月のみ）],AE$93,測量台帳1__2ｋ[NC区分],"神奈川") -> 32432448 | ... AI98: =SUMIFS(台帳表ｋ[金額],台帳表ｋ[入金月（月のみ）],AI$93,台帳表ｋ[ＮＣ区分],"神奈川")+SUMIFS(測量台帳1ｋ[入金額],測量台帳1ｋ[入金月（月のみ）],AI$93,測量台帳1ｋ[NC区分],"神奈川")+SUMIFS(測量台帳1__2ｋ[入金額(後)],測量台帳1__2ｋ[入金月(後)（月のみ）],AI$93,測量台帳1__2ｋ[NC区分],"神奈川") -> 0 | AJ98: =SUM(X98:AI98) -> 323589962
W102: 湘南 | Y102: 設計 | AD102: 杭測
B103: 参考 湘南（分） | C103: 売上速報 | D103: =+J103+Q103 -> 0 | H103: 杭以外売上 | J103: =+AA106 -> 0 | O103: 杭測売上 | Q103: =+AE107 -> 0 | W103: 先月目標累計 | X103: =IF($B$1=6,"0",SUM(目標比較!$D$28:INDEX(目標比較!$D$28:$O$28,MATCH(速報sheet!$B$1,目標比較!$D$5:$O$5, 0)-1))) -> #REF! | Z103: NC受注 | AA103: =COUNTIFS(台帳表ｋ[ＮＣ区分],"湘南",#REF!,$B$1) -> #REF! | AB103: 件 | AD103: TG受注 | AE103: =COUNTIFS(測量台帳1ｋ[NC区分],"湘南",測量台帳1ｋ[受注月],$B$1)+COUNTIFS(測量台帳1__2ｋ[NC区分],"湘南",測量台帳1__2ｋ[受注月(後)],$B$1) -> 0 | AF103: 件 | AG103: 未発注 | AH103: =COUNTIFS(測量台帳1ｋ[NC区分],"湘南",測量台帳1ｋ[外注 発注月],"<>")+COUNTIFS(測量台帳1__2ｋ[NC区分],"湘南",測量台帳1__2ｋ[外注 発注月(後)],"<>") -> 454
C104: 売上目標 | D104: =X104 -> #REF! | E104: 差額 | F104: =D103-D104 -> #REF! | H104: 杭以外予想 | J104: =+X108 -> #REF! | L104: 差額 | M104: =J103-J104 -> #REF! | O104: 杭測予想 | Q104: =+X109 -> #REF! | S104: 差額 | T104: =Q103-Q104 -> #REF! | W104: 今月目標 | X104: =INDEX(目標比較!$D$28:$O$28, MATCH(速報sheet!$B$1,目標比較!$D$5:$O$5, 0)) -> #REF! | Z104: NC納品 | AA104: =COUNTIFS(台帳表ｋ[ＮＣ区分],"湘南",台帳表ｋ[納品月],$B$1) -> 0 | AB104: 件 | AD104: 外注発注 | AE104: =COUNTIFS(測量台帳1ｋ[NC区分],"湘南",測量台帳1ｋ[外注 発注月],$B$1)+COUNTIFS(測量台帳1__2ｋ[NC区分],"湘南",測量台帳1__2ｋ[外注 発注月(後)],$B$1) -> 0 | AF104: 件
C105: 売上累計 | D105: =+D103+X106 -> #REF! | E105: 差額 | F105: =D105-X105 -> #REF! | H105: 全体予想 | J105: =+X107 -> #REF! | L105: 差額 | M105: =D103-J105 -> #REF! | O105: 来月売上目標 | Q105: =X110 -> #REF! | W105: 今月目標累計 | X105: =IF($B$1=6,"0",SUM(目標比較!$D$28:INDEX(目標比較!$D$28:$O$28,MATCH(速報sheet!$B$1,目標比較!$D$5:$O$5, 0)))) -> #REF! | Z105: NC清算 | AA105: =COUNTIFS(台帳表ｋ[ＮＣ区分],"湘南",台帳表ｋ[入金月（月のみ）],$B$1) -> 0 | AB105: 件 | AD105: 外注納品 | AE105: =COUNTIFS(測量台帳1ｋ[NC区分],"湘南",測量台帳1ｋ[外注納品月],$B$1)+COUNTIFS(測量台帳1__2ｋ[NC区分],"湘南",測量台帳1__2ｋ[外注納品月(後)],$B$1) -> 0 | AF105: 件
C106: 要因 | W106: 先月売上累計 | X106: =IF($B$1=6,"0",SUM(速報sheet!$X$117:INDEX($X$117:$AI$117,MATCH(速報sheet!$B$1,$X$112:$AI$112, 0)-1))) -> #REF! | Z106: NC清算 | AA106: =SUMIFS(台帳表ｋ[金額],台帳表ｋ[入金月（月のみ）],$B$1,台帳表ｋ[ＮＣ区分],"湘南") -> 0 | AB106: 千円 | AD106: TG納品 | AE106: =COUNTIFS(測量台帳1ｋ[NC区分],"湘南",測量台帳1ｋ[納品月],$B$1)+COUNTIFS(測量台帳1__2ｋ[NC区分],"湘南",測量台帳1__2ｋ[納品 月(後)],$B$1) -> 0 | AF106: 件
W107: 今月予想売上 | X107: =INDEX(目標比較!$D$32:$O$32, MATCH(速報sheet!$B$1,目標比較!$D$5:$O$5, 0)) -> #REF! | Z107: NC手持ち | AA107: =COUNTIFS(台帳表ｋ[ＮＣ区分],"湘南",台帳表ｋ[顧客引渡 実施日],"") -> 0 | AB107: 件 | AD107: TG清算 | AE107: =SUMIFS(測量台帳1ｋ[入金額],測量台帳1ｋ[入金月（月のみ）],$B$1,測量台帳1ｋ[NC区分],"湘南")+SUMIFS(測量台帳1__2ｋ[入金額(後)],測量台帳1__2ｋ[入金月(後)（月のみ）],$B$1,測量台帳1__2ｋ[NC区分],"湘南") -> 0 | AF107: 千円
W108: 今月杭以外予想 | X108: =INDEX(目標比較!$D$30:$O$30, MATCH(速報sheet!$B$1,目標比較!$D$5:$O$5, 0)) -> #REF! | Z108: 保留 | AA108: =COUNTIFS(台帳表ｋ[ＮＣ区分],"湘南",台帳表ｋ[顧客引渡 実施日],"保留") -> 0 | AB108: 件
W109: 今月杭予想売上 | X109: =INDEX(目標比較!$D$29:$O$29, MATCH(速報sheet!$B$1,目標比較!$D$5:$O$5, 0)) -> #REF!
W110: 来月売上目標 | X110: =INDEX(目標比較!$D$28:$O$28, MATCH(速報sheet!$B$1+1,目標比較!$D$5:$O$5, 0)) -> #REF!
X112: 6 | Y112: 7 | Z112: 8 | AA112: 9 | AB112: 10 | AC112: 11 | AD112: 12 | AE112: 1 | AF112: 2 | AG112: 3 | AH112: 4 | AI112: 5 | AJ112: 累計
C113: 傾向 | W113: 総売上目標 | X113: =目標比較!D28 -> 9200000 | Y113: =目標比較!E28 -> 8900000 | Z113: =目標比較!F28 -> 8600000 | AA113: =目標比較!G28 -> 8600000 | AB113: =目標比較!H28 -> 9300000 | AC113: =目標比較!I28 -> 8400000 | AD113: =目標比較!J28 -> 7700000 | AE113: =目標比較!K28 -> 8400000 | ... AJ113: =目標比較!P28 -> 109000000
W114: 売上予想 | X114: =目標比較!D32 -> 266443 | Y114: =目標比較!E32 -> 2610977 | Z114: =目標比較!F32 -> 979679 | AA114: =目標比較!G32 -> 345205 | AB114: =目標比較!H32 -> 1290345 | AC114: =目標比較!I32 -> 1924682 | AD114: =目標比較!J32 -> 4627380 | AE114: =目標比較!K32 -> 7764155 | ... AJ114: =目標比較!P32 -> 26704751
W115: 杭予想 | X115: =目標比較!D29 -> 1400000 | Y115: =目標比較!E29 -> 1600000 | Z115: =目標比較!F29 -> 1200000 | AA115: =目標比較!G29 -> 1200000 | AB115: =目標比較!H29 -> 1600000 | AC115: =目標比較!I29 -> 1300000 | AD115: =目標比較!J29 -> 1000000 | AE115: =目標比較!K29 -> 1200000 | ... AJ115: =目標比較!P29 -> 16000000
W116: 総杭以外予想 | X116: =目標比較!D30 -> 7800000 | Y116: =目標比較!E30 -> 7300000 | Z116: =目標比較!F30 -> 7400000 | AA116: =目標比較!G30 -> 7400000 | AB116: =目標比較!H30 -> 7700000 | AC116: =目標比較!I30 -> 7100000 | AD116: =目標比較!J30 -> 6700000 | AE116: =目標比較!K30 -> 7200000 | ... AJ116: =目標比較!P30 -> 93000000
W117: 実売上 | X117: =SUMIFS(台帳表ｋ[金額],台帳表ｋ[入金月（月のみ）],X$112,台帳表ｋ[ＮＣ区分],"湘南")+SUMIFS(測量台帳1ｋ[入金額],測量台帳1ｋ[入金月（月のみ）],X$112,測量台帳1ｋ[NC区分],"湘南")+SUMIFS(測量台帳1__2ｋ[入金額(後)],測量台帳1__2ｋ[入金月(後)（月のみ）],X$112,測量台帳1__2ｋ[NC区分],"湘南") -> 2568348 | Y117: =SUMIFS(台帳表ｋ[金額],台帳表ｋ[入金月（月のみ）],Y$112,台帳表ｋ[ＮＣ区分],"湘南")+SUMIFS(測量台帳1ｋ[入金額],測量台帳1ｋ[入金月（月のみ）],Y$112,測量台帳1ｋ[NC区分],"湘南")+SUMIFS(測量台帳1__2ｋ[入金額(後)],測量台帳1__2ｋ[入金月(後)（月のみ）],Y$112,測量台帳1__2ｋ[NC区分],"湘南") -> 4903478 | Z117: =SUMIFS(台帳表ｋ[金額],台帳表ｋ[入金月（月のみ）],Z$112,台帳表ｋ[ＮＣ区分],"湘南")+SUMIFS(測量台帳1ｋ[入金額],測量台帳1ｋ[入金月（月のみ）],Z$112,測量台帳1ｋ[NC区分],"湘南")+SUMIFS(測量台帳1__2ｋ[入金額(後)],測量台帳1__2ｋ[入金月(後)（月のみ）],Z$112,測量台帳1__2ｋ[NC区分],"湘南") -> 2349323 | AA117: =SUMIFS(台帳表ｋ[金額],台帳表ｋ[入金月（月のみ）],AA$112,台帳表ｋ[ＮＣ区分],"湘南")+SUMIFS(測量台帳1ｋ[入金額],測量台帳1ｋ[入金月（月のみ）],AA$112,測量台帳1ｋ[NC区分],"湘南")+SUMIFS(測量台帳1__2ｋ[入金額(後)],測量台帳1__2ｋ[入金月(後)（月のみ）],AA$112,測量台帳1__2ｋ[NC区分],"湘南") -> 2196893 | AB117: =SUMIFS(台帳表ｋ[金額],台帳表ｋ[入金月（月のみ）],AB$112,台帳表ｋ[ＮＣ区分],"湘南")+SUMIFS(測量台帳1ｋ[入金額],測量台帳1ｋ[入金月（月のみ）],AB$112,測量台帳1ｋ[NC区分],"湘南")+SUMIFS(測量台帳1__2ｋ[入金額(後)],測量台帳1__2ｋ[入金月(後)（月のみ）],AB$112,測量台帳1__2ｋ[NC区分],"湘南") -> 3763667 | AC117: =SUMIFS(台帳表ｋ[金額],台帳表ｋ[入金月（月のみ）],AC$112,台帳表ｋ[ＮＣ区分],"湘南")+SUMIFS(測量台帳1ｋ[入金額],測量台帳1ｋ[入金月（月のみ）],AC$112,測量台帳1ｋ[NC区分],"湘南")+SUMIFS(測量台帳1__2ｋ[入金額(後)],測量台帳1__2ｋ[入金月(後)（月のみ）],AC$112,測量台帳1__2ｋ[NC区分],"湘南") -> 7019962 | AD117: =SUMIFS(台帳表ｋ[金額],台帳表ｋ[入金月（月のみ）],AD$112,台帳表ｋ[ＮＣ区分],"湘南")+SUMIFS(測量台帳1ｋ[入金額],測量台帳1ｋ[入金月（月のみ）],AD$112,測量台帳1ｋ[NC区分],"湘南")+SUMIFS(測量台帳1__2ｋ[入金額(後)],測量台帳1__2ｋ[入金月(後)（月のみ）],AD$112,測量台帳1__2ｋ[NC区分],"湘南") -> 12113690 | AE117: =SUMIFS(台帳表ｋ[金額],台帳表ｋ[入金月（月のみ）],AE$112,台帳表ｋ[ＮＣ区分],"湘南")+SUMIFS(測量台帳1ｋ[入金額],測量台帳1ｋ[入金月（月のみ）],AE$112,測量台帳1ｋ[NC区分],"湘南")+SUMIFS(測量台帳1__2ｋ[入金額(後)],測量台帳1__2ｋ[入金月(後)（月のみ）],AE$112,測量台帳1__2ｋ[NC区分],"湘南") -> 11444369 | ... AI117: =SUMIFS(台帳表ｋ[金額],台帳表ｋ[入金月（月のみ）],AI$112,台帳表ｋ[ＮＣ区分],"湘南")+SUMIFS(測量台帳1ｋ[入金額],測量台帳1ｋ[入金月（月のみ）],AI$112,測量台帳1ｋ[NC区分],"湘南")+SUMIFS(測量台帳1__2ｋ[入金額(後)],測量台帳1__2ｋ[入金月(後)（月のみ）],AI$112,測量台帳1__2ｋ[NC区分],"湘南") -> 0 | AJ117: =SUM(X117:AI117) -> 61974293
C118: 今月の戦略 | W118: 👆
W119: 神奈川事業にて記載してください
B123: =B1 -> #REF! | C123: 月売上速報（設備本部）
...

Sheet 設備G入力用
A1: 設備売上入力
D2: グループ | E2: コード | F2: 6 | G2: 7 | H2: 8 | I2: 9 | J2: 10 | K2: 11 | L2: 12 | M2: 1 | N2: 2 | O2: 3 | P2: 4 | Q2: 5 | R2: 合計
A3: システム帳票 | B3: 西部計推 | C3: 西部ＮＣ | D3: 工事G | E3: 30 | F3: 123749 | G3: 730168 | H3: =168439+110677 -> 279116 | I3: 308458 | J3: 252656 | K3: 627832 | L3: 771975 | M3: 384785 | N3: 396957 | R3: =SUM(設備G入力用!$F3:$Q3) -> 3875696
D4: 供給G | E4: 31 | R4: =SUM(設備G入力用!$F4:$Q4) -> 0
D5: 保全T | E5: 33 | R5: =SUM(設備G入力用!$F5:$Q5) -> 0
D6: TGPN照会T | E6: 32 | R6: =SUM(設備G入力用!$F6:$Q6) -> 0
D7: 設計道調(311) | E7: 35 | R7: =SUM(設備G入力用!$F7:$Q7) -> 0
D8: 西部建設T(311) | E8: 45 | R8: =SUM(設備G入力用!$F8:$Q8) -> 0
C9: 多摩ＮＣ | D9: 工事G | E9: 40 | R9: =SUM(設備G入力用!$F9:$Q9) -> 0
D10: 供給G | E10: 41 | R10: =SUM(設備G入力用!$F10:$Q10) -> 0
D11: 保全T | E11: 42 | R11: =SUM(設備G入力用!$F11:$Q11) -> 0
D12: 照会T | E12: 43 | R12: =SUM(設備G入力用!$F12:$Q12) -> 0
D13: 道調T | E13: 44 | R13: =SUM(設備G入力用!$F13:$Q13) -> 0
D14: 設計道調(311) | E14: 35 | R14: =SUM(設備G入力用!$F14:$Q14) -> 0
D15: 西部建設T(311) | E15: 45 | R15: =SUM(設備G入力用!$F15:$Q15) -> 0
C16: 共通 | D16: GL24 | E16: 52 | R16: =SUM(設備G入力用!$F16:$Q16) -> 0
D17: 渉外G | E17: 07 | R17: =SUM(設備G入力用!$F17:$Q17) -> 0
D18: 地域計画部 | E18: 70 | R18: =SUM(設備G入力用!$F18:$Q18) -> 0
D19: 社内他受・IB | E19: IB | R19: =SUM(設備G入力用!$F19:$Q19) -> 0
D20: その他 | E20: 36 | R20: =SUM(設備G入力用!$F20:$Q20) -> 0
B21: 中央計推 | C21: 中央NC | D21: 南部NC工事T | E21: 10 | R21: =SUM(設備G入力用!$F21:$Q21) -> 0
D22: 南部NC保全T | E22: 17 | R22: =SUM(設備G入力用!$F22:$Q22) -> 0
D23: 南部NC照会T | E23: 13 | R23: =SUM(設備G入力用!$F23:$Q23) -> 0
D24: 南部NC供給T | R24: =SUM(設備G入力用!$F24:$Q24) -> 0
D25: 南部NC設計T | E25: 16 | R25: =SUM(設備G入力用!$F25:$Q25) -> 0
D26: 南部NC道調T | R26: =SUM(設備G入力用!$F26:$Q26) -> 0
C27: 共通 | D27: GL24 | R27: =SUM(設備G入力用!$F27:$Q27) -> 0
D28: 社内他受・IB | E28: IB | R28: =SUM(設備G入力用!$F28:$Q28) -> 0
D29: 渉外G | E29: 07 | R29: =SUM(設備G入力用!$F29:$Q29) -> 0
D30: 地域計画部 | E30: 70 | R30: =SUM(設備G入力用!$F30:$Q30) -> 0
D31: その他 | R31: =SUM(設備G入力用!$F31:$Q31) -> 0
B32: 北部計推 | C32: 埼玉NC | D32: 埼玉NC工事T | E32: 40 | R32: =SUM(設備G入力用!$F32:$Q32) -> 0
D33: 埼玉NC保全T | E33: 41 | R33: =SUM(設備G入力用!$F33:$Q33) -> 0
D34: 埼玉NC照会T | E34: 42 | R34: =SUM(設備G入力用!$F34:$Q34) -> 0
D35: 埼玉NC供給T | E35: 43 | R35: =SUM(設備G入力用!$F35:$Q35) -> 0
D36: 埼玉NC設計T | E36: 46 | R36: =SUM(設備G入力用!$F36:$Q36) -> 0
D37: 埼玉NC道調T | E37: 47 | R37: =SUM(設備G入力用!$F37:$Q37) -> 0
C38: 北部NC | D38: 北部NC工事T | E38: 30 | R38: =SUM(設備G入力用!$F38:$Q38) -> 0
D39: 北部NC保全T | E39: 32 | R39: =SUM(設備G入力用!$F39:$Q39) -> 0
D40: 北部NC照会T | E40: 33 | R40: =SUM(設備G入力用!$F40:$Q40) -> 0
D41: 北部NC供給T | R41: =SUM(設備G入力用!$F41:$Q41) -> 0
D42: 北部NC設計T | E42: 37 | R42: =SUM(設備G入力用!$F42:$Q42) -> 0
D43: 北部NC道調T | R43: =SUM(設備G入力用!$F43:$Q43) -> 0
C44: 共通 | D44: GL24 | R44: =SUM(設備G入力用!$F44:$Q44) -> 0
D45: 社内他受・IB | E45: IB | R45: =SUM(設備G入力用!$F45:$Q45) -> 0
D46: 渉外G | E46: 07 | R46: =SUM(設備G入力用!$F46:$Q46) -> 0
D47: 地域計画部 | E47: 70 | R47: =SUM(設備G入力用!$F47:$Q47) -> 0
D48: その他 | R48: =SUM(設備G入力用!$F48:$Q48) -> 0
B49: 神奈川計推 | C49: 神奈川ＮＣ | D49: 工事G Ⅰ | E49: 20 | R49: =SUM(設備G入力用!$F49:$Q49) -> 0
D50: 工事G Ⅱ | E50: 21 | F50: 85084 | G50: 181594 | H50: 134777 | I50: 211012 | J50: 120767 | K50: 323128 | L50: 147706 | M50: 137702 | N50: 227189 | R50: =SUM(設備G入力用!$F50:$Q50) -> 1568959
D51: 供給G | E51: 22 | R51: =SUM(設備G入力用!$F51:$Q51) -> 0
D52: 保全T | E52: 23 | R52: =SUM(設備G入力用!$F52:$Q52) -> 0
D53: 照会T | E53: 24 | R53: =SUM(設備G入力用!$F53:$Q53) -> 0
D54: 設計道調G | E54: 27 | R54: =SUM(設備G入力用!$F54:$Q54) -> 0
C55: 湘南 | D55: 湘南1工事G | E55: 40 | R55: =SUM(設備G入力用!$F55:$Q55) -> 0
D56: 湘南2工事G | E56: 48 | R56: =SUM(設備G入力用!$F56:$Q56) -> 0
D57: 湘南保全G | E57: 41 | R57: =SUM(設備G入力用!$F57:$Q57) -> 0
D58: 湘南照会Ｇ | E58: 42 | R58: =SUM(設備G入力用!$F58:$Q58) -> 0
D59: 湘南供給Ｇ | E59: 43 | R59: =SUM(設備G入力用!$F59:$Q59) -> 0
D60: 湘南設計G | E60: 46 | R60: =SUM(設備G入力用!$F60:$Q60) -> 0
C61: 共通 | D61: GL24 | E61: 50 | R61: =SUM(設備G入力用!$F61:$Q61) -> 0
D62: 地計G | E62: 70 | R62: =SUM(設備G入力用!$F62:$Q62) -> 0
D63: 社内他受・IB | E63: IB | R63: =SUM(設備G入力用!$F63:$Q63) -> 0
D64: 渉外G | E64: 07 | R64: =SUM(設備G入力用!$F64:$Q64) -> 0
D65: その他 | R65: =SUM(設備G入力用!$F65:$Q65) -> 0
B66: 他 | D66: 160 幹線G | E66: 61 | R66: =SUM(設備G入力用!$F66:$Q66) -> 0
A67: 手書き請求書 | D67: ＮＣ道路T申請 | E67: 100 | R67: =SUM(設備G入力用!$F67:$Q67) -> 0
D68: 杭測量 | E68: 101 | R68: =SUM(設備G入力用!$F68:$Q68) -> 0
D69: その他(請求書) | E69: 103 | R69: =SUM(設備G入力用!$F69:$Q69) -> 0
D70: 内管改善 | E70: 201 | R70: =SUM(設備G入力用!$F70:$Q70) -> 0
D71: 地域計画部 | E71: 202 | R71: =SUM(設備G入力用!$F71:$Q71) -> 0
D72: その他営業 | E72: 203 | R72: =SUM(設備G入力用!$F72:$Q72) -> 0
D73: 合計 | F73: =SUBTOTAL(109,設備G入力用!$F$3:$F$72) -> 208833 | G73: =SUBTOTAL(109,設備G入力用!$G$3:$G$72) -> 911762 | H73: =SUBTOTAL(109,設備G入力用!$H$3:$H$72) -> 413893 | I73: =SUBTOTAL(109,設備G入力用!$I$3:$I$72) -> 519470 | J73: =SUBTOTAL(109,設備G入力用!$J$3:$J$72) -> 373423 | K73: =SUBTOTAL(109,設備G入力用!$K$3:$K$72) -> 950960 | L73: =SUBTOTAL(109,設備G入力用!$L$3:$L$72) -> 919681 | M73: =SUBTOTAL(109,設備G入力用!$M$3:$M$72) -> 522487 | N73: =SUBTOTAL(109,設備G入力用!$N$3:$N$72) -> 624146 | O73: =SUBTOTAL(109,設備G入力用!$O$3:$O$72) -> 0 | P73: =SUBTOTAL(109,設備G入力用!$P$3:$P$72) -> 0 | Q73: =SUBTOTAL(109,設備G入力用!$Q$3:$Q$72) -> 0 | R73: =SUBTOTAL(109,設備G入力用!$R$3:$R$72) -> 5444655
E76: 多摩 | J76: 140000 | K76: 140000 | L76: 140000 | M76: 84000 | N76: 84000
E77: 西部
E78: 神奈川
E79: 湘南

Sheet 確報【６月】
A1: 6 | D1: 月 | F1: 売上確定報告 | AA1: TG係別確認用
H2: TRUST集計 | AA2: TRUST集計用
H3: 導管本部 | V3: 設備本部
H4: 西部（西部NC） | J4: 西部（埼玉NC） | L4: 西部（北部NC） | N4: 西部（中央NC） | P4: 多摩（NC） | R4: 神奈川（NC） | T4: 湘南分室（NC） | V4: 設備技術G | X4: 合 計 | AF4: 西部（事）から | AL4: 多摩（事）から | AR4: 神奈川（事）から | AX4: 神奈川（事）分室から
A5: TGNW | B5: 導管 | C5: システム帳票 | H5: =SUM(I6:I69) -> 7571638 | J5: =SUM(K6:K69) -> 181330 | L5: =SUM(M6:M69) -> 4669006 | N5: =SUM(O6:O69) -> 5225252 | P5: =SUM(Q6:Q69) -> 39969992 | R5: =SUM(S6:S69) -> 32872643 | T5: =SUM(U6:U69) -> 9162308 | V5: =SUM(W6:W69) -> 208833 | X5: A₌Ｂ~M | Y5: =SUM(H5:W5) -> 99861002 | Z5: A | AE5: 西 | AF5: 調整先 | AG5: G | AH5: 発行NO | AI5: 金額 | AK5: 多 | AL5: 調整先 | AM5: G | AN5: 発行NO | AO5: 金額 | AQ5: 神 | AR5: 調整先 | AS5: G | AT5: 発行NO | AU5: 金額 | AW5: 湘 | AX5: 調整先 | AY5: G | AZ5: 発行NO | BA5: 金額
C6: システム帳票 | D6: 西部計推 | E6: 西部ＮＣ | F6: 工事G | G6: * | H6: 30 | I6: =SUMIFS(台帳表ｓ[金額],台帳表ｓ[精算 グループ],確報【６月】!$H6,台帳表ｓ[入金月（月のみ）],確報【６月】!$A$1,台帳表ｓ[ＮＣ区分],"西部")+SUMIFS(測量台帳1ｓ[入金額],測量台帳1ｓ[精算 グループ],確報【６月】!$H6,測量台帳1ｓ[入金月（月のみ）],確報【６月】!$A$1,測量台帳1ｓ[NC区分],"西部")+SUMIFS(測量台帳1__2ｓ[入金額(後)],測量台帳1__2ｓ[精算 グループ(後)],確報【６月】!$H6,測量台帳1__2ｓ[入金月(後)（月のみ）],確報【６月】!$A$1,測量台帳1__2ｓ[NC区分],"西部") -> 5485534 | J6: 30 | L6: 30 | N6: 30 | P6: 30 | Q6: =SUMIFS(台帳表ｔ[金額],台帳表ｔ[精算 グループ],確報【６月】!$H6,台帳表ｔ[入金月（月のみ）],確報【６月】!$A$1,台帳表ｔ[ＮＣ区分],"多摩")+SUMIFS(測量台帳1ｔ[入金額],測量台帳1ｔ[精算 グループ],確報【６月】!$H6,測量台帳1ｔ[入金月（月のみ）],確報【６月】!$A$1,測量台帳1ｔ[NC区分],"多摩")+SUMIFS(測量台帳1__2ｔ[入金額(後)],測量台帳1__2ｔ[精算 グループ(後)],確報【６月】!$H6,測量台帳1__2ｔ[入金月(後)（月のみ）],確報【６月】!$A$1,測量台帳1__2ｔ[NC区分],"多摩") -> 0 | R6: 30 | T6: 30 | V6: 30 | W6: {=INDEX(設備G入力用!$F$2:$Q$72,ROW(A2), MATCH($A$1,設備G入力用!$F$2:$Q$2,0))} -> 123749 | X6: =SUM(I6,K6,M6,O6,Q6,S6,U6,W6) -> 5609283 | AA6: 西部計推 | AB6: 30 | AC6: =SUM(I6,K6,M6,O6,Q6,S6,U6,W6) -> 5609283 | AE6: {=IFERROR(_xlfn._xlws.FILTER(台帳表ｓ[整理番号], (台帳表ｓ[繁閑調整]<>"") *(CLEAN(台帳表ｓ[入金月（月のみ）])=CLEAN($A$1))),"なし")} -> なし | AF6: =IFERROR(_xlfn.XLOOKUP(確報【６月】!$AE6,台帳表ｓ[整理番号],台帳表ｓ[繁閑調整]),"") | AG6: =IFERROR(_xlfn.XLOOKUP(確報【６月】!$AE6,台帳表ｓ[整理番号],台帳表ｓ[精算 グループ]),"") | AH6: =IFERROR(_xlfn.XLOOKUP(確報【６月】!$AE6,台帳表ｓ[整理番号],台帳表ｓ[請求書発行番号]),"") | AI6: =IFERROR(_xlfn.XLOOKUP(確報【６月】!$AE6,台帳表ｓ[整理番号],台帳表ｓ[繁閑調整金]),"") | AK6: {=IFERROR(_xlfn._xlws.FILTER(台帳表ｔ[整理番号], (台帳表ｔ[繁閑調整]<>"") *(CLEAN(台帳表ｔ[入金月（月のみ）])=CLEAN($A$1))),"なし")} -> 535 | AL6: =IFERROR(_xlfn.XLOOKUP(確報【６月】!AK6,台帳表ｔ[整理番号],台帳表ｔ[繁閑調整]),"") -> 設備 | AM6: =IFERROR(_xlfn.XLOOKUP(確報【６月】!AK6,台帳表ｔ[整理番号],台帳表ｔ[精算 グループ]),"") -> 42 | AN6: =IFERROR(_xlfn.XLOOKUP(確報【６月】!AK6,台帳表ｔ[整理番号],台帳表ｔ[請求書発行番号]),"") -> 50015322 | AO6: =IFERROR(_xlfn.XLOOKUP(確報【６月】!AK6,台帳表ｔ[整理番号],台帳表ｔ[繁閑調整金]),"") -> 482370 | AQ6: {=IFERROR(_xlfn._xlws.FILTER(台帳表ｋ[整理番号], (台帳表ｋ[繁閑調整]<>"")*(CLEAN(台帳表ｋ[入金月（月のみ）])=CLEAN($A$1))*(台帳表ｋ[事務所/分室]=$AQ$5)),"なし")} -> 166 | AR6: =IFERROR(_xlfn.XLOOKUP(確報【６月】!AQ6,台帳表ｋ[整理番号],台帳表ｋ[繁閑調整]),"") -> 設備 | AS6: =IFERROR(_xlfn.XLOOKUP(確報【６月】!AQ6,台帳表ｋ[整理番号],台帳表ｋ[精算 グループ]),"") -> 21 | AT6: =IFERROR(_xlfn.XLOOKUP(確報【６月】!AQ6,台帳表ｋ[整理番号],台帳表ｋ[請求書発行番号]),"") -> 50004694 | AU6: =IFERROR(_xlfn.XLOOKUP(確報【６月】!AQ6,台帳表ｋ[整理番号],台帳表ｋ[繁閑調整金]),"") -> 47291 | AW6: {=IFERROR(_xlfn._xlws.FILTER(台帳表ｋ[整理番号], (台帳表ｋ[繁閑調整]<>"")*(CLEAN(台帳表ｋ[入金月（月のみ）])=CLEAN($A$1))*(台帳表ｋ[事務所/分室]=$AW$5)),"なし")} -> 156 | AX6: =IFERROR(_xlfn.XLOOKUP(確報【６月】!AW6,台帳表ｋ[整理番号],台帳表ｋ[繁閑調整]),"") -> 設備 | AY6: =IFERROR(_xlfn.XLOOKUP(確報【６月】!AW6,台帳表ｋ[整理番号],台帳表ｋ[精算 グループ]),"") -> 21 | AZ6: =IFERROR(_xlfn.XLOOKUP(確報【６月】!AW6,台帳表ｋ[整理番号],台帳表ｋ[請求書発行番号]),"") -> 50003633 | BA6: =IFERROR(_xlfn.XLOOKUP(確報【６月】!AW6,台帳表ｋ[整理番号],台帳表ｋ[繁閑調整金]),"") -> 46678
F7: 供給G | G7: * | H7: 31 | I7: =SUMIFS(台帳表ｓ[金額],台帳表ｓ[精算 グループ],確報【６月】!$H7,台帳表ｓ[入金月（月のみ）],確報【６月】!$A$1,台帳表ｓ[ＮＣ区分],"西部")+SUMIFS(測量台帳1ｓ[入金額],測量台帳1ｓ[精算 グループ],確報【６月】!$H7,測量台帳1ｓ[入金月（月のみ）],確報【６月】!$A$1,測量台帳1ｓ[NC区分],"西部")+SUMIFS(測量台帳1__2ｓ[入金額(後)],測量台帳1__2ｓ[精算 グループ(後)],確報【６月】!$H7,測量台帳1__2ｓ[入金月(後)（月のみ）],確報【６月】!$A$1,測量台帳1__2ｓ[NC区分],"西部") -> 0 | J7: 31 | L7: 31 | N7: 31 | P7: 31 | Q7: =SUMIFS(台帳表ｔ[金額],台帳表ｔ[精算 グループ],確報【６月】!$H7,台帳表ｔ[入金月（月のみ）],確報【６月】!$A$1,台帳表ｔ[ＮＣ区分],"多摩")+SUMIFS(測量台帳1ｔ[入金額],測量台帳1ｔ[精算 グループ],確報【６月】!$H7,測量台帳1ｔ[入金月（月のみ）],確報【６月】!$A$1,測量台帳1ｔ[NC区分],"多摩")+SUMIFS(測量台帳1__2ｔ[入金額(後)],測量台帳1__2ｔ[精算 グループ(後)],確報【６月】!$H7,測量台帳1__2ｔ[入金月(後)（月のみ）],確報【６月】!$A$1,測量台帳1__2ｔ[NC区分],"多摩") -> 0 | R7: 31 | T7: 31 | V7: 31 | W7: {=INDEX(設備G入力用!$F$2:$Q$72,ROW(A3), MATCH($A$1,設備G入力用!$F$2:$Q$2,0))} -> 0 | X7: =SUM(I7,K7,M7,O7,Q7,S7,U7,W7) -> 0 | AB7: 31 | AC7: =SUM(I7,K7,M7,O7,Q7,S7,U7,W7) -> 0 | AF7: =IFERROR(_xlfn.XLOOKUP(確報【６月】!$AE7,台帳表ｓ[整理番号],台帳表ｓ[繁閑調整]),"") | AG7: =IFERROR(_xlfn.XLOOKUP(確報【６月】!$AE7,台帳表ｓ[整理番号],台帳表ｓ[精算 グループ]),"") | AH7: =IFERROR(_xlfn.XLOOKUP(確報【６月】!$AE7,台帳表ｓ[整理番号],台帳表ｓ[請求書発行番号]),"") | AI7: =IFERROR(_xlfn.XLOOKUP(確報【６月】!$AE7,台帳表ｓ[整理番号],台帳表ｓ[繁閑調整金]),"") | AL7: =IFERROR(_xlfn.XLOOKUP(確報【６月】!AK7,台帳表ｔ[整理番号],台帳表ｔ[繁閑調整]),"") | AM7: =IFERROR(_xlfn.XLOOKUP(確報【６月】!AK7,台帳表ｔ[整理番号],台帳表ｔ[精算 グループ]),"") | AN7: =IFERROR(_xlfn.XLOOKUP(確報【６月】!AK7,台帳表ｔ[整理番号],台帳表ｔ[請求書発行番号]),"") | AO7: =IFERROR(_xlfn.XLOOKUP(確報【６月】!AK7,台帳表ｔ[整理番号],台帳表ｔ[繁閑調整金]),"") | AR7: =IFERROR(_xlfn.XLOOKUP(確報【６月】!AQ7,台帳表ｋ[整理番号],台帳表ｋ[繁閑調整]),"") | AS7: =IFERROR(_xlfn.XLOOKUP(確報【６月】!AQ7,台帳表ｋ[整理番号],台帳表ｋ[精算 グループ]),"") | AT7: =IFERROR(_xlfn.XLOOKUP(確報【６月】!AQ7,台帳表ｋ[整理番号],台帳表ｋ[請求書発行番号]),"") | AU7: =IFERROR(_xlfn.XLOOKUP(確報【６月】!AQ7,台帳表ｋ[整理番号],台帳表ｋ[繁閑調整金]),"") | AX7: =IFERROR(_xlfn.XLOOKUP(確報【６月】!AW7,台帳表ｋ[整理番号],台帳表ｋ[繁閑調整]),"") | AY7: =IFERROR(_xlfn.XLOOKUP(確報【６月】!AW7,台帳表ｋ[整理番号],台帳表ｋ[精算 グループ]),"") | AZ7: =IFERROR(_xlfn.XLOOKUP(確報【６月】!AW7,台帳表ｋ[整理番号],台帳表ｋ[請求書発行番号]),"") | BA7: =IFERROR(_xlfn.XLOOKUP(確報【６月】!AW7,台帳表ｋ[整理番号],台帳表ｋ[繁閑調整金]),"")
